Workbook
Name _Hlk109387980: #REF!
Name Query_from_MS_Access_Database_1: 'NON TEACHING STAFF'!$J$5:$CG$246
Name Query_from_MS_Access_Database_1: 'TEACHING STAFF'!$G$4:$BP$177

Sheet TEACHING STAFF
B1: UNIVERSITY OF AFRICA, TORU-ORUA.
B2: STAFF PAYROLL FOR THE MONTH OF FEBRUARY, 2026. | CE2: =#REF! -> #REF!
A3: S/N | B3: NAMES OF STAFF | C3: DEPARTMENT | D3: JOB DESCRIPTION | E3: GRADE NAME | F3: BANK NAME | G3: ACCT NO | H3: ANNUAL SALARY | I3: ANNUAL | J3: OLD BASIC | K3: 25/35% increment | L3: minimum wage | M3: NEW BASIC | N3: EXCESS WORK LOAD | O3: FIELD TRIP | P3: RESPONSIBILITY | Q3: Field Trip | R3: MEDICAL | S3: ARREARS | T3: PERCULIAR | U3: PERSONAL ASSISTANT | V3: LEAVE ALLOWANCE | W3: NEWSPAPER ALLOWANCE | Y3: INDUCEMENT | Z3: GENERAL HAZARD | AA3: OTHER ALLOWS/ADDEDUM | AB3: DOMESTIC STAFF ALLOW. | AC3: Shift | AD3: RESPONSIBILITY ALLOW. | AE3: Entertainment | AF3: Responsibility | AG3: Other Addtions | AI3: SALARY ADVACE | AJ3: ANUPA | AK3: UTILITY BILL | AL3: TOP LIFTER LIMITED | AM3: ASUU | AN3: ASUU WELFARE | AO3: FASTGROW | AP3: FLORIS MULTI PURPOSE | AQ3: FBAS WELFARE | AR3: PERSONAL OWING | AS3: FAE DEUCATION | AT3: BELKARI LOANS | AU3: SCHOOL FEES DEDUCTION | AV3: UAT CRESTED POLO | AW3: FMS WELFARE DEDUCTION | AX3: FSS WELFARE DEDUCTION | AY3: UAT FEMALE FORUM | AZ3: ECONOMICS | BA3: UAT CO-OPERATIVE | BB3: FLORESHINE GLOBAL | BC3: UTILITY BILLS | BD3: UAT RENT | BE3: BSETF | BF3: SCHOOL /HOSTELFEES | BG3: EXTRA DEPENDENT BHIS | BH3: BHIS | BI3: NHF | BJ3: BMUWMPCS | BK3: P.A.Y.E. | BL3: GROSS PAYBEFORE | BM3: TOT DEDUCT | BN3: Sal. advance | BO3: PERCENTAGES | BP3: NET PAY | BQ3: Gosss Earnings | BR3: Personal Allowance | BS3: NHF | BT3: Total Non-Taxable Income | BU3: Total Taxable Income | BV3: Minimum tax | BW3: 1st 300K @ 7% | BX3: next 300k @ 11% | BY3: next 500k @ 15% | BZ3: next 500k @ 19% | CA3: next 1.6m @ 21% | CB3: above 3.2m @ 24% | CC3: Total PAYE | CD3: Min Tax | CE3: Total PAYE Tax | CF3: Monthly PAYE Tax | CG3: 20% Rebate | CH3: ETR | CI3: Current deductions | CJ3: Underpayment (monthly) | CK3: Underpayment (annual) | CN3: REMARK
A4: 1 | B4: ADEMOLA AYODEJI JOLAYEMI | C4: ENGLISH AND LITERARY STUDIES | D4: DEAN, POST-GRADUATE SCHOOL | E4: CONUSS 7/10 | F4: FIRST | G4: 2017212564 | H4: =M4*12 -> 9356702.4 | I4: =M4*12 -> 9356702.4 | J4: 555352 | K4: 194373.2 | L4: 30000 | M4: =SUM(J4:L4) -> 779725.2 | N4: =M4*0.35/3 -> 90967.94 | O4: 8333.33 | P4: =41667 -> 41667 | R4: 2500 | U4: 250000 | Z4: 2500 | AM4: =M4*0.02 -> 15594.504 | AN4: 500 | AP4: 100000 | AS4: 1000 | BA4: 456250 | BC4: 12500 | BD4: 25000 | BE4: 3500 | BF4: 3500 | BH4: =BL4*0.02 -> 23513.869 | BK4: 204399.81 | BL4: =M4+N4+O4+P4+R4+S4+T4+U4+V4+W4+Y4+Z4+AA4+AB4 -> 1175693.5 | BM4: 845758.18 | BP4: =BL4-BM4 -> 329935.29 | BQ4: =BL4*12 -> 14108322 | BR4: =200000+(0.2*BQ4) -> 3021664.3 | BS4: =BI4*12 -> 0 | BT4: =SUM(BR4:BS4) -> 3021664.3 | BU4: =+BQ4-BT4 -> 11086657 | BW4: =IF((BU4>0),(IF((BU4>300000),(300000*7%),(BU4*7%))),(BQ4*1%)) -> 21000 | BX4: =IF((BU4-300000)>0,(IF((BU4>600000),(300000*11%),((BU4-300000)*11%))),("")) -> 33000 | BY4: =IF(((BU4-600000)>0),(IF((BU4>1100000),(500000*15%),((BU4-600000)*15%))),("")) -> 75000 | BZ4: =IF(((BU4-(1100000))>0),(IF((BU4>(1600000)),((500000)*19%),((BU4-(1100000))*19%))),("")) -> 95000 | CA4: =IF(((BU4-(1600000))>0),(IF((BU4>(3200000)),((1600000)*21%),((BU4-(1600000))*21%))),("")) -> 336000 | CB4: =IF(((BU4-(3200000))>0),(IF((BU4>(3200000)),((BU4-(3200000))*24%),(0))),("")) -> 1892797.8 | CC4: =SUM(BW4:CB4) -> 2452797.8 | CD4: =1%*BQ4 -> 141083.22 | CE4: =MAX(CC4:CD4) -> 2452797.8 | CF4: =+CE4/12 -> 204399.81
A5: 2 | B5: SIKOKI FRANCIS DAVID | C5: BIOLOGICAL SCIENCE | D5: DEAN BASIC AND APPLIED SCIENCE (CONTRACT PROFESSOR) | E5: CONUSS 7/10 | F5: ACCESS | G5: 0055002341 | H5: =M5*12 -> 9356702.4 | I5: =M5*12 -> 9356702.4 | J5: 555352 | K5: 194373.2 | L5: 30000 | M5: =SUM(J5:L5) -> 779725.2 | P5: =41667 -> 41667 | R5: 2500 | Z5: 2500 | AM5: =M5*0.02 -> 15594.504 | AN5: 500 | AQ5: 1000 | BC5: 12500 | BD5: 25000 | BE5: 3500 | BF5: 3500 | BH5: =BL5*0.02 -> 16527.844 | BK5: 137333.97 | BL5: =M5+N5+O5+P5+R5+S5+T5+U5+V5+W5+Y5+Z5+AA5 -> 826392.2 | BM5: 215456.32 | BP5: =BL5-BM5 -> 610935.88 | BQ5: =BL5*12 -> 9916706.4 | BR5: =200000+(0.2*BQ5) -> 2183341.3 | BS5: =BI5*12 -> 0 | BT5: =SUM(BR5:BS5) -> 2183341.3 | BU5: =+BQ5-BT5 -> 7733365.1 | BW5: =IF((BU5>0),(IF((BU5>300000),(300000*7%),(BU5*7%))),(BQ5*1%)) -> 21000 | BX5: =IF((BU5-300000)>0,(IF((BU5>600000),(300000*11%),((BU5-300000)*11%))),("")) -> 33000 | BY5: =IF(((BU5-600000)>0),(IF((BU5>1100000),(500000*15%),((BU5-600000)*15%))),("")) -> 75000 | BZ5: =IF(((BU5-(1100000))>0),(IF((BU5>(1600000)),((500000)*19%),((BU5-(1100000))*19%))),("")) -> 95000 | CA5: =IF(((BU5-(1600000))>0),(IF((BU5>(3200000)),((1600000)*21%),((BU5-(1600000))*21%))),("")) -> 336000 | CB5: =IF(((BU5-(3200000))>0),(IF((BU5>(3200000)),((BU5-(3200000))*24%),(0))),("")) -> 1088007.6 | CC5: =SUM(BW5:CB5) -> 1648007.6 | CD5: =1%*BQ5 -> 99167.064 | CE5: =MAX(CC5:CD5) -> 1648007.6 | CF5: =+CE5/12 -> 137333.97
A6: 3 | B6: ABUMERE OAMEN ERONMOSELE | C6: ='[1]TEACHING STAFF'!$D$6 -> PHYSICS | D6: CONTRACT APPOINTMENT | E6: CONUSS 7/10 | F6: ECOBANK | G6: 0072045836 | J6: 555352 | K6: 194373.2 | L6: 30000 | M6: =SUM(J6:L6) -> 779725.2 | P6: 20833.33 | R6: 2500 | Z6: 2500 | AM6: =M6*0.02 -> 15594.504 | AN6: 500 | AQ6: 1000 | BC6: 4166.67 | BD6: ='[1]TEACHING STAFF'!$AS$6 -> 8333.33 | BE6: 3500 | BF6: 3500 | BH6: =BL6*0.02 -> 16111.171 | BK6: 133333.9 | BL6: =M6+N6+O6+P6+R6+S6+T6+U6+V6+W6+Y6+Z6+AA6 -> 805558.53 | BM6: =BK6+BH6+BE6+BD6+BC6+AQ6+AN6+AM6 -> 182539.57 | BP6: =BL6-BM6 -> 623018.96
A7: 4 | B7: DONBEBE WANKASI | C7: CHEMICAL SCIENCES | D7: ADJUNCT PROFESSOR | E7: CONUSS 7/3 | F7: ACCESS | G7: 0026574605 | H7: =M7*12 -> 3843072.5 | J7: 319245.33 | K7: 45673.005 | L7: 15000 | M7: 320256.04 | R7: 2500 | Z7: 2500 | AC7: 0 | AM7: =M7*0.02 -> 6405.1208 | AN7: 500 | AQ7: 1000 | BE7: 1750 | BH7: =BL7*0.02 -> 6505.1208 | BK7: 41809.681 | BL7: =M7+N7+O7+P7+R7+S7+T7+U7+V7+W7+Y7+Z7+AA7 -> 325256.04 | BM7: =AI7+AJ7+AK7+AL7+AM7+AN7+AP7++AQ7+AR7+AS7+AT7+AU7+AV7+AW7+AX7+AY7+AZ7+BA7+BB7+BC7+BD7+BE7+BG7+BH7+BK7 -> 57969.923 | BP7: =BL7-BM7 -> 267286.12 | BQ7: =BL7*12 -> 3903072.5 | BR7: =200000+(0.2*BQ7) -> 980614.5 | BS7: =BI7*12 -> 0 | BT7: =SUM(BR7:BS7) -> 980614.5 | BU7: =+BQ7-BT7 -> 2922458 | BW7: =IF((BU7>0),(IF((BU7>300000),(300000*7%),(BU7*7%))),(BQ7*1%)) -> 21000 | BX7: =IF((BU7-300000)>0,(IF((BU7>600000),(300000*11%),((BU7-300000)*11%))),("")) -> 33000 | BY7: =IF(((BU7-600000)>0),(IF((BU7>1100000),(500000*15%),((BU7-600000)*15%))),("")) -> 75000 | BZ7: =IF(((BU7-(1100000))>0),(IF((BU7>(1600000)),((500000)*19%),((BU7-(1100000))*19%))),("")) -> 95000 | CA7: =IF(((BU7-(1600000))>0),(IF((BU7>(3200000)),((1600000)*21%),((BU7-(1600000))*21%))),("")) -> 277716.18 | CB7: =IF(((BU7-(3200000))>0),(IF((BU7>(3200000)),((BU7-(3200000))*24%),(0))),("")) | CC7: =SUM(BW7:CB7) -> 501716.18 | CD7: =1%*BQ7 -> 39030.725 | CE7: =MAX(CC7:CD7) -> 501716.18 | CF7: =BK7 -> 41809.681 | CN7: ADJUNCT EXPIRES WITH THE 2025/2026 ACADEMIC SESSION
A8: 5 | B8: CHINYERE P. ONONUGBO | C8: PHYSICS | D8: ADJUNCT PROFESSOR | E8: CONUAS 7/3 | F8: UBA | G8: 2088596893 | M8: =640512.08/2 -> 320256.04 | R8: 2500 | Z8: 2500 | AC8: 0 | AM8: =M8*0.02 -> 6405.1208 | AN8: 500 | AQ8: 1000 | BE8: 1750 | BH8: =BL8*0.02 -> 6505.1208 | BK8: 41809.681 | BL8: =M8+N8+O8+P8+R8+S8+T8+U8+V8+W8+Y8+Z8+AA8 -> 325256.04 | BM8: =AI8+AJ8+AK8+AL8+AM8+AN8+AP8++AQ8+AR8+AS8+AT8+AU8+AV8+AW8+AX8+AY8+AZ8+BA8+BB8+BC8+BD8+BE8+BG8+BH8+BK8 -> 57969.923 | BP8: =BL8-BM8 -> 267286.12 | CN8: ADJUNCT EXPIRES WITH THE 2025/2026 ACADEMIC SESSION
A9: 6 | B9: DANIEL I. OLORUNFEMI | C9: BIOLOGICAL SCIENCE | D9: ADJUNCT PROFESSOR | E9: CONUAS 7/9 | F9: ACCESS | G9: 0030621811 | H9: =M9*12 -> 4559020 | J9: 319245.33 | K9: 45673.005 | L9: 15000 | M9: =SUM(J9:L9) -> 379918.34 | R9: 2500 | Z9: 2500 | AC9: 0 | AM9: =M9*0.02 -> 7598.3667 | AN9: 500 | AQ9: 1000 | BE9: 1750 | BH9: =BL9*0.02 -> 7698.3667 | BK9: 52570.987 | BL9: =M9+N9+O9+P9+R9+S9+T9+U9+V9+W9+Y9+Z9+AA9 -> 384918.34 | BM9: =AI9+AJ9+AK9+AL9+AM9+AN9+AP9++AQ9+AR9+AS9+AT9+AU9+AV9+AW9+AX9+AY9+AZ9+BA9+BB9+BC9+BD9+BE9+BG9+BH9+BK9 -> 71117.72 | BP9: =BL9-BM9 -> 313800.61 | CN9: ADJUNCT EXPIRES WITH THE 2025/2026 ACADEMIC SESSION
A10: 7 | B10: OKOROBIA MARK ATEI | C10: HISTORY AND INTERNATIONAL STUDIES | D10: ADJUNCT PROFESSOR | E10: CONUSS 7/10 | F10: UBA | G10: 1006415522 | J10: 277675.58 | K10: 97186.454 | L10: 15000 | M10: =SUM(J10:L10) -> 389862.04 | R10: 2500 | Z10: 2500 | AC10: 0 | AM10: =M10*0.02 -> 7797.2407 | AN10: 500 | AO10: 0 | AS10: 1000 | BE10: 1750 | BH10: =BL10*0.02 -> 7897.2407 | BK10: 54480.178 | BL10: =M10+N10+O10+P10+R10+S10+T10+U10+V10+W10+Y10+Z10+AA10 -> 394862.04 | BM10: =AI10+AJ10+AK10+AL10+AM10+AN10+AP10++AQ10+AR10+AS10+AT10+AU10+AV10+AW10+AX10+AY10+AZ10+BA10+BB10+BC10+BD10+BE10+BG10+BH10+BK10 -> 73424.659 | BP10: =BL10-BM10 -> 321437.38 | BQ10: =BM10-BN10 -> 73424.659 | CN10: ADJUNCT EXPIRES WITH THE 2025/2026 ACADEMIC SESSION
A11: 8 | B11: EBISEITEI PRECIOUS | C11: BIOLOGICAL SCIENCE | D11: SENIOR LECTURER | E11: CONUSSS 5/3 | F11: STANBIC IBTC | G11: 0035529328 | H11: 2425322 | I11: 2688069 | J11: 224005.75 | K11: 56001.438 | L11: 30000 | M11: 413255.25 | N11: =M11*0.35/3 -> 48213.113 | O11: 5000 | P11: 41667 | R11: 2500 | Z11: 2500 | AM11: =M11*0.02 -> 8265.105 | AN11: 500 | AQ11: 1000 | AV11: 5000 | BE11: 1500 | BH11: =BL11*0.02 -> 10262.707 | BK11: 77188.66 | BL11: =M11+N11+O11+P11+R11+S11+T11+U11+V11+W11+Y11+Z11+AA11 -> 513135.36 | BM11: =AI11+AJ11+AK11+AL11+AM11+AN11+AP11++AQ11+AR11+AS11+AT11+AU11+AV11+AW11+AX11+AY11+AZ11+BA11+BB11+BC11+BD11+BE11+BG11+BH11+BK11 -> 103716.47 | BP11: =BL11-BM11 -> 409418.89 | BQ11: =BL11*12 -> 6157624.3 | BR11: =200000+(0.2*BQ11) -> 1431524.9 | BS11: =BI11*12 -> 0 | BT11: =SUM(BR11:BS11) -> 1431524.9 | BU11: =+BQ11-BT11 -> 4726099.5 | BW11: =IF((BU11>0),(IF((BU11>300000),(300000*7%),(BU11*7%))),(BQ11*1%)) -> 21000 | BX11: =IF((BU11-300000)>0,(IF((BU11>600000),(300000*11%),((BU11-300000)*11%))),("")) -> 33000 | BY11: =IF(((BU11-600000)>0),(IF((BU11>1100000),(500000*15%),((BU11-600000)*15%))),("")) -> 75000 | BZ11: =IF(((BU11-(1100000))>0),(IF((BU11>(1600000)),((500000)*19%),((BU11-(1100000))*19%))),("")) -> 95000 | CA11: =IF(((BU11-(1600000))>0),(IF((BU11>(3200000)),((1600000)*21%),((BU11-(1600000))*21%))),("")) -> 336000 | CB11: =IF(((BU11-(3200000))>0),(IF((BU11>(3200000)),((BU11-(3200000))*24%),(0))),("")) -> 366263.88 | CC11: =SUM(BW11:CB11) -> 926263.88 | CD11: =1%*BQ11 -> 61576.243 | CE11: =MAX(CC11:CD11) -> 926263.88 | CF11: =+CE11/12 -> 77188.656
A12: 9 | B12: ZIAKEDE SOLOMON KOROYE | C12: PHYSICS | D12: LECTURER II | E12: CONUASS 3/6 | F12: GTB | G12: 0237212657 | H12: 2048214 | I12: 2144788 | J12: 178732.33 | K12: 44683.083 | L12: 30000 | M12: 259114.17 | N12: =M12*0.35/3 -> 30229.986 | O12: 5000 | R12: 2500 | Z12: 2500 | AM12: =M12*0.02 -> 5182.2834 | AN12: 500 | AQ12: 1000 | BA12: 5000 | BE12: 1000 | BH12: =BL12*0.02 -> 5986.8831 | BK12: 37456.48 | BL12: =M12+N12+O12+P12+R12+S12+T12+U12+V12+W12+Y12+Z12+AA12 -> 299344.16 | BM12: =AI12+AJ12+AK12+AL12+AM12+AN12+AP12++AQ12+AR12+AS12+AT12+AU12+AV12+AW12+AX12+AY12+AZ12+BA12+BB12+BC12+BD12+BE12+BG12+BH12+BK12 -> 56125.647 | BP12: =BL12-BM12 -> 243218.51 | BQ12: =BL12*12 -> 3592129.9 | BR12: =200000+(0.2*BQ12) -> 918425.98 | BS12: =BI12*12 -> 0 | BT12: =SUM(BR12:BS12) -> 918425.98 | BU12: =+BQ12-BT12 -> 2673703.9 | BW12: =IF((BU12>0),(IF((BU12>300000),(300000*7%),(BU12*7%))),(BQ12*1%)) -> 21000 | BX12: =IF((BU12-300000)>0,(IF((BU12>600000),(300000*11%),((BU12-300000)*11%))),("")) -> 33000 | BY12: =IF(((BU12-600000)>0),(IF((BU12>1100000),(500000*15%),((BU12-600000)*15%))),("")) -> 75000 | BZ12: =IF(((BU12-(1100000))>0),(IF((BU12>(1600000)),((500000)*19%),((BU12-(1100000))*19%))),("")) -> 95000 | CA12: =IF(((BU12-(1600000))>0),(IF((BU12>(3200000)),((1600000)*21%),((BU12-(1600000))*21%))),("")) -> 225477.82 | CB12: =IF(((BU12-(3200000))>0),(IF((BU12>(3200000)),((BU12-(3200000))*24%),(0))),("")) | CC12: =SUM(BW12:CB12) -> 449477.82 | CD12: =1%*BQ12 -> 35921.299 | CE12: =MAX(CC12:CD12) -> 449477.82 | CF12: =+CE12/12 -> 37456.485
A13: 10 | B13: DEINGIMO KEME | C13: BIOLOGICAL SCIENCE | D13: LECTURER I | E13: CONUASS 4/3 | F13: UBA | G13: 2067246166 | H13: 2308911 | I13: 2048214 | J13: 192409.25 | K13: 48102.312 | L13: 30000 | M13: 319130.33 | N13: =M13*0.35/3 -> 37231.872 | O13: 5000 | R13: 2500 | Z13: 2500 | AM13: =M13*0.02 -> 6382.6066 | AN13: 500 | AP13: 21000 | AQ13: 1000 | BA13: 0 | BE13: 1500 | BH13: =BL13*0.02 -> 7327.244 | BK13: 49008.21 | BL13: =M13+N13+O13+P13+R13+S13+T13+U13+V13+W13+Y13+Z13+AA13 -> 366362.2 | BM13: =AI13+AJ13+AK13+AL13+AM13+AN13+AP13++AQ13+AR13+AS13+AT13+AU13+AV13+AW13+AX13+AY13+AZ13+BA13+BB13+BC13+BD13+BE13+BG13+BH13+BK13 -> 86718.061 | BP13: =BL13-BM13 -> 279644.14 | BQ13: =BL13*12 -> 4396346.4 | BR13: =200000+(0.2*BQ13) -> 1079269.3 | BS13: =BI13*12 -> 0 | BT13: =SUM(BR13:BS13) -> 1079269.3 | BU13: =+BQ13-BT13 -> 3317077.1 | BW13: =IF((BU13>0),(IF((BU13>300000),(300000*7%),(BU13*7%))),(BQ13*1%)) -> 21000 | BX13: =IF((BU13-300000)>0,(IF((BU13>600000),(300000*11%),((BU13-300000)*11%))),("")) -> 33000 | BY13: =IF(((BU13-600000)>0),(IF((BU13>1100000),(500000*15%),((BU13-600000)*15%))),("")) -> 75000 | BZ13: =IF(((BU13-(1100000))>0),(IF((BU13>(1600000)),((500000)*19%),((BU13-(1100000))*19%))),("")) -> 95000 | CA13: =IF(((BU13-(1600000))>0),(IF((BU13>(3200000)),((1600000)*21%),((BU13-(1600000))*21%))),("")) -> 336000 | CB13: =IF(((BU13-(3200000))>0),(IF((BU13>(3200000)),((BU13-(3200000))*24%),(0))),("")) -> 28098.513 | CC13: =SUM(BW13:CB13) -> 588098.51 | CD13: =1%*BQ13 -> 43963.464 | CE13: =MAX(CC13:CD13) -> 588098.51 | CF13: =+CE13/12 -> 49008.209
A14: 11 | B14: TARIEBIBO ENAI GEDE | C14: MATHEMATICS AND COMPUTER SCIENCE | D14: LECTURER I | E14: CONUASS 4/6 | F14: STERLING | G14: 0077840928 | H14: 2688069 | I14: 2775651 | J14: 231304.25 | K14: 57826.062 | L14: 30000 | M14: 328253.42 | N14: =M14*0.35/3 -> 38296.232 | O14: 5000 | R14: 2500 | Z14: 2500 | AM14: =M14*0.02 -> 6565.0684 | AN14: 500 | AQ14: 1000 | BA14: 19333.33 | BE14: 1500 | BH14: =BL14*0.02 -> 7530.993 | BK14: 50964.2 | BL14: =M14+N14+O14+P14+R14+S14+T14+U14+V14+W14+Y14+Z14+AA14 -> 376549.65 | BM14: =AI14+AJ14+AK14+AL14+AM14+AN14+AP14++AQ14+AR14+AS14+AT14+AU14+AV14+AW14+AX14+AY14+AZ14+BA14+BB14+BC14+BD14+BE14+BG14+BH14+BK14 -> 87393.591 | BP14: =BL14-BM14 -> 289156.06 | BQ14: =BL14*12 -> 4518595.8 | BR14: =200000+(0.2*BQ14) -> 1103719.2 | BS14: =BI14*12 -> 0 | BT14: =SUM(BR14:BS14) -> 1103719.2 | BU14: =+BQ14-BT14 -> 3414876.7 | BW14: =IF((BU14>0),(IF((BU14>300000),(300000*7%),(BU14*7%))),(BQ14*1%)) -> 21000 | BX14: =IF((BU14-300000)>0,(IF((BU14>600000),(300000*11%),((BU14-300000)*11%))),("")) -> 33000 | BY14: =IF(((BU14-600000)>0),(IF((BU14>1100000),(500000*15%),((BU14-600000)*15%))),("")) -> 75000 | BZ14: =IF(((BU14-(1100000))>0),(IF((BU14>(1600000)),((500000)*19%),((BU14-(1100000))*19%))),("")) -> 95000 | CA14: =IF(((BU14-(1600000))>0),(IF((BU14>(3200000)),((1600000)*21%),((BU14-(1600000))*21%))),("")) -> 336000 | CB14: =IF(((BU14-(3200000))>0),(IF((BU14>(3200000)),((BU14-(3200000))*24%),(0))),("")) -> 51570.399 | CC14: =SUM(BW14:CB14) -> 611570.4 | CD14: =1%*BQ14 -> 45185.958 | CE14: =MAX(CC14:CD14) -> 611570.4 | CF14: =+CE14/12 -> 50964.2
A15: 12 | B15: LAWAL BABATUNDE YUSUF | C15: PHYSICS | D15: ASSOCIATE PROFESSOR | E15: CONUAS 6/1 | F15: STERLING | G15: 0071870439 | H15: 3588849 | I15: 3679250 | J15: 306604.17 | K15: 76651.042 | L15: 30000 | M15: 464981 | N15: =M15*0.35/3 -> 54247.783 | O15: 5000 | R15: 2500 | Z15: 2500 | AM15: =M15*0.02 -> 9299.62 | AN15: 500 | AP15: 101667 | AQ15: 1000 | BA15: 85000 | BC15: 7500 | BD15: 15000 | BE15: 2000 | BH15: =BL15*0.02 -> 10584.576 | BK15: 80278.59 | BL15: =M15+N15+O15+P15+R15+S15+T15+U15+V15+W15+Y15+Z15+AA15 -> 529228.78 | BM15: =AI15+AJ15+AK15+AL15+AM15+AN15+AP15++AQ15+AR15+AS15+AT15+AU15+AV15+AW15+AX15+AY15+AZ15+BA15+BB15+BC15+BD15+BE15+BG15+BH15+BK15 -> 312829.79 | BP15: =BL15-BM15 -> 216399 | BQ15: =BL15*12 -> 6350745.4 | BR15: =200000+(0.2*BQ15) -> 1470149.1 | BS15: =BI15*12 -> 0 | BT15: =SUM(BR15:BS15) -> 1470149.1 | BU15: =+BQ15-BT15 -> 4880596.3 | BW15: =IF((BU15>0),(IF((BU15>300000),(300000*7%),(BU15*7%))),(BQ15*1%)) -> 21000 | BX15: =IF((BU15-300000)>0,(IF((BU15>600000),(300000*11%),((BU15-300000)*11%))),("")) -> 33000 | BY15: =IF(((BU15-600000)>0),(IF((BU15>1100000),(500000*15%),((BU15-600000)*15%))),("")) -> 75000 | BZ15: =IF(((BU15-(1100000))>0),(IF((BU15>(1600000)),((500000)*19%),((BU15-(1100000))*19%))),("")) -> 95000 | CA15: =IF(((BU15-(1600000))>0),(IF((BU15>(3200000)),((1600000)*21%),((BU15-(1600000))*21%))),("")) -> 336000 | CB15: =IF(((BU15-(3200000))>0),(IF((BU15>(3200000)),((BU15-(3200000))*24%),(0))),("")) -> 403343.12 | CC15: =SUM(BW15:CB15) -> 963343.12 | CD15: =1%*BQ15 -> 63507.454 | CE15: =MAX(CC15:CD15) -> 963343.12 | CF15: =+CE15/12 -> 80278.593
A16: 13 | B16: NEIN GODKNOWS | C16: INDUSTRAL RELATION AND PERSONAL MGT | D16: SENIOR LECTURER | E16: CONUAS 5/9 | F16: UNION | G16: 0029213035 | I16: 4307259 | J16: 358938.25 | K16: 89734.562 | L16: 30000 | M16: 491756.42 | N16: =M16*0.35/3 -> 57371.582 | O16: 5000 | P16: =P17 -> 20833.33 | R16: 2500 | Z16: 2500 | AM16: =M16*0.02 -> 9835.1284 | AN16: 500 | AV16: 5000 | AW16: 1000 | AX16: 1000 | BA16: 0 | BE16: 2000 | BH16: =BL16*0.02 -> 11599.227 | BK16: 90019.24 | BL16: =M16+N16+O16+P16+R16+S16+T16+U16+V16+W16+Y16+Z16+AA16 -> 579961.33 | BM16: =AI16+AJ16+AK16+AL16+AM16+AN16+AP16++AQ16+AR16+AS16+AT16+AU16+AV16+AW16+AX16+AY16+AZ16+BA16+BB16+BC16+BD16+BE16+BG16+BH16+BK16 -> 120953.6 | BP16: =BL16-BM16 -> 459007.74 | BQ16: =BL16*12 -> 6959536 | BR16: =200000+(0.2*BQ16) -> 1591907.2 | BS16: =BI16*12 -> 0 | BT16: =SUM(BR16:BS16) -> 1591907.2 | BU16: =+BQ16-BT16 -> 5367628.8 | BW16: =IF((BU16>0),(IF((BU16>300000),(300000*7%),(BU16*7%))),(BQ16*1%)) -> 21000 | BX16: =IF((BU16-300000)>0,(IF((BU16>600000),(300000*11%),((BU16-300000)*11%))),("")) -> 33000 | BY16: =IF(((BU16-600000)>0),(IF((BU16>1100000),(500000*15%),((BU16-600000)*15%))),("")) -> 75000 | BZ16: =IF(((BU16-(1100000))>0),(IF((BU16>(1600000)),((500000)*19%),((BU16-(1100000))*19%))),("")) -> 95000 | CA16: =IF(((BU16-(1600000))>0),(IF((BU16>(3200000)),((1600000)*21%),((BU16-(1600000))*21%))),("")) -> 336000 | CB16: =IF(((BU16-(3200000))>0),(IF((BU16>(3200000)),((BU16-(3200000))*24%),(0))),("")) -> 520230.91 | CC16: =SUM(BW16:CB16) -> 1080230.9 | CD16: =1%*BQ16 -> 69595.36 | CE16: =MAX(CC16:CD16) -> 1080230.9 | CF16: =+CE16/12 -> 90019.242
A17: 14 | B17: ECHETA O SYDNEY | C17: HOTEL MANAGEMENT AND TOURISM | D17: SENIOR LECTURER | E17: CONUASS 5/4 | F17: FIRST | G17: 3013002388 | H17: 3588849 | I17: 3679250 | J17: 306604.17 | K17: 76651.042 | L17: 30000 | M17: 426338.75 | N17: =M17*0.35/3 -> 49739.521 | O17: 5000 | P17: 20833.33 | R17: 2500 | Z17: 2500 | AM17: =M17*0.02 -> 8526.775 | AN17: 500 | AW17: 1000 | BA17: 0 | BC17: 3750 | BD17: 7500 | BE17: 2000 | BH17: =BL17*0.02 -> 10138.232 | BK17: 75993.694 | BL17: =M17+N17+O17+P17+R17+S17+T17+U17+V17+W17+Y17+Z17+AA17 -> 506911.6 | BM17: =AI17+AJ17+AK17+AL17+AM17+AN17+AP17++AQ17+AR17+AS17+AT17+AU17+AV17+AW17+AX17+AY17+AZ17+BA17+BB17+BC17+BD17+BE17+BG17+BH17+BK17 -> 109408.7 | BP17: =BL17-BM17 -> 397502.9 | CF17: =+CE17/12 -> 0
A18: 15 | B18: OGBUTA ANTHONY ANWULI | C18: CHEMICAL SCIENCES | D18: LECTURER I | E18: CONUAS 4/6 | F18: FIRST | G18: 3041696126 | H18: 2688069 | I18: 2775651 | J18: 231304.25 | K18: 57826.062 | L18: 30000 | M18: 328253.42 | N18: =M18*0.35/3 -> 38296.232 | O18: 5000 | R18: 2500 | Z18: 2500 | AM18: =M18*0.02 -> 6565.0684 | AN18: 500 | AQ18: 1000 | BA18: 10000 | BC18: 5000 | BD18: 10000 | BE18: 1500 | BF18: 2000 | BH18: =BL18*0.02 -> 7530.993 | BK18: 50964.2 | BL18: =M18+N18+O18+P18+R18+S18+T18+U18+V18+W18+Y18+Z18+AA18 -> 376549.65 | BM18: =BK18+BH18+BE18+BD18+BC18+BA18+AQ18+AN18+AM18 -> 93060.261 | BP18: =BL18-BM18 -> 283489.39 | BQ18: =BL18*12 -> 4518595.8 | BR18: =200000+(0.2*BQ18) -> 1103719.2 | BS18: =BI18*12 -> 0 | BT18: =SUM(BR18:BS18) -> 1103719.2 | BU18: =+BQ18-BT18 -> 3414876.7 | BW18: =IF((BU18>0),(IF((BU18>300000),(300000*7%),(BU18*7%))),(BQ18*1%)) -> 21000 | BX18: =IF((BU18-300000)>0,(IF((BU18>600000),(300000*11%),((BU18-300000)*11%))),("")) -> 33000 | BY18: =IF(((BU18-600000)>0),(IF((BU18>1100000),(500000*15%),((BU18-600000)*15%))),("")) -> 75000 | BZ18: =IF(((BU18-(1100000))>0),(IF((BU18>(1600000)),((500000)*19%),((BU18-(1100000))*19%))),("")) -> 95000 | CA18: =IF(((BU18-(1600000))>0),(IF((BU18>(3200000)),((1600000)*21%),((BU18-(1600000))*21%))),("")) -> 336000 | CB18: =IF(((BU18-(3200000))>0),(IF((BU18>(3200000)),((BU18-(3200000))*24%),(0))),("")) -> 51570.399 | CC18: =SUM(BW18:CB18) -> 611570.4 | CD18: =1%*BQ18 -> 45185.958 | CE18: =MAX(CC18:CD18) -> 611570.4 | CF18: =+CE18/12 -> 50964.2
A19: 16 | B19: WAIDOR KEITH TAMARAEBI | C19: MATHEMATICS AND COMPUTER SCIENCE | D19: LECTURER I | E19: CONUASS 4/8 | F19: WEMA | G19: 0227351994 | H19: 2863233 | I19: 2950816 | J19: 245901.33 | K19: 61475.333 | L19: 30000 | M19: 346499.83 | N19: =M19*0.35/3 -> 40424.98 | O19: 5000 | R19: 2500 | Z19: 2500 | AM19: =M19*0.02 -> 6929.9966 | AN19: 500 | AQ19: 1000 | BA19: 0 | BC19: 7500 | BD19: 15000 | BE19: 1500 | BH19: =BL19*0.02 -> 7938.4962 | BK19: 54876.23 | BL19: =M19+N19+O19+P19+R19+S19+T19+U19+V19+W19+Y19+Z19+AA19 -> 396924.81 | BM19: =AI19+AJ19+AK19+AL19+AM19+AN19+AP19++AQ19+AR19+AS19+AT19+AU19+AV19+AW19+AX19+AY19+AZ19+BA19+BB19+BC19+BD19+BE19+BG19+BH19+BK19 -> 95244.723 | BP19: =BL19-BM19 -> 301680.09 | BQ19: =BL19*12 -> 4763097.7 | BR19: =200000+(0.2*BQ19) -> 1152619.5 | BS19: =BI19*12 -> 0 | BT19: =SUM(BR19:BS19) -> 1152619.5 | BU19: =+BQ19-BT19 -> 3610478.2 | BW19: =IF((BU19>0),(IF((BU19>300000),(300000*7%),(BU19*7%))),(BQ19*1%)) -> 21000 | BX19: =IF((BU19-300000)>0,(IF((BU19>600000),(300000*11%),((BU19-300000)*11%))),("")) -> 33000 | BY19: =IF(((BU19-600000)>0),(IF((BU19>1100000),(500000*15%),((BU19-600000)*15%))),("")) -> 75000 | BZ19: =IF(((BU19-(1100000))>0),(IF((BU19>(1600000)),((500000)*19%),((BU19-(1100000))*19%))),("")) -> 95000 | CA19: =IF(((BU19-(1600000))>0),(IF((BU19>(3200000)),((1600000)*21%),((BU19-(1600000))*21%))),("")) -> 336000 | CB19: =IF(((BU19-(3200000))>0),(IF((BU19>(3200000)),((BU19-(3200000))*24%),(0))),("")) -> 98514.763 | CC19: =SUM(BW19:CB19) -> 658514.76 | CD19: =1%*BQ19 -> 47630.977 | CE19: =MAX(CC19:CD19) -> 658514.76 | CF19: =+CE19/12 -> 54876.23
A20: 17 | B20: ODUBO CHARITY TAMARAUEBI | C20: ACCOUNTING | D20: LECTURER I | E20: CONUASS 4/4 | F20: STANBIC IBTC | G20: 0019236855 | H20: 2199496 | I20: 2600486 | J20: 216707.17 | K20: 54176.792 | L20: 30000 | M20: 310007.17 | N20: =M20*0.35/3 -> 36167.503 | O20: 5000 | R20: 2500 | Z20: 2500 | AM20: =M20*0.02 -> 6200.1434 | AN20: 500 | AW20: 1000 | AY20: 2000 | BA20: 33339.29 | BE20: 1500 | BH20: =BL20*0.02 -> 7123.4935 | BK20: 47052.2 | BL20: =M20+N20+O20+P20+R20+S20+T20+U20+V20+W20+Y20+Z20+AA20 -> 356174.67 | BM20: =AI20+AJ20+AK20+AL20+AM20+AN20+AP20++AQ20+AR20+AS20+AT20+AU20+AV20+AW20+AX20+AY20+AZ20+BA20+BB20+BC20+BD20+BE20+BG20+BH20+BK20 -> 98715.127 | BP20: =BL20-BM20 -> 257459.55 | BQ20: =BL20*12 -> 4274096.1 | BR20: =200000+(0.2*BQ20) -> 1054819.2 | BS20: =BI20*12 -> 0 | BT20: =SUM(BR20:BS20) -> 1054819.2 | BU20: =+BQ20-BT20 -> 3219276.9 | BW20: =IF((BU20>0),(IF((BU20>300000),(300000*7%),(BU20*7%))),(BQ20*1%)) -> 21000 | BX20: =IF((BU20-300000)>0,(IF((BU20>600000),(300000*11%),((BU20-300000)*11%))),("")) -> 33000 | BY20: =IF(((BU20-600000)>0),(IF((BU20>1100000),(500000*15%),((BU20-600000)*15%))),("")) -> 75000 | BZ20: =IF(((BU20-(1100000))>0),(IF((BU20>(1600000)),((500000)*19%),((BU20-(1100000))*19%))),("")) -> 95000 | CA20: =IF(((BU20-(1600000))>0),(IF((BU20>(3200000)),((1600000)*21%),((BU20-(1600000))*21%))),("")) -> 336000 | CB20: =IF(((BU20-(3200000))>0),(IF((BU20>(3200000)),((BU20-(3200000))*24%),(0))),("")) -> 4626.447 | CC20: =SUM(BW20:CB20) -> 564626.45 | CD20: =1%*BQ20 -> 42740.961 | CE20: =MAX(CC20:CD20) -> 564626.45 | CF20: =+CE20/12 -> 47052.204
A21: 18 | B21: OLADIPO ABOSEDE MOJISOLA | C21: AGRICULTURAL ECONOMICS AND EXTENSION | D21: LECTURER I | E21: CONUASS 4/6 | F21: ZENITH | G21: 2178561969 | H21: =#REF! -> #REF! | I21: 2775651 | J21: 231304.25 | K21: 57826.062 | L21: 30000 | M21: 328253.42 | N21: =M21*0.35/3 -> 38296.232 | O21: 5000 | R21: 2500 | Z21: 2500 | AM21: =M21*0.02 -> 6565.0684 | AN21: 500 | AY21: 2000 | BA21: 0 | BC21: 5000 | BD21: 10000 | BE21: 1500 | BH21: =BL21*0.02 -> 7530.993 | BK21: 50964.2 | BL21: =M21+N21+O21+P21+R21+S21+T21+U21+V21+W21+Y21+Z21+AA21 -> 376549.65 | BM21: =AI21+AJ21+AK21+AL21+AM21+AN21+AP21++AQ21+AR21+AS21+AT21+AU21+AV21+AW21+AX21+AY21+AZ21+BA21+BB21+BC21+BD21+BE21+BG21+BH21+BK21 -> 84060.261 | BP21: =BL21-BM21 -> 292489.39 | BQ21: =BL21*12 -> 4518595.8 | BR21: =200000+(0.2*BQ21) -> 1103719.2 | BS21: =BI21*12 -> 0 | BT21: =SUM(BR21:BS21) -> 1103719.2 | BU21: =+BQ21-BT21 -> 3414876.7 | BW21: =IF((BU21>0),(IF((BU21>300000),(300000*7%),(BU21*7%))),(BQ21*1%)) -> 21000 | BX21: =IF((BU21-300000)>0,(IF((BU21>600000),(300000*11%),((BU21-300000)*11%))),("")) -> 33000 | BY21: =IF(((BU21-600000)>0),(IF((BU21>1100000),(500000*15%),((BU21-600000)*15%))),("")) -> 75000 | BZ21: =IF(((BU21-(1100000))>0),(IF((BU21>(1600000)),((500000)*19%),((BU21-(1100000))*19%))),("")) -> 95000 | CA21: =IF(((BU21-(1600000))>0),(IF((BU21>(3200000)),((1600000)*21%),((BU21-(1600000))*21%))),("")) -> 336000 | CB21: =IF(((BU21-(3200000))>0),(IF((BU21>(3200000)),((BU21-(3200000))*24%),(0))),("")) -> 51570.399 | CC21: =SUM(BW21:CB21) -> 611570.4 | CD21: =1%*BQ21 -> 45185.958 | CE21: =MAX(CC21:CD21) -> 611570.4 | CF21: =+CE21/12 -> 50964.2
A22: 19 | B22: BOLOUPREMO TARILA | C22: BANKING AND FINANCE | D22: ASSOCIATE PROFESSOR | E22: CONUASS 6/1 | F22: STERLING | G22: 0077210321 | H22: 2775651 | I22: 3428047 | J22: 285670.58 | K22: 71417.646 | L22: 30000 | M22: 464981 | N22: =M22*0.35/3 -> 54247.783 | O22: 5000 | P22: 20833.33 | R22: 2500 | Z22: 2500 | AA22: 30000 | AM22: =M22*0.02 -> 9299.62 | AN22: 500 | AP22: 21000 | AW22: 1000 | BA22: 97947 | BE22: 1500 | BG22: =1250*2 -> 2500 | BH22: =BL22*0.02 -> 11601.242 | BK22: 90038.59 | BL22: =M22+N22+O22+P22+R22+S22+T22+U22+V22+W22+Y22+Z22+AA22 -> 580062.11 | BM22: =AI22+AJ22+AK22+AL22+AM22+AN22+AP22++AQ22+AR22+AS22+AT22+AU22+AV22+AW22+AX22+AY22+AZ22+BA22+BB22+BC22+BD22+BE22+BG22+BH22+BK22 -> 235386.45 | BP22: =BL22-BM22 -> 344675.66 | BQ22: =BL22*12 -> 6960745.4 | BR22: =200000+(0.2*BQ22) -> 1592149.1 | BS22: =BI22*12 -> 0 | BT22: =SUM(BR22:BS22) -> 1592149.1 | BU22: =+BQ22-BT22 -> 5368596.3 | BW22: =IF((BU22>0),(IF((BU22>300000),(300000*7%),(BU22*7%))),(BQ22*1%)) -> 21000 | BX22: =IF((BU22-300000)>0,(IF((BU22>600000),(300000*11%),((BU22-300000)*11%))),("")) -> 33000 | BY22: =IF(((BU22-600000)>0),(IF((BU22>1100000),(500000*15%),((BU22-600000)*15%))),("")) -> 75000 | BZ22: =IF(((BU22-(1100000))>0),(IF((BU22>(1600000)),((500000)*19%),((BU22-(1100000))*19%))),("")) -> 95000 | CA22: =IF(((BU22-(1600000))>0),(IF((BU22>(3200000)),((1600000)*21%),((BU22-(1600000))*21%))),("")) -> 336000 | CB22: =IF(((BU22-(3200000))>0),(IF((BU22>(3200000)),((BU22-(3200000))*24%),(0))),("")) -> 520463.11 | CC22: =SUM(BW22:CB22) -> 1080463.1 | CD22: =1%*BQ22 -> 69607.454 | CE22: =MAX(CC22:CD22) -> 1080463.1 | CF22: =+CE22/12 -> 90038.592
A23: 20 | B23: EKOKEME TAMARAUKRO TIMIPRE | C23: BANKING AND FINANCE | D23: SENIOR LECTURER | E23: CONUASS 5/2 | F23: GTB | G23: 0036064176 | H23: 2035373 | I23: 2144788 | J23: =J26 -> 202110.17 | K23: =K26 -> 50527.542 | L23: 30000 | M23: 400171.75 | N23: =M23*0.35/3 -> 46686.704 | O23: 5000 | R23: 2500 | Z23: 2500 | AM23: =M23*0.02 -> 8003.435 | AN23: 500 | AW23: 1000 | BA23: 0 | BE23: 1500 | BH23: =BL23*0.02 -> 9137.1691 | BK23: 66383.49 | BL23: =M23+N23+O23+P23+R23+S23+T23+U23+V23+W23+Y23+Z23+AA23 -> 456858.45 | BM23: =AI23+AJ23+AK23+AL23+AM23+AN23+AP23++AQ23+AR23+AS23+AT23+AU23+AV23+AW23+AX23+AY23+AZ23+BA23+BB23+BC23+BD23+BE23+BG23+BH23+BK23 -> 86524.094 | BP23: =BL23-BM23 -> 370334.36 | BQ23: =BL23*12 -> 5482301.5 | BR23: =200000+(0.2*BQ23) -> 1296460.3 | BS23: =BI23*12 -> 0 | BT23: =SUM(BR23:BS23) -> 1296460.3 | BU23: =+BQ23-BT23 -> 4185841.2 | BW23: =IF((BU23>0),(IF((BU23>300000),(300000*7%),(BU23*7%))),(BQ23*1%)) -> 21000 | BX23: =IF((BU23-300000)>0,(IF((BU23>600000),(300000*11%),((BU23-300000)*11%))),("")) -> 33000 | BY23: =IF(((BU23-600000)>0),(IF((BU23>1100000),(500000*15%),((BU23-600000)*15%))),("")) -> 75000 | BZ23: =IF(((BU23-(1100000))>0),(IF((BU23>(1600000)),((500000)*19%),((BU23-(1100000))*19%))),("")) -> 95000 | CA23: =IF(((BU23-(1600000))>0),(IF((BU23>(3200000)),((1600000)*21%),((BU23-(1600000))*21%))),("")) -> 336000 | CB23: =IF(((BU23-(3200000))>0),(IF((BU23>(3200000)),((BU23-(3200000))*24%),(0))),("")) -> 236601.88 | CC23: =SUM(BW23:CB23) -> 796601.88 | CD23: =1%*BQ23 -> 54823.014 | CE23: =MAX(CC23:CD23) -> 796601.88 | CF23: =+CE23/12 -> 66383.49
A24: 21 | B24: KROKEME OKOYAN | C24: BANKING AND FINANCE | D24: LECTURER I | E24: CONUASS 4/2 | F24: STANBIC IBTC | G24: 0033854745 | H24: 1980666 | I24: 2035373 | J24: 169614.42 | K24: 42403.604 | L24: 30000 | M24: 291760.84 | N24: =M24*0.35/3 -> 34038.764 | O24: 5000 | P24: 20833.33 | R24: 2500 | Z24: 2500 | AM24: =M24*0.02 -> 5835.2167 | AN24: 500 | AP24: 76667 | AW24: 1000 | BA24: 0 | BE24: 1500 | BH24: =BL24*0.02 -> 7132.6586 | BK24: 47140.19 | BL24: =M24+N24+O24+P24+R24+S24+T24+U24+V24+W24+Y24+Z24+AA24 -> 356632.93 | BM24: =AI24+AJ24+AK24+AL24+AM24+AN24+AP24++AQ24+AR24+AS24+AT24+AU24+AV24+AW24+AX24+AY24+AZ24+BA24+BB24+BC24+BD24+BE24+BG24+BH24+BK24 -> 139775.06 | BP24: =BL24-BM24 -> 216857.87 | BQ24: =BL24*12 -> 4279595.2 | BR24: =200000+(0.2*BQ24) -> 1055919 | BS24: =BI24*12 -> 0 | BT24: =SUM(BR24:BS24) -> 1055919 | BU24: =+BQ24-BT24 -> 3223676.1 | BW24: =IF((BU24>0),(IF((BU24>300000),(300000*7%),(BU24*7%))),(BQ24*1%)) -> 21000 | BX24: =IF((BU24-300000)>0,(IF((BU24>600000),(300000*11%),((BU24-300000)*11%))),("")) -> 33000 | BY24: =IF(((BU24-600000)>0),(IF((BU24>1100000),(500000*15%),((BU24-600000)*15%))),("")) -> 75000 | BZ24: =IF(((BU24-(1100000))>0),(IF((BU24>(1600000)),((500000)*19%),((BU24-(1100000))*19%))),("")) -> 95000 | CA24: =IF(((BU24-(1600000))>0),(IF((BU24>(3200000)),((1600000)*21%),((BU24-(1600000))*21%))),("")) -> 336000 | CB24: =IF(((BU24-(3200000))>0),(IF((BU24>(3200000)),((BU24-(3200000))*24%),(0))),("")) -> 5682.275 | CC24: =SUM(BW24:CB24) -> 565682.28 | CD24: =1%*BQ24 -> 42795.952 | CE24: =MAX(CC24:CD24) -> 565682.28 | CF24: =+CE24/12 -> 47140.19
A25: 22 | B25: ADIM CHIDIEBERE VICTOR | C25: BUSINESS ADMINISTRATION | D25: SENIOR LECTURER | E25: CONUASS 5/3 | F25: GTB | G25: 0035615588 | I25: 2090081 | J25: 174173.42 | K25: 43543.354 | L25: 30000 | M25: 413255.25 | N25: =M25*0.35/3 -> 48213.113 | O25: 5000 | P25: 20833.33 | R25: 2500 | Z25: 2500 | AM25: =M25*0.02 -> 8265.105 | AN25: 500 | AW25: 1000 | BA25: 0 | BC25: 3750 | BD25: 7500 | BE25: 1500 | BH25: =BL25*0.02 -> 9846.0338 | BK25: 69188.59 | BL25: =M25+N25+O25+P25+R25+S25+T25+U25+V25+W25+Y25+Z25+AA25 -> 492301.69 | BM25: =AI25+AJ25+AK25+AL25+AM25+AN25+AP25++AQ25+AR25+AS25+AT25+AU25+AV25+AW25+AX25+AY25+AZ25+BA25+BB25+BC25+BD25+BE25+BG25+BH25+BK25 -> 101549.73 | BP25: =BL25-BM25 -> 390751.96 | BQ25: =BL25*12 -> 5907620.3 | BR25: =200000+(0.2*BQ25) -> 1381524.1 | BS25: =BI25*12 -> 0 | BT25: =SUM(BR25:BS25) -> 1381524.1 | BU25: =+BQ25-BT25 -> 4526096.2 | BW25: =IF((BU25>0),(IF((BU25>300000),(300000*7%),(BU25*7%))),(BQ25*1%)) -> 21000 | BX25: =IF((BU25-300000)>0,(IF((BU25>600000),(300000*11%),((BU25-300000)*11%))),("")) -> 33000 | BY25: =IF(((BU25-600000)>0),(IF((BU25>1100000),(500000*15%),((BU25-600000)*15%))),("")) -> 75000 | BZ25: =IF(((BU25-(1100000))>0),(IF((BU25>(1600000)),((500000)*19%),((BU25-(1100000))*19%))),("")) -> 95000 | CA25: =IF(((BU25-(1600000))>0),(IF((BU25>(3200000)),((1600000)*21%),((BU25-(1600000))*21%))),("")) -> 336000 | CB25: =IF(((BU25-(3200000))>0),(IF((BU25>(3200000)),((BU25-(3200000))*24%),(0))),("")) -> 318263.1 | CC25: =SUM(BW25:CB25) -> 878263.1 | CD25: =1%*BQ25 -> 59076.203 | CE25: =MAX(CC25:CD25) -> 878263.1 | CF25: =+CE25/12 -> 73188.592
A26: 23 | B26: LUBO EBISINE | C26: ECONOMICS | D26: LECTURER I | E26: CONUASS 4/2 | F26: STERLING | G26: 0079015111 | H26: 2308911 | I26: 2425322 | J26: 202110.17 | K26: 50527.542 | L26: 30000 | M26: 291760.83 | N26: =M26*0.35/3 -> 34038.764 | O26: 5000 | R26: 2500 | Z26: 2500 | AM26: =M26*0.02 -> 5835.2166 | AN26: 500 | AP26: 93334 | AX26: 1000 | AZ26: 1000 | BA26: 118333.33 | BE26: 1500 | BH26: =BL26*0.02 -> 6715.9919 | BK26: 43581 | BL26: =M26+N26+O26+P26+R26+S26+T26+U26+V26+W26+Y26+Z26+AA26 -> 335799.59 | BM26: =AI26+AJ26+AK26+AL26+AM26+AN26+AP26++AQ26+AR26+AS26+AT26+AU26+AV26+AW26+AX26+AY26+AZ26+BA26+BB26+BC26+BD26+BE26+BG26+BH26+BK26 -> 271799.54 | BP26: =BL26-BM26 -> 64000.055 | BQ26: =BL26*12 -> 4029595.1 | BR26: =200000+(0.2*BQ26) -> 1005919 | BS26: =BI26*12 -> 0 | BT26: =SUM(BR26:BS26) -> 1005919 | BU26: =+BQ26-BT26 -> 3023676.1 | BW26: =IF((BU26>0),(IF((BU26>300000),(300000*7%),(BU26*7%))),(BQ26*1%)) -> 21000 | BX26: =IF((BU26-300000)>0,(IF((BU26>600000),(300000*11%),((BU26-300000)*11%))),("")) -> 33000 | BY26: =IF(((BU26-600000)>0),(IF((BU26>1100000),(500000*15%),((BU26-600000)*15%))),("")) -> 75000 | BZ26: =IF(((BU26-(1100000))>0),(IF((BU26>(1600000)),((500000)*19%),((BU26-(1100000))*19%))),("")) -> 95000 | CA26: =IF(((BU26-(1600000))>0),(IF((BU26>(3200000)),((1600000)*21%),((BU26-(1600000))*21%))),("")) -> 298971.98 | CB26: =IF(((BU26-(3200000))>0),(IF((BU26>(3200000)),((BU26-(3200000))*24%),(0))),("")) | CC26: =SUM(BW26:CB26) -> 522971.98 | CD26: =1%*BQ26 -> 40295.951 | CE26: =MAX(CC26:CD26) -> 522971.98 | CF26: =+CE26/12 -> 43580.998
A27: 24 | B27: OKABA EBIKONBOWEI ALEX | C27: BIOLOGICAL SCIENCE | D27: LECTURER I | E27: CONUASS 4/6 | F27: STERLING | G27: 0059407958 | H27: 2688069 | I27: 2775651 | J27: 231304.25 | K27: 57826.062 | L27: 30000 | M27: 328253.42 | N27: =M27*0.35/3 -> 38296.232 | O27: 5000 | P27: =P22 -> 20833.33 | R27: 2500 | Z27: 2500 | AL27: 93334 | AM27: =M27*0.02 -> 6565.0684 | AN27: 500 | AP27: 109688 | AQ27: 1000 | BA27: 95000 | BE27: 1500 | BH27: =BL27*0.02 -> 7947.6596 | BK27: 54964.2 | BL27: =M27+N27+O27+P27+R27+S27+T27+U27+V27+W27+Y27+Z27+AA27 -> 397382.98 | BM27: =AI27+AJ27+AK27+AL27+AM27+AN27+AP27++AQ27+AR27+AS27+AT27+AU27+AV27+AW27+AX27+AY27+AZ27+BA27+BB27+BC27+BD27+BE27+BG27+BH27+BK27 -> 370498.93 | BP27: =BL27-BM27 -> 26884.054 | BQ27: =BL27*12 -> 4768595.8 | BR27: =200000+(0.2*BQ27) -> 1153719.2 | BS27: =BI27*12 -> 0 | BT27: =SUM(BR27:BS27) -> 1153719.2 | BU27: =+BQ27-BT27 -> 3614876.6 | BW27: =IF((BU27>0),(IF((BU27>300000),(300000*7%),(BU27*7%))),(BQ27*1%)) -> 21000 | BX27: =IF((BU27-300000)>0,(IF((BU27>600000),(300000*11%),((BU27-300000)*11%))),("")) -> 33000 | BY27: =IF(((BU27-600000)>0),(IF((BU27>1100000),(500000*15%),((BU27-600000)*15%))),("")) -> 75000 | BZ27: =IF(((BU27-(1100000))>0),(IF((BU27>(1600000)),((500000)*19%),((BU27-(1100000))*19%))),("")) -> 95000 | CA27: =IF(((BU27-(1600000))>0),(IF((BU27>(3200000)),((1600000)*21%),((BU27-(1600000))*21%))),("")) -> 336000 | CB27: =IF(((BU27-(3200000))>0),(IF((BU27>(3200000)),((BU27-(3200000))*24%),(0))),("")) -> 99570.391 | CC27: =SUM(BW27:CB27) -> 659570.39 | CD27: =1%*BQ27 -> 47685.958 | CE27: =MAX(CC27:CD27) -> 659570.39 | CF27: =+CE27/12 -> 54964.199
A28: 25 | B28: ORIBHABOR BLESSING CHINELO | C28: GUIDANCE AND COUNSELLING | D28: ASSOCIATE PROFESSOR | E28: CONUASS 6/2 | F28: FIRST | G28: 2035909165 | H28: 4432861 | I28: 4558463 | J28: 379871.92 | K28: 94967.979 | L28: 30000 | M28: 480795.42 | N28: =M28*0.35/3 -> 56092.799 | O28: 5000 | R28: 2500 | Z28: 2500 | AM28: =M28*0.02 -> 9615.9084 | AN28: 500 | AP28: 40834 | AS28: 1000 | AY28: 2000 | BA28: 265000 | BC28: 7500 | BD28: 15000 | BE28: 2000 | BH28: =BL28*0.02 -> 10937.764 | BK28: 83669.2 | BL28: =M28+N28+O28+P28+R28+S28+T28+U28+V28+W28+Y28+Z28+AA28 -> 546888.22 | BM28: =AI28+AJ28+AK28+AL28+AM28+AN28+AP28++AQ28+AR28+AS28+AT28+AU28+AV28+AW28+AX28+AY28+AZ28+BA28+BB28+BC28+BD28+BE28+BG28+BH28+BK28 -> 438056.87 | BP28: =BL28-BM28 -> 108831.35 | BQ28: =BL28*12 -> 6562658.6 | BR28: =200000+(0.2*BQ28) -> 1512531.7 | BS28: =BI28*12 -> 0 | BT28: =SUM(BR28:BS28) -> 1512531.7 | BU28: =+BQ28-BT28 -> 5050126.9 | BW28: =IF((BU28>0),(IF((BU28>300000),(300000*7%),(BU28*7%))),(BQ28*1%)) -> 21000 | BX28: =IF((BU28-300000)>0,(IF((BU28>600000),(300000*11%),((BU28-300000)*11%))),("")) -> 33000 | BY28: =IF(((BU28-600000)>0),(IF((BU28>1100000),(500000*15%),((BU28-600000)*15%))),("")) -> 75000 | BZ28: =IF(((BU28-(1100000))>0),(IF((BU28>(1600000)),((500000)*19%),((BU28-(1100000))*19%))),("")) -> 95000 | CA28: =IF(((BU28-(1600000))>0),(IF((BU28>(3200000)),((1600000)*21%),((BU28-(1600000))*21%))),("")) -> 336000 | CB28: =IF(((BU28-(3200000))>0),(IF((BU28>(3200000)),((BU28-(3200000))*24%),(0))),("")) -> 444030.46 | CC28: =SUM(BW28:CB28) -> 1004030.5 | CD28: =1%*BQ28 -> 65626.586 | CE28: =MAX(CC28:CD28) -> 1004030.5 | CF28: =+CE28/12 -> 83669.205
A29: 26 | B29: FRANK SAPELE FUNKEYE | C29: POLITICAL SCIENCE | D29: ASSOCIATE PROFESSOR | E29: CONUASS 6/1 | F29: STERLING | G29: 0073394429 | M29: 464981 | N29: =M29*0.35/3 -> 54247.783 | O29: 5000 | P29: 20833.33 | R29: 2500 | Z29: 2500 | AM29: =M29*0.02 -> 9299.62 | AN29: 500 | AX29: 1000 | AY29: 2000 | BA29: 78833.33 | BC29: 3500 | BD29: 7500 | BE29: 2000 | BH29: 10584.58 | BK29: 84278.53 | BL29: =M29+N29+O29+P29+R29+S29+T29+U29+V29+W29+Y29+Z29+AA29 -> 550062.11 | BM29: =AI29+AJ29+AK29+AL29+AM29+AN29+AP29++AQ29+AR29+AS29+AT29+AU29+AV29+AW29+AX29+AY29+AZ29+BA29+BB29+BC29+BD29+BE29+BG29+BH29+BK29 -> 199496.06 | BP29: =BL29-BM29 -> 350566.05
A30: 27 | B30: BENSON DUNU TONBRAPADE | C30: EDUCATIONAL MANAGEMENT | D30: ASSOCIATE PROFESSOR | E30: CONUAS 6/1 | F30: UNION | G30: 0010851185 | H30: =#REF! -> #REF! | I30: 3804852 | J30: 317071 | K30: 79267.75 | L30: 30000 | M30: 464981 | N30: =M30*0.35/3 -> 54247.783 | O30: 5000 | P30: 41667 | R30: 2500 | Z30: 2500 | AM30: =M30*0.02 -> 9299.62 | AN30: 500 | AP30: 26667 | AS30: 1000 | AV30: 5000 | BA30: 119583.33 | BC30: 7500 | BD30: 15000 | BE30: 2000 | BH30: =BL30*0.02 -> 11417.916 | BK30: 88278.66 | BL30: =Z30+R30+P30+O30+N30+M30 -> 570895.78 | BM30: =AI30+AJ30+AK30+AL30+AM30+AN30+AP30++AQ30+AR30+AS30+AT30+AU30+AV30+AW30+AX30+AY30+AZ30+BA30+BB30+BC30+BD30+BE30+BG30+BH30+BK30 -> 286246.53 | BP30: =BL30-BM30 -> 284649.26 | BQ30: =BL30*12 -> 6850749.4 | BR30: =200000+(0.2*BQ30) -> 1570149.9 | BS30: =BI30*12 -> 0 | BT30: =SUM(BR30:BS30) -> 1570149.9 | BU30: =+BQ30-BT30 -> 5280599.5 | BW30: =IF((BU30>0),(IF((BU30>300000),(300000*7%),(BU30*7%))),(BQ30*1%)) -> 21000 | BX30: =IF((BU30-300000)>0,(IF((BU30>600000),(300000*11%),((BU30-300000)*11%))),("")) -> 33000 | BY30: =IF(((BU30-600000)>0),(IF((BU30>1100000),(500000*15%),((BU30-600000)*15%))),("")) -> 75000 | BZ30: =IF(((BU30-(1100000))>0),(IF((BU30>(1600000)),((500000)*19%),((BU30-(1100000))*19%))),("")) -> 95000 | CA30: =IF(((BU30-(1600000))>0),(IF((BU30>(3200000)),((1600000)*21%),((BU30-(1600000))*21%))),("")) -> 336000 | CB30: =IF(((BU30-(3200000))>0),(IF((BU30>(3200000)),((BU30-(3200000))*24%),(0))),("")) -> 499343.88 | CC30: =SUM(BW30:CB30) -> 1059343.9 | CD30: =1%*BQ30 -> 68507.494 | CE30: =MAX(CC30:CD30) -> 1059343.9 | CF30: =+CE30/12 -> 88278.657
A31: 28 | B31: IYE RONAMI SAMUEL | C31: LIBRARY | D31: ASSISTANT LECTURER | E31: CONUAS 2/4 | F31: ZENITH | G31: 2007556061 | H31: 1691938 | I31: 1796468 | J31: 149705.67 | K31: 37426.417 | L31: 30000 | M31: 222376.83 | N31: =M31*0.35/3 -> 25943.964 | O31: 5000 | R31: 2500 | Z31: 2500 | AM31: =M31*0.02 -> 4447.5366 | AN31: 500 | BA31: 0 | BC31: 7500 | BD31: 15000 | BE31: 1000 | BF31: 1000 | BH31: =BL31*0.02 -> 5166.4159 | BK31: 30564.56 | BL31: =M31+N31+O31+P31+R31+S31+T31+U31+V31+W31+Y31+Z31+AA31 -> 258320.79 | BM31: 65178.51 | BP31: =BL31-BM31 -> 193142.28 | BQ31: =BL31*12 -> 3099849.5 | BR31: =200000+(0.2*BQ31) -> 819969.9 | BS31: =BI31*12 -> 0 | BT31: =SUM(BR31:BS31) -> 819969.9 | BU31: =+BQ31-BT31 -> 2279879.6 | BW31: =IF((BU31>0),(IF((BU31>300000),(300000*7%),(BU31*7%))),(BQ31*1%)) -> 21000 | BX31: =IF((BU31-300000)>0,(IF((BU31>600000),(300000*11%),((BU31-300000)*11%))),("")) -> 33000 | BY31: =IF(((BU31-600000)>0),(IF((BU31>1100000),(500000*15%),((BU31-600000)*15%))),("")) -> 75000 | BZ31: =IF(((BU31-(1100000))>0),(IF((BU31>(1600000)),((500000)*19%),((BU31-(1100000))*19%))),("")) -> 95000 | CA31: =IF(((BU31-(1600000))>0),(IF((BU31>(3200000)),((1600000)*21%),((BU31-(1600000))*21%))),("")) -> 142774.72 | CB31: =IF(((BU31-(3200000))>0),(IF((BU31>(3200000)),((BU31-(3200000))*24%),(0))),("")) | CC31: =SUM(BW31:CB31) -> 366774.72 | CD31: =1%*BQ31 -> 30998.495 | CE31: =MAX(CC31:CD31) -> 366774.72 | CF31: =+CE31/12 -> 30564.56
A32: 29 | B32: ANDERSON BLESSING PERE-ERE | C32: ENGLISH AND LITERARY STUDIES | D32: GRADUATE ASSISTANT | E32: CONUAS 1/3 | F32: STERLING | G32: 0071139983 | J32: 63367 | K32: 15841.75 | L32: 30000 | M32: 192875.25 | N32: =M32*0.35/3 -> 22502.112 | O32: 5000 | R32: 2500 | Z32: 2500 | AM32: =M32*0.02 -> 3857.505 | AN32: 500 | AY32: 2000 | BA32: 0 | BE32: 1000 | BH32: 2580.0986 | BK32: 25030.06 | BL32: =M32+N32+O32+P32+R32+S32+T32+U32+V32+W32+Y32+Z32+AA32 -> 225377.36 | BM32: =AI32+AJ32+AK32+AL32+AM32+AN32+AP32++AQ32+AR32+AS32+AT32+AU32+AV32+AW32+AX32+AY32+AZ32+BA32+BB32+BC32+BD32+BE32+BG32+BH32+BK32 -> 34967.664 | BP32: =BL32-BM32 -> 190409.7 | BQ32: =BL32*12 -> 2704528.4 | BR32: =200000+(0.2*BQ32) -> 740905.67 | BS32: =BI32*12 -> 0 | BT32: =SUM(BR32:BS32) -> 740905.67 | BU32: =+BQ32-BT32 -> 1963622.7 | BW32: =IF((BU32>0),(IF((BU32>300000),(300000*7%),(BU32*7%))),(BQ32*1%)) -> 21000 | BX32: =IF((BU32-300000)>0,(IF((BU32>600000),(300000*11%),((BU32-300000)*11%))),("")) -> 33000 | BY32: =IF(((BU32-600000)>0),(IF((BU32>1100000),(500000*15%),((BU32-600000)*15%))),("")) -> 75000 | BZ32: =IF(((BU32-(1100000))>0),(IF((BU32>(1600000)),((500000)*19%),((BU32-(1100000))*19%))),("")) -> 95000 | CA32: =IF(((BU32-(1600000))>0),(IF((BU32>(3200000)),((1600000)*21%),((BU32-(1600000))*21%))),("")) -> 76360.763 | CB32: =IF(((BU32-(3200000))>0),(IF((BU32>(3200000)),((BU32-(3200000))*24%),(0))),("")) | CC32: =SUM(BW32:CB32) -> 300360.76 | CD32: =1%*BQ32 -> 27045.284 | CE32: =MAX(CC32:CD32) -> 300360.76 | CF32: =+CE32/12 -> 25030.064
A33: 30 | B33: EREBI BOMIEGHA CLEMENT | C33: ENGLISH AND LITERARY STUDIES | D33: GRADUATE ASSISTANT | E33: CONUAS 1/3 | F33: UBA | G33: 2104479346 | J33: 63367 | K33: 15841.75 | L33: 30000 | M33: 192875.25 | N33: =M33*0.35/3 -> 22502.112 | O33: 5000 | R33: 2500 | Z33: 2500 | AM33: =M33*0.02 -> 3857.505 | AN33: 500 | BA33: 0 | BE33: 1000 | BH33: 2580.0986 | BK33: 25030.06 | BL33: =M33+N33+O33+P33+R33+S33+T33+U33+V33+W33+Y33+Z33+AA33 -> 225377.36 | BM33: =AI33+AJ33+AK33+AL33+AM33+AN33+AP33++AQ33+AR33+AS33+AT33+AU33+AV33+AW33+AX33+AY33+AZ33+BA33+BB33+BC33+BD33+BE33+BG33+BH33+BK33 -> 32967.664 | BP33: =BL33-BM33 -> 192409.7 | CF33: =CF32 -> 25030.064
A34: 31 | B34: BRISIBE FRED EMI | C34: THEATRE ARTS | D34: LECTURER II | E34: CONUAS 3/4 | F34: ZENITH | G34: 1002357668 | H34: 1691939 | I34: 2035373 | J34: 169614.42 | K34: 42403.604 | L34: 30000 | M34: 247716.75 | N34: =M34*0.35/3 -> 28900.287 | O34: 5000 | R34: 2500 | Z34: 2500 | AI34: 50000 | AM34: =M34*0.02 -> 4954.335 | AN34: 500 | AP34: 61667 | AS34: 1000 | BA34: 0 | BE34: 1000 | BH34: =BL34*0.02 -> 5732.3408 | BK34: 35318.33 | BL34: =M34+N34+O34+P34+R34+S34+T34+U34+V34+W34+Y34+Z34+AA34 -> 286617.04 | BM34: =AI34+AJ34+AK34+AL34+AM34+AN34+AP34++AQ34+AR34+AS34+AT34+AU34+AV34+AW34+AX34+AY34+AZ34+BA34+BB34+BC34+BD34+BE34+BG34+BH34+BK34 -> 160172.01 | BP34: =BL34-BM34 -> 126445.03 | BQ34: =BL34*12 -> 3439404.5 | BR34: =200000+(0.2*BQ34) -> 887880.89 | BS34: =BI34*12 -> 0 | BT34: =SUM(BR34:BS34) -> 887880.89 | BU34: =+BQ34-BT34 -> 2551523.6 | BW34: =IF((BU34>0),(IF((BU34>300000),(300000*7%),(BU34*7%))),(BQ34*1%)) -> 21000 | BX34: =IF((BU34-300000)>0,(IF((BU34>600000),(300000*11%),((BU34-300000)*11%))),("")) -> 33000 | BY34: =IF(((BU34-600000)>0),(IF((BU34>1100000),(500000*15%),((BU34-600000)*15%))),("")) -> 75000 | BZ34: =IF(((BU34-(1100000))>0),(IF((BU34>(1600000)),((500000)*19%),((BU34-(1100000))*19%))),("")) -> 95000 | CA34: =IF(((BU34-(1600000))>0),(IF((BU34>(3200000)),((1600000)*21%),((BU34-(1600000))*21%))),("")) -> 199819.95 | CB34: =IF(((BU34-(3200000))>0),(IF((BU34>(3200000)),((BU34-(3200000))*24%),(0))),("")) | CC34: =SUM(BW34:CB34) -> 423819.95 | CD34: =1%*BQ34 -> 34394.045 | CE34: =MAX(CC34:CD34) -> 423819.95 | CF34: =+CE34/12 -> 35318.329
A35: 32 | B35: DISEYE ISOWO | C35: COMPUTER SCIENCE AND MATHEMATICAL | D35: LECTURER II | E35: CONUAS 3/3 | F35: GLOBUS | G35: 2003332007 | I35: 1925958 | J35: 160496.5 | K35: 40124.125 | L35: 30000 | M35: 242018.08 | N35: =M35*0.35/3 -> 28235.443 | O35: 5000 | R35: 2500 | Z35: 2500 | AM35: =M35*0.02 -> 4840.3616 | AN35: 500 | AQ35: 1000 | AV35: 10000 | BA35: 0 | BE35: 1000 | BH35: =BL35*0.02 -> 5605.0705 | BK35: 34249.26 | BL35: =M35+N35+O35+P35+R35+S35+T35+U35+V35+W35+Y35+Z35+AA35 -> 280253.52 | BM35: =AI35+AJ35+AK35+AL35+AM35+AN35+AP35++AQ35+AR35+AS35+AT35+AU35+AV35+AW35+AX35+AY35+AZ35+BA35+BB35+BC35+BD35+BE35+BG35+BH35+BK35 -> 57194.692 | BP35: =BL35-BM35 -> 223058.83 | BQ35: =BL35*12 -> 3363042.3 | BR35: =200000+(0.2*BQ35) -> 872608.45 | BS35: =BI35*12 -> 0 | BT35: =SUM(BR35:BS35) -> 872608.45 | BU35: =+BQ35-BT35 -> 2490433.8 | BW35: =IF((BU35>0),(IF((BU35>300000),(300000*7%),(BU35*7%))),(BQ35*1%)) -> 21000 | BX35: =IF((BU35-300000)>0,(IF((BU35>600000),(300000*11%),((BU35-300000)*11%))),("")) -> 33000 | BY35: =IF(((BU35-600000)>0),(IF((BU35>1100000),(500000*15%),((BU35-600000)*15%))),("")) -> 75000 | BZ35: =IF(((BU35-(1100000))>0),(IF((BU35>(1600000)),((500000)*19%),((BU35-(1100000))*19%))),("")) -> 95000 | CA35: =IF(((BU35-(1600000))>0),(IF((BU35>(3200000)),((1600000)*21%),((BU35-(1600000))*21%))),("")) -> 186991.1 | CB35: =IF(((BU35-(3200000))>0),(IF((BU35>(3200000)),((BU35-(3200000))*24%),(0))),("")) | CC35: =SUM(BW35:CB35) -> 410991.1 | CD35: =1%*BQ35 -> 33630.423 | CE35: =MAX(CC35:CD35) -> 410991.1 | CF35: =+CE35/12 -> 34249.258
A36: 33 | B36: OGUNBODEDE FRANCIS KOLAWOLE | C36: LIBRARY | D36: LECTURER II | E36: CONUAS 3/1 | F36: STERLING | G36: 0081963426 | H36: 1796468 | I36: 1846818 | J36: 153901.5 | K36: 38475.375 | L36: 30000 | BQ36: =BL36*12 -> 0 | BR36: =200000+(0.2*BQ36) -> 200000 | BS36: =BI36*12 -> 0 | BT36: =SUM(BR36:BS36) -> 200000 | BU36: =+BQ36-BT36 -> -200000 | BW36: =IF((BU36>0),(IF((BU36>300000),(300000*7%),(BU36*7%))),(BQ36*1%)) -> 0 | BX36: =IF((BU36-300000)>0,(IF((BU36>600000),(300000*11%),((BU36-300000)*11%))),("")) | BY36: =IF(((BU36-600000)>0),(IF((BU36>1100000),(500000*15%),((BU36-600000)*15%))),("")) | BZ36: =IF(((BU36-(1100000))>0),(IF((BU36>(1600000)),((500000)*19%),((BU36-(1100000))*19%))),("")) | CA36: =IF(((BU36-(1600000))>0),(IF((BU36>(3200000)),((1600000)*21%),((BU36-(1600000))*21%))),("")) | CB36: =IF(((BU36-(3200000))>0),(IF((BU36>(3200000)),((BU36-(3200000))*24%),(0))),("")) | CC36: =SUM(BW36:CB36) -> 0 | CD36: =1%*BQ36 -> 0 | CE36: =MAX(CC36:CD36) -> 0 | CF36: =+CE36/12 -> 0
A37: 34 | B37: KPODOH DANIEL OYINMIEBI | C37: THEATRE ARTS | D37: ASSIST LECTURER | E37: CONUAS 2/4 | F37: UBA | G37: 1018108205 | H37: 1796468 | I37: 1796468 | J37: 149705.67 | K37: 37426.417 | L37: 30000 | M37: 222376.83 | N37: =M37*0.35/3 -> 25943.964 | O37: 5000 | R37: 2500 | Z37: 2500 | AM37: =M37*0.02 -> 4447.5366 | AN37: 500 | AS37: 1000 | BA37: 0 | BC37: 4166.67 | BD37: 8333.33 | BE37: 1000 | BH37: =BL37*0.02 -> 5166.4159 | BK37: 30564.56 | BL37: =M37+N37+O37+P37+R37+S37+T37+U37+V37+W37+Y37+Z37+AA37 -> 258320.79 | BM37: =AI37+AJ37+AK37+AL37+AM37+AN37+AP37++AQ37+AR37+AS37+AT37+AU37+AV37+AW37+AX37+AY37+AZ37+BA37+BB37+BC37+BD37+BE37+BG37+BH37+BK37 -> 55178.512 | BP37: =BL37-BM37 -> 203142.28 | BQ37: =BL37*12 -> 3099849.5 | BR37: =200000+(0.2*BQ37) -> 819969.9 | BS37: =BI37*12 -> 0 | BT37: =SUM(BR37:BS37) -> 819969.9 | BU37: =+BQ37-BT37 -> 2279879.6 | BW37: =IF((BU37>0),(IF((BU37>300000),(300000*7%),(BU37*7%))),(BQ37*1%)) -> 21000 | BX37: =IF((BU37-300000)>0,(IF((BU37>600000),(300000*11%),((BU37-300000)*11%))),("")) -> 33000 | BY37: =IF(((BU37-600000)>0),(IF((BU37>1100000),(500000*15%),((BU37-600000)*15%))),("")) -> 75000 | BZ37: =IF(((BU37-(1100000))>0),(IF((BU37>(1600000)),((500000)*19%),((BU37-(1100000))*19%))),("")) -> 95000 | CA37: =IF(((BU37-(1600000))>0),(IF((BU37>(3200000)),((1600000)*21%),((BU37-(1600000))*21%))),("")) -> 142774.72 | CB37: =IF(((BU37-(3200000))>0),(IF((BU37>(3200000)),((BU37-(3200000))*24%),(0))),("")) | CC37: =SUM(BW37:CB37) -> 366774.72 | CD37: =1%*BQ37 -> 30998.495 | CE37: =MAX(CC37:CD37) -> 366774.72 | CF37: =+CE37/12 -> 30564.56
A38: 35 | B38: RICHARD BRILLIANT | C38: ENGLISH AND LITERARY STUDIES | D38: LECTURER I | E38: CONUAS 4/2 | F38: STERLING | G38: 0028949995 | H38: 1980666 | I38: 2035373 | J38: 169614.42 | K38: 42403.604 | L38: 30000 | M38: 291760.83 | N38: =M38*0.35/3 -> 34038.764 | O38: 5000 | R38: 2500 | Z38: 2500 | AM38: =M38*0.02 -> 5835.2166 | AN38: 500 | AS38: 1000 | BA38: 90000 | BE38: 1000 | BF38: 1000 | BH38: =BL38*0.02 -> 6715.9919 | BK38: 43580.998 | BL38: =M38+N38+O38+P38+R38+S38+T38+U38+V38+W38+Y38+Z38+AA38 -> 335799.59 | BM38: =BK38+BH38+BE38+BA38+AS38+AN38+AM38 -> 148632.21 | BP38: =BL38-BM38 -> 187167.39 | BQ38: =BL38*12 -> 4029595.1 | BR38: =200000+(0.2*BQ38) -> 1005919 | BS38: =BI38*12 -> 0 | BT38: =SUM(BR38:BS38) -> 1005919 | BU38: =+BQ38-BT38 -> 3023676.1 | BW38: =IF((BU38>0),(IF((BU38>300000),(300000*7%),(BU38*7%))),(BQ38*1%)) -> 21000 | BX38: =IF((BU38-300000)>0,(IF((BU38>600000),(300000*11%),((BU38-300000)*11%))),("")) -> 33000 | BY38: =IF(((BU38-600000)>0),(IF((BU38>1100000),(500000*15%),((BU38-600000)*15%))),("")) -> 75000 | BZ38: =IF(((BU38-(1100000))>0),(IF((BU38>(1600000)),((500000)*19%),((BU38-(1100000))*19%))),("")) -> 95000 | CA38: =IF(((BU38-(1600000))>0),(IF((BU38>(3200000)),((1600000)*21%),((BU38-(1600000))*21%))),("")) -> 298971.98 | CB38: =IF(((BU38-(3200000))>0),(IF((BU38>(3200000)),((BU38-(3200000))*24%),(0))),("")) | CC38: =SUM(BW38:CB38) -> 522971.98 | CD38: =1%*BQ38 -> 40295.951 | CE38: =MAX(CC38:CD38) -> 522971.98 | CF38: =+CE38/12 -> 43580.998
A39: 36 | B39: NAPOLEON EBIYEFA | C39: HISTORY AND INTERNATIONAL STUDIES | D39: ASSIST LECTURER | E39: CONUAS 2/4 | F39: UBA | G39: 2108025545 | H39: 1746118 | I39: 1796468 | J39: 149705.67 | K39: 37426.417 | L39: 30000 | M39: 222376.83 | N39: =M39*0.35/3 -> 25943.964 | O39: 5000 | R39: 2500 | Z39: 2500 | AM39: =M39*0.02 -> 4447.5366 | AN39: 500 | BA39: 0 | BE39: 1000 | BH39: =BL39*0.02 -> 5166.4159 | BK39: 30564.56 | BL39: =M39+N39+O39+P39+R39+S39+T39+U39+V39+W39+Y39+Z39+AA39 -> 258320.79 | BM39: =AI39+AJ39+AK39+AL39+AM39+AN39+AP39++AQ39+AR39+AS39+AT39+AU39+AV39+AW39+AX39+AY39+AZ39+BA39+BB39+BC39+BD39+BE39+BG39+BH39+BK39 -> 41678.512 | BP39: =BL39-BM39 -> 216642.28 | BQ39: =BL39*12 -> 3099849.5 | BR39: =200000+(0.2*BQ39) -> 819969.9 | BS39: =BI39*12 -> 0 | BT39: =SUM(BR39:BS39) -> 819969.9 | BU39: =+BQ39-BT39 -> 2279879.6 | BW39: =IF((BU39>0),(IF((BU39>300000),(300000*7%),(BU39*7%))),(BQ39*1%)) -> 21000 | BX39: =IF((BU39-300000)>0,(IF((BU39>600000),(300000*11%),((BU39-300000)*11%))),("")) -> 33000 | BY39: =IF(((BU39-600000)>0),(IF((BU39>1100000),(500000*15%),((BU39-600000)*15%))),("")) -> 75000 | BZ39: =IF(((BU39-(1100000))>0),(IF((BU39>(1600000)),((500000)*19%),((BU39-(1100000))*19%))),("")) -> 95000 | CA39: =IF(((BU39-(1600000))>0),(IF((BU39>(3200000)),((1600000)*21%),((BU39-(1600000))*21%))),("")) -> 142774.72 | CB39: =IF(((BU39-(3200000))>0),(IF((BU39>(3200000)),((BU39-(3200000))*24%),(0))),("")) | CC39: =SUM(BW39:CB39) -> 366774.72 | CD39: =1%*BQ39 -> 30998.495 | CE39: =MAX(CC39:CD39) -> 366774.72 | CF39: =+CE39/12 -> 30564.56
A40: 37 | B40: NWOSU NNBUIHE NANCY | C40: EDUCATIONAL MANAGEMENT | D40: ASSOCIATE PROFESSOR | E40: CONUAS 6/4 | F40: FIRST | G40: 3051864825 | H40: 3930454 | I40: 4175818 | J40: 347984.83 | K40: 86996.208 | L40: 30000 | M40: 512424.25 | N40: =M40*0.35/3 -> 59782.829 | O40: 5000 | P40: 20833.33 | R40: 2500 | Z40: 2500 | AM40: =M40*0.02 -> 10248.485 | AN40: 500 | AP40: 45000 | AS40: 1000 | AY40: 2000 | BA40: 97500 | BC40: 4166.67 | BD40: 8333.33 | BE40: 2000 | BH40: =BL40*0.02 -> 12060.808 | BK40: 94450.43 | BL40: =M40+N40+O40+P40+R40+S40+T40+U40+V40+W40+Y40+Z40+AA40 -> 603040.41 | BM40: =AI40+AJ40+AK40+AL40+AM40+AN40+AP40++AQ40+AR40+AS40+AT40+AU40+AV40+AW40+AX40+AY40+AZ40+BA40+BB40+BC40+BD40+BE40+BG40+BH40+BK40 -> 277259.72 | BP40: =BL40-BM40 -> 325780.69 | BQ40: =BL40*12 -> 7236484.9 | BR40: =200000+(0.2*BQ40) -> 1647297 | BS40: =BI40*12 -> 0 | BT40: =SUM(BR40:BS40) -> 1647297 | BU40: =+BQ40-BT40 -> 5589187.9 | BW40: =IF((BU40>0),(IF((BU40>300000),(300000*7%),(BU40*7%))),(BQ40*1%)) -> 21000 | BX40: =IF((BU40-300000)>0,(IF((BU40>600000),(300000*11%),((BU40-300000)*11%))),("")) -> 33000 | BY40: =IF(((BU40-600000)>0),(IF((BU40>1100000),(500000*15%),((BU40-600000)*15%))),("")) -> 75000 | BZ40: =IF(((BU40-(1100000))>0),(IF((BU40>(1600000)),((500000)*19%),((BU40-(1100000))*19%))),("")) -> 95000 | CA40: =IF(((BU40-(1600000))>0),(IF((BU40>(3200000)),((1600000)*21%),((BU40-(1600000))*21%))),("")) -> 336000 | CB40: =IF(((BU40-(3200000))>0),(IF((BU40>(3200000)),((BU40-(3200000))*24%),(0))),("")) -> 573405.1 | CC40: =SUM(BW40:CB40) -> 1133405.1 | CD40: =1%*BQ40 -> 72364.849 | CE40: =MAX(CC40:CD40) -> 1133405.1 | CF40: =+CE40/12 -> 94450.425
A41: 38 | B41: DONATUS OTAIGBE ONOGBOSELE | C41: ECONOMICS | D41: ASSOCIATE PROFESSOR | E41: CONUAS 6/5 | F41: ZENITH | G41: 1005415103 | H41: 4479454 | I41: 4631272 | J41: 385939.33 | K41: 96484.833 | L41: 30000 | M41: 528238.58 | N41: =M41*0.35/3 -> 61627.834 | O41: 6666.67 | P41: =20833.33+20833.33 -> 41666.66 | R41: 2500 | Z41: 2500 | AM41: =M41*0.02 -> 10564.772 | AN41: 500 | AP41: 75000 | AX41: 1000 | AZ41: 1000 | BA41: 119459 | BC41: 12500 | BD41: 25000 | BE41: 2500 | BH41: =BL41*0.02 -> 12863.995 | BK41: 102161.02 | BL41: =M41+N41+O41+P41+R41+S41+T41+U41+V41+W41+Y41+Z41+AA41 -> 643199.74 | BM41: =AI41+AJ41+AK41+AL41+AM41+AN41+AP41++AQ41+AR41+AS41+AT41+AU41+AV41+AW41+AX41+AY41+AZ41+BA41+BB41+BC41+BD41+BE41+BG41+BH41+BK41 -> 362548.79 | BP41: =BL41-BM41 -> 280650.96 | BQ41: =BL41*12 -> 7718396.9 | BR41: =200000+(0.2*BQ41) -> 1743679.4 | BS41: =BI41*12 -> 0 | BT41: =SUM(BR41:BS41) -> 1743679.4 | BU41: =+BQ41-BT41 -> 5974717.5 | BW41: =IF((BU41>0),(IF((BU41>300000),(300000*7%),(BU41*7%))),(BQ41*1%)) -> 21000 | BX41: =IF((BU41-300000)>0,(IF((BU41>600000),(300000*11%),((BU41-300000)*11%))),("")) -> 33000 | BY41: =IF(((BU41-600000)>0),(IF((BU41>1100000),(500000*15%),((BU41-600000)*15%))),("")) -> 75000 | BZ41: =IF(((BU41-(1100000))>0),(IF((BU41>(1600000)),((500000)*19%),((BU41-(1100000))*19%))),("")) -> 95000 | CA41: =IF(((BU41-(1600000))>0),(IF((BU41>(3200000)),((1600000)*21%),((BU41-(1600000))*21%))),("")) -> 336000 | CB41: =IF(((BU41-(3200000))>0),(IF((BU41>(3200000)),((BU41-(3200000))*24%),(0))),("")) -> 665932.21 | CC41: =SUM(BW41:CB41) -> 1225932.2 | CD41: =1%*BQ41 -> 77183.969 | CE41: =MAX(CC41:CD41) -> 1225932.2 | CF41: =+CE41/12 -> 102161.02
A42: 39 | B42: JASPER EZENWAKA | C42: CROP SOIL AND PEST MGT | D42: PROFESSOR | E42: CONUAS 7/3 | F42: ACCESS | G42: 0016880418 | H42: =M42*12/2 -> 3843072.5 | J42: 207164.27 | K42: 51791.069 | L42: 15000 | M42: 640512.08 | N42: =M42*0.35/3 -> 74726.409 | O42: 6666.67 | R42: 2500 | Z42: 2500 | AM42: =M42*0.02 -> 12810.242 | AN42: 500 | BA42: 0 | BE42: 3500 | BH42: =BL42*0.02 -> 14538.103 | BK42: 118232.46 | BL42: =M42+N42+O42+P42+R42+S42+T42+U42+V42+W42+Y42+Z42+AA42 -> 726905.16 | BM42: =AI42+AJ42+AK42+AL42+AM42+AN42+AP42++AQ42+AR42+AS42+AT42+AU42+AV42+AW42+AX42+AY42+AZ42+BA42+BB42+BC42+BD42+BE42+BG42+BH42+BK42 -> 149580.8 | BP42: =BL42-BM42 -> 577324.36 | BQ42: =BL42*12 -> 8722861.9 | BR42: =200000+(0.2*BQ42) -> 1944572.4 | BS42: =BI42*12 -> 0 | BT42: =SUM(BR42:BS42) -> 1944572.4 | BU42: =+BQ42-BT42 -> 6778289.5 | BW42: =IF((BU42>0),(IF((BU42>300000),(300000*7%),(BU42*7%))),(BQ42*1%)) -> 21000 | BX42: =IF((BU42-300000)>0,(IF((BU42>600000),(300000*11%),((BU42-300000)*11%))),("")) -> 33000 | BY42: =IF(((BU42-600000)>0),(IF((BU42>1100000),(500000*15%),((BU42-600000)*15%))),("")) -> 75000 | BZ42: =IF(((BU42-(1100000))>0),(IF((BU42>(1600000)),((500000)*19%),((BU42-(1100000))*19%))),("")) -> 95000 | CA42: =IF(((BU42-(1600000))>0),(IF((BU42>(3200000)),((1600000)*21%),((BU42-(1600000))*21%))),("")) -> 336000 | CB42: =IF(((BU42-(3200000))>0),(IF((BU42>(3200000)),((BU42-(3200000))*24%),(0))),("")) -> 858789.49 | CC42: =SUM(BW42:CB42) -> 1418789.5 | CD42: =1%*BQ42 -> 87228.619 | CE42: =MAX(CC42:CD42) -> 1418789.5 | CF42: =+CE42/12 -> 118232.46
A43: 40 | B43: PROF. KAYWOOD ELIJAH LEIZOU | C43: CHEMICAL SCIENCES | D43: PROFESSOR | E43: CONUAS 7/1 | F43: STERLING | G43: 0078905710 | M43: 600738.25 | N43: =M43*0.35/3 -> 70086.129 | O43: 6666.67 | R43: 2500 | Z43: 2500 | AM43: =M43*0.02 -> 12014.765 | AN43: 500 | AQ43: 1000 | BA43: 100000 | BE43: 3500 | BH43: =BL43*0.02 -> 13649.821 | BK43: 39401.69 | BL43: =M43+N43+O43+P43+R43+S43+T43+U43+V43+W43+Y43+Z43+AA43 -> 682491.05 | BM43: =AI43+AJ43+AK43+AL43+AM43+AN43+AP43++AQ43+AR43+AS43+AT43+AU43+AV43+AW43+AX43+AY43+AZ43+BA43+BB43+BC43+BD43+BE43+BG43+BH43+BK43 -> 170066.28 | BP43: =BL43-BM43 -> 512424.77
A44: 41 | B44: EVANS F.OSAISAI | C44: COMPUTER SCIENCE AND MATHEMATICAL | D44: PROFESSOR | E44: CONUAS 7/1 | F44: UBA | G44: 1003548777 | M44: 600739.25 | N44: =M44*0.35/3 -> 70086.246 | O44: 6666.67 | R44: 2500 | Z44: 2500 | AM44: =M44*0.02 -> 12014.785 | AN44: 500 | AQ44: 1000 | BA44: 20000 | BE44: 3500 | BH44: =BL44*0.02 -> 13649.843 | BK44: 39402.69 | BL44: =M44+N44+O44+P44+R44+S44+T44+U44+V44+W44+Y44+Z44+AA44 -> 682492.17 | BM44: =AI44+AJ44+AK44+AL44+AM44+AN44+AP44++AQ44+AR44+AS44+AT44+AU44+AV44+AW44+AX44+AY44+AZ44+BA44+BB44+BC44+BD44+BE44+BG44+BH44+BK44 -> 90067.318 | BP44: =BL44-BM44 -> 592424.85
A45: 42 | B45: MATHEW O WEGWU | C45: BIOLOGICAL SCIENCE | D45: ADJUNCT PROFESSOR | E45: CONUAS 7/4 | F45: UBA | G45: 1005008228 | H45: 4479455 | J45: 233481.96 | K45: 81718.686 | L45: 15000 | M45: =SUM(J45:L45) -> 330200.65 | R45: 2500 | Z45: 2500 | AM45: =M45*0.02 -> 6604.0129 | AN45: 500 | AQ45: 1000 | BA45: 0 | BE45: 1750 | BH45: =BL45*0.02 -> 6704.0129 | BK45: 43480.375 | BL45: =M45+N45+O45+P45+R45+S45+T45+U45+V45+W45+Y45+Z45+AA45 -> 335200.65 | BM45: =AI45+AJ45+AK45+AL45+AM45+AN45+AP45++AQ45+AR45+AS45+AT45+AU45+AV45+AW45+AX45+AY45+AZ45+BA45+BB45+BC45+BD45+BE45+BG45+BH45+BK45 -> 60038.401 | BP45: =BL45-BM45 -> 275162.24 | BQ45: =BL45*12 -> 4022407.8 | BR45: =200000+(0.2*BQ45) -> 1004481.6 | BS45: =BI45*12 -> 0 | BT45: =SUM(BR45:BS45) -> 1004481.6 | BU45: =+BQ45-BT45 -> 3017926.2 | BW45: =IF((BU45>0),(IF((BU45>300000),(300000*7%),(BU45*7%))),(BQ45*1%)) -> 21000 | BX45: =IF((BU45-300000)>0,(IF((BU45>600000),(300000*11%),((BU45-300000)*11%))),("")) -> 33000 | BY45: =IF(((BU45-600000)>0),(IF((BU45>1100000),(500000*15%),((BU45-600000)*15%))),("")) -> 75000 | BZ45: =IF(((BU45-(1100000))>0),(IF((BU45>(1600000)),((500000)*19%),((BU45-(1100000))*19%))),("")) -> 95000 | CA45: =IF(((BU45-(1600000))>0),(IF((BU45>(3200000)),((1600000)*21%),((BU45-(1600000))*21%))),("")) -> 297764.5 | CB45: =IF(((BU45-(3200000))>0),(IF((BU45>(3200000)),((BU45-(3200000))*24%),(0))),("")) | CC45: =SUM(BW45:CB45) -> 521764.5 | CD45: =1%*BQ45 -> 40224.078 | CE45: =MAX(CC45:CD45) -> 521764.5 | CF45: =+CE45/12 -> 43480.375 | CN45: ADJUNCT PERIOD END WITH THE 2025/2026 ACADEMIC SESSION
A46: 43 | B46: BUNAKIYE RICHARD JAPHETH | C46: MATHEMATICS AND COMPUTER SCIENCE | D46: PROFESSOR | E46: CONUAS 7/3 | F46: GTB | G46: 0042255731 | H46: =M46*12 -> 7686145 | J46: 148068.7 | K46: 37017.176 | L46: 15000 | M46: 640512.08 | N46: =M46*0.35/3 -> 74726.409 | O46: =O44 -> 6666.67 | R46: 2500 | Z46: 2500 | AM46: =M46*0.02 -> 12810.242 | AN46: 500 | AP46: 0 | AQ46: =1000 -> 1000 | AV46: 10000 | BA46: 200000 | BE46: 2000 | BH46: =BL46*0.02 -> 14538.103 | BK46: 118552.46 | BL46: =M46+N46+O46+P46+R46+S46+T46+U46+V46+W46+Y46+Z46+AA46 -> 726905.16 | BM46: =AI46+AJ46+AK46+AL46+AM46+AN46+AP46++AQ46+AR46+AS46+AT46+AU46+AV46+AW46+AX46+AY46+AZ46+BA46+BB46+BC46+BD46+BE46+BG46+BH46+BK46 -> 359400.8 | BP46: =BL46-BM46 -> 367504.36 | BQ46: =BL46*12 -> 8722861.9 | BR46: =200000+(0.2*BQ46) -> 1944572.4 | BS46: =BI46*12 -> 0 | BT46: =SUM(BR46:BS46) -> 1944572.4 | BU46: =+BQ46-BT46 -> 6778289.5 | BW46: =IF((BU46>0),(IF((BU46>300000),(300000*7%),(BU46*7%))),(BQ46*1%)) -> 21000 | BX46: =IF((BU46-300000)>0,(IF((BU46>600000),(300000*11%),((BU46-300000)*11%))),("")) -> 33000 | BY46: =IF(((BU46-600000)>0),(IF((BU46>1100000),(500000*15%),((BU46-600000)*15%))),("")) -> 75000 | BZ46: =IF(((BU46-(1100000))>0),(IF((BU46>(1600000)),((500000)*19%),((BU46-(1100000))*19%))),("")) -> 95000 | CA46: =IF(((BU46-(1600000))>0),(IF((BU46>(3200000)),((1600000)*21%),((BU46-(1600000))*21%))),("")) -> 336000 | CB46: =IF(((BU46-(3200000))>0),(IF((BU46>(3200000)),((BU46-(3200000))*24%),(0))),("")) -> 858789.49 | CC46: =SUM(BW46:CB46) -> 1418789.5 | CD46: =1%*BQ46 -> 87228.619 | CE46: =MAX(CC46:CD46) -> 1418789.5 | CF46: =+CE46/12 -> 118232.46
A47: 44 | B47: EBINIMI J ANSA | C47: FISHERIES | D47: ADJNUNCT SENIOR LECTURER | E47: CONUAS 5/13 | F47: STANBIC IBTC | G47: 9200480279 | H47: =M47*12/2 -> 1632271.5 | J47: 186262.75 | K47: 70782.5 | L47: 15000 | M47: =SUM(J47:L47) -> 272045.25 | R47: 2500 | Z47: 2500 | AM47: =M47*0.02 -> 5440.905 | AN47: 500 | BA47: 0 | BE47: 2000 | BH47: =BL47*0.02 -> 5540.905 | BK47: 33774.67 | BL47: =M47+N47+O47+P47+R47+S47+T47+U47+V47+W47+Y47+Z47+AA47 -> 277045.25 | BM47: =AI47+AJ47+AK47+AL47+AM47+AN47+AP47++AQ47+AR47+AS47+AT47+AU47+AV47+AW47+AX47+AY47+AZ47+BA47+BB47+BC47+BD47+BE47+BG47+BH47+BK47 -> 47256.48 | BP47: =BL47-BM47 -> 229788.77 | BQ47: =BL47*12 -> 3324543 | BR47: =200000+(0.2*BQ47) -> 864908.6 | BS47: =BI47*12 -> 0 | BT47: =SUM(BR47:BS47) -> 864908.6 | BU47: =+BQ47-BT47 -> 2459634.4 | BW47: =IF((BU47>0),(IF((BU47>300000),(300000*7%),(BU47*7%))),(BQ47*1%)) -> 21000 | BX47: =IF((BU47-300000)>0,(IF((BU47>600000),(300000*11%),((BU47-300000)*11%))),("")) -> 33000 | BY47: =IF(((BU47-600000)>0),(IF((BU47>1100000),(500000*15%),((BU47-600000)*15%))),("")) -> 75000 | BZ47: =IF(((BU47-(1100000))>0),(IF((BU47>(1600000)),((500000)*19%),((BU47-(1100000))*19%))),("")) -> 95000 | CA47: =IF(((BU47-(1600000))>0),(IF((BU47>(3200000)),((1600000)*21%),((BU47-(1600000))*21%))),("")) -> 180523.22 | CB47: =IF(((BU47-(3200000))>0),(IF((BU47>(3200000)),((BU47-(3200000))*24%),(0))),("")) | CC47: =SUM(BW47:CB47) -> 404523.22 | CD47: =1%*BQ47 -> 33245.43 | CE47: =MAX(CC47:CD47) -> 404523.22 | CF47: =+CE47/12 -> 33710.269
A48: 45 | B48: JULIANA IWORIKUMO CONSUL | C48: MATHEMATICS AND COMPUTER SCIENCE | D48: ADJNUNCT ASSOCIATE PROFESSOR | E48: CONUAS 6/2 | F48: GTB | G48: 0112692440 | H48: =M48*12/2 -> 1442386.3 | J48: 189402.24 | K48: 47350.56 | L48: 15000 | M48: 240397.71 | R48: 2500 | Z48: 2500 | AM48: =M48*0.02 -> 4807.9542 | AN48: 500 | AQ48: 1000 | BA48: 0 | BE48: 2000 | BH48: =BL48*0.02 -> 4907.9542 | BK48: 28393.482 | BL48: =M48+N48+O48+P48+R48+S48+T48+U48+V48+W48+Y48+Z48+AA48 -> 245397.71 | BM48: =AI48+AJ48+AK48+AL48+AM48+AN48+AP48++AQ48+AR48+AS48+AT48+AU48+AV48+AW48+AX48+AY48+AZ48+BA48+BB48+BC48+BD48+BE48+BG48+BH48+BK48 -> 41609.39 | BP48: =BL48-BM48 -> 203788.32 | BQ48: =BL48*12 -> 2944772.5 | BR48: =200000+(0.2*BQ48) -> 788954.5 | BS48: =BI48*12 -> 0 | BT48: =SUM(BR48:BS48) -> 788954.5 | BU48: =+BQ48-BT48 -> 2155818 | BW48: =IF((BU48>0),(IF((BU48>300000),(300000*7%),(BU48*7%))),(BQ48*1%)) -> 21000 | BX48: =IF((BU48-300000)>0,(IF((BU48>600000),(300000*11%),((BU48-300000)*11%))),("")) -> 33000 | BY48: =IF(((BU48-600000)>0),(IF((BU48>1100000),(500000*15%),((BU48-600000)*15%))),("")) -> 75000 | BZ48: =IF(((BU48-(1100000))>0),(IF((BU48>(1600000)),((500000)*19%),((BU48-(1100000))*19%))),("")) -> 95000 | CA48: =IF(((BU48-(1600000))>0),(IF((BU48>(3200000)),((1600000)*21%),((BU48-(1600000))*21%))),("")) -> 116721.78 | CB48: =IF(((BU48-(3200000))>0),(IF((BU48>(3200000)),((BU48-(3200000))*24%),(0))),("")) | CC48: =SUM(BW48:CB48) -> 340721.78 | CD48: =1%*BQ48 -> 29447.725 | CE48: =MAX(CC48:CD48) -> 340721.78 | CF48: =+CE48/12 -> 28393.482
A49: 46 | B49: OLAJIDE ROTIMI | C49: ANIMAL PRODUCTION AND HEALTH | D49: FULL TIME PROFESSOR | E49: CONUAS 7/10 | F49: GTB | G49: 0110692501 | H49: 6310662 | I49: 6487437 | J49: 540619.75 | K49: 189216.91 | L49: 30000 | M49: 779724.08 | N49: =M49*0.35/3 -> 90967.809 | O49: 6666.67 | P49: 41667 | R49: 2500 | Z49: 2500 | AM49: =M49*0.02 -> 15594.482 | AN49: 500 | BA49: 0 | BC49: 5000 | BD49: 10000 | BE49: 3500 | BH49: =BL49*0.02 -> 18480.511 | BK49: 156079.57 | BL49: =M49+N49+O49+P49+R49+S49+T49+U49+V49+W49+Y49+Z49+AA49 -> 924025.56 | BM49: =AI49+AJ49+AK49+AL49+AM49+AN49+AP49++AQ49+AR49+AS49+AT49+AU49+AV49+AW49+AX49+AY49+AZ49+BA49+BB49+BC49+BD49+BE49+BG49+BH49+BK49 -> 209154.56 | BP49: =BL49-BM49 -> 714871 | BQ49: =BL49*12 -> 11088307 | BR49: =200000+(0.2*BQ49) -> 2417661.3 | BS49: =BI49*12 -> 0 | BT49: =SUM(BR49:BS49) -> 2417661.3 | BU49: =+BQ49-BT49 -> 8670645.4 | BW49: =IF((BU49>0),(IF((BU49>300000),(300000*7%),(BU49*7%))),(BQ49*1%)) -> 21000 | BX49: =IF((BU49-300000)>0,(IF((BU49>600000),(300000*11%),((BU49-300000)*11%))),("")) -> 33000 | BY49: =IF(((BU49-600000)>0),(IF((BU49>1100000),(500000*15%),((BU49-600000)*15%))),("")) -> 75000 | BZ49: =IF(((BU49-(1100000))>0),(IF((BU49>(1600000)),((500000)*19%),((BU49-(1100000))*19%))),("")) -> 95000 | CA49: =IF(((BU49-(1600000))>0),(IF((BU49>(3200000)),((1600000)*21%),((BU49-(1600000))*21%))),("")) -> 336000 | CB49: =IF(((BU49-(3200000))>0),(IF((BU49>(3200000)),((BU49-(3200000))*24%),(0))),("")) -> 1312954.9 | CC49: =SUM(BW49:CB49) -> 1872954.9 | CD49: =1%*BQ49 -> 110883.07 | CE49: =MAX(CC49:CD49) -> 1872954.9 | CF49: =+CE49/12 -> 156079.57
A50: 47 | B50: GOIN LINDA | C50: LINGUISTICS AND NIGERIAN LANGUAGES | D50: ADJUNCT SENIOR LECTURER | E50: CONUAS 5/13 | F50: FIRST | G50: 2019013002 | H50: 4935269 | I50: 4935269 | J50: 191627.63 | L50: 15000 | M50: =544090.5/2 -> 272045.25 | R50: 2500 | Z50: 2500 | AM50: =M50*0.02 -> 5440.905 | AN50: 500 | AS50: 1000 | BA50: 0 | BE50: 3500 | BH50: =BL50*0.02 -> 5540.905 | BK50: 33710.27 | BL50: =M50+N50+O50+P50+R50+S50+T50+U50+V50+W50+Y50+Z50+AA50 -> 277045.25 | BM50: =AI50+AJ50+AK50+AL50+AM50+AN50+AP50++AQ50+AR50+AS50+AT50+AU50+AV50+AW50+AX50+AY50+AZ50+BA50+BB50+BC50+BD50+BE50+BG50+BH50+BK50 -> 49692.08 | BP50: =BL50-BM50 -> 227353.17 | BQ50: =BL50*12 -> 3324543 | BR50: =200000+(0.2*BQ50) -> 864908.6 | BS50: =BI50*12 -> 0 | BT50: =SUM(BR50:BS50) -> 864908.6 | BU50: =+BQ50-BT50 -> 2459634.4 | BW50: =IF((BU50>0),(IF((BU50>300000),(300000*7%),(BU50*7%))),(BQ50*1%)) -> 21000 | BX50: =IF((BU50-300000)>0,(IF((BU50>600000),(300000*11%),((BU50-300000)*11%))),("")) -> 33000 | BY50: =IF(((BU50-600000)>0),(IF((BU50>1100000),(500000*15%),((BU50-600000)*15%))),("")) -> 75000 | BZ50: =IF(((BU50-(1100000))>0),(IF((BU50>(1600000)),((500000)*19%),((BU50-(1100000))*19%))),("")) -> 95000 | CA50: =IF(((BU50-(1600000))>0),(IF((BU50>(3200000)),((1600000)*21%),((BU50-(1600000))*21%))),("")) -> 180523.22 | CB50: =IF(((BU50-(3200000))>0),(IF((BU50>(3200000)),((BU50-(3200000))*24%),(0))),("")) | CC50: =SUM(BW50:CB50) -> 404523.22 | CD50: =1%*BQ50 -> 33245.43 | CE50: =MAX(CC50:CD50) -> 404523.22 | CF50: =+CE50/12 -> 33710.269
A51: 48 | B51: TORUPERE KOROYE | C51: EDUCATIONAL MANAGEMENT | D51: Ag. DEAN ARTS AND EDUCATION | E51: CONUAS 6/8 | F51: FIDELITY | G51: 4021365312 | H51: 4935269 | I51: 5086727 | J51: 411242.42 | K51: 102810.6 | L51: 30000 | M51: 575681.83 | N51: =M51*0.35/3 -> 67162.88 | O51: 5000 | P51: =P49 -> 41667 | R51: 2500 | Z51: 2500 | AM51: =M51*0.02 -> 11513.637 | AN51: 500 | AS51: 1000 | BA51: 75000 | BE51: 2000 | BH51: =BL51*0.02 -> 13890.234 | BK51: 112012.92 | BL51: =M51+N51+O51+P51+R51+S51+T51+U51+V51+W51+Y51+Z51+AA51 -> 694511.71 | BM51: =AI51+AJ51+AK51+AL51+AM51+AN51+AP51++AQ51+AR51+AS51+AT51+AU51+AV51+AW51+AX51+AY51+AZ51+BA51+BB51+BC51+BD51+BE51+BG51+BH51+BK51 -> 215916.79 | BP51: =BL51-BM51 -> 478594.92 | BQ51: =BL51*12 -> 8334140.5 | BR51: =200000+(0.2*BQ51) -> 1866828.1 | BS51: =BI51*12 -> 0 | BT51: =SUM(BR51:BS51) -> 1866828.1 | BU51: =+BQ51-BT51 -> 6467312.4 | BW51: =IF((BU51>0),(IF((BU51>300000),(300000*7%),(BU51*7%))),(BQ51*1%)) -> 21000 | BX51: =IF((BU51-300000)>0,(IF((BU51>600000),(300000*11%),((BU51-300000)*11%))),("")) -> 33000 | BY51: =IF(((BU51-600000)>0),(IF((BU51>1100000),(500000*15%),((BU51-600000)*15%))),("")) -> 75000 | BZ51: =IF(((BU51-(1100000))>0),(IF((BU51>(1600000)),((500000)*19%),((BU51-(1100000))*19%))),("")) -> 95000 | CA51: =IF(((BU51-(1600000))>0),(IF((BU51>(3200000)),((1600000)*21%),((BU51-(1600000))*21%))),("")) -> 336000 | CB51: =IF(((BU51-(3200000))>0),(IF((BU51>(3200000)),((BU51-(3200000))*24%),(0))),("")) -> 784154.98 | CC51: =SUM(BW51:CB51) -> 1344155 | CD51: =1%*BQ51 -> 83341.405 | CE51: =MAX(CC51:CD51) -> 1344155 | CF51: =+CE51/12 -> 112012.92
A52: 49 | B52: UZAKAH RICHARD PREYE | C52: BIOLOGICAL SCIENCE | D52: ASSOCIATE PROFESSOR | E52: CONUAS 6/5 | F52: FIRST | G52: 2003315491 | H52: 4181658 | I52: 4327636 | J52: 360636.33 | K52: 90159.083 | L52: 30000 | M52: 528238.58 | N52: =M52*0.35/3 -> 61627.834 | O52: 5000 | R52: 2500 | Z52: 2500 | AM52: =M52*0.02 -> 10564.772 | AN52: 500 | AQ52: 1000 | BA52: 197709 | BC52: 5000 | BD52: 10000 | BE52: 2000 | BH52: =BL52*0.02 -> 11997.328 | BK52: 93841.02 | BL52: =M52+N52+O52+P52+R52+S52+T52+U52+V52+W52+Y52+Z52+AA52 -> 599866.41 | BM52: =AI52+AJ52+AK52+AL52+AM52+AN52+AP52++AQ52+AR52+AS52+AT52+AU52+AV52+AW52+AX52+AY52+AZ52+BA52+BB52+BC52+BD52+BE52+BG52+BH52+BK52 -> 332612.12 | BP52: =BL52-BM52 -> 267254.29 | BQ52: =BL52*12 -> 7198397 | BR52: =200000+(0.2*BQ52) -> 1639679.4 | BS52: =BI52*12 -> 0 | BT52: =SUM(BR52:BS52) -> 1639679.4 | BU52: =+BQ52-BT52 -> 5558717.6 | BW52: =IF((BU52>0),(IF((BU52>300000),(300000*7%),(BU52*7%))),(BQ52*1%)) -> 21000 | BX52: =IF((BU52-300000)>0,(IF((BU52>600000),(300000*11%),((BU52-300000)*11%))),("")) -> 33000 | BY52: =IF(((BU52-600000)>0),(IF((BU52>1100000),(500000*15%),((BU52-600000)*15%))),("")) -> 75000 | BZ52: =IF(((BU52-(1100000))>0),(IF((BU52>(1600000)),((500000)*19%),((BU52-(1100000))*19%))),("")) -> 95000 | CA52: =IF(((BU52-(1600000))>0),(IF((BU52>(3200000)),((1600000)*21%),((BU52-(1600000))*21%))),("")) -> 336000 | CB52: =IF(((BU52-(3200000))>0),(IF((BU52>(3200000)),((BU52-(3200000))*24%),(0))),("")) -> 566092.22 | CC52: =SUM(BW52:CB52) -> 1126092.2 | CD52: =1%*BQ52 -> 71983.97 | CE52: =MAX(CC52:CD52) -> 1126092.2 | CF52: =+CE52/12 -> 93841.018
A53: 50 | B53: SUNDAY DUTIMIARIYE ABRAYE | C53: THEATRE ARTS | D53: ADJUNCT PROFESSOR | E53: CONUAS 7/1 | F53: UBA | G53: 2031755814 | H53: 4783091 | J53: =422768.33/2 -> 211384.17 | K53: 73984.46 | L53: 15000 | M53: =SUM(J53:L53) -> 300368.62 | R53: 2500 | Z53: 2500 | AM53: =M53*0.02 -> 6007.3725 | AN53: 500 | AS53: 1000 | BA53: 0 | BE53: 1750 | BH53: =BL53*0.02 -> 6107.3725 | BK53: 38533.5 | BL53: =M53+N53+O53+P53+R53+S53+T53+U53+V53+W53+Y53+Z53+AA53 -> 305368.62 | BM53: =AI53+AJ53+AK53+AL53+AM53+AN53+AP53++AQ53+AR53+AS53+AT53+AU53+AV53+AW53+AX53+AY53+AZ53+BA53+BB53+BC53+BD53+BE53+BG53+BH53+BK53 -> 53898.245 | BP53: =BL53-BM53 -> 251470.38 | BQ53: =BL53*12 -> 3664423.5 | BR53: =200000+(0.2*BQ53) -> 932884.7 | BS53: =BI53*12 -> 0 | BT53: =SUM(BR53:BS53) -> 932884.7 | BU53: =+BQ53-BT53 -> 2731538.8 | BW53: =IF((BU53>0),(IF((BU53>300000),(300000*7%),(BU53*7%))),(BQ53*1%)) -> 21000 | BX53: =IF((BU53-300000)>0,(IF((BU53>600000),(300000*11%),((BU53-300000)*11%))),("")) -> 33000 | BY53: =IF(((BU53-600000)>0),(IF((BU53>1100000),(500000*15%),((BU53-600000)*15%))),("")) -> 75000 | BZ53: =IF(((BU53-(1100000))>0),(IF((BU53>(1600000)),((500000)*19%),((BU53-(1100000))*19%))),("")) -> 95000 | CA53: =IF(((BU53-(1600000))>0),(IF((BU53>(3200000)),((1600000)*21%),((BU53-(1600000))*21%))),("")) -> 237623.15 | CB53: =IF(((BU53-(3200000))>0),(IF((BU53>(3200000)),((BU53-(3200000))*24%),(0))),("")) | CC53: =SUM(BW53:CB53) -> 461623.15 | CD53: =1%*BQ53 -> 36644.235 | CE53: =MAX(CC53:CD53) -> 461623.15 | CF53: =+CE53/12 -> 38468.596
A54: 51 | B54: COURT OGELE TIMIEPERE | C54: BUSINESS ADMINISTRATION | D54: ASSOCIATE PROFESSOR | E54: CONUAS 6/3 | F54: GTB | G54: 0264701713 | H54: 3950454 | I54: 4327636 | J54: 360636.33 | K54: 90159.083 | L54: 30000 | M54: 496609.83 | N54: =M54*0.35/3 -> 57937.813 | O54: 5000 | P54: =P51 -> 41667 | R54: 2500 | Z54: 2500 | AA54: 30000 | AM54: =M54*0.02 -> 9932.1966 | AN54: 500 | AP54: 30000 | AV54: 10000 | AW54: 1000 | BA54: 40000 | BC54: 3750 | BD54: 7500 | BE54: 2000 | BH54: =BL54*0.02 -> 12724.293 | BK54: 100819.88 | BL54: =M54+N54+O54+P54+R54+S54+T54+U54+V54+W54+Y54+Z54+AA54 -> 636214.64 | BM54: =AI54+AJ54+AK54+AL54+AM54+AN54+AP54++AQ54+AR54+AS54+AT54+AU54+AV54+AW54+AX54+AY54+AZ54+BA54+BB54+BC54+BD54+BE54+BG54+BH54+BK54 -> 218226.37 | BP54: =BL54-BM54 -> 417988.27 | BQ54: =BL54*12 -> 7634575.7 | BR54: =200000+(0.2*BQ54) -> 1726915.1 | BS54: =BI54*12 -> 0 | BT54: =SUM(BR54:BS54) -> 1726915.1 | BU54: =+BQ54-BT54 -> 5907660.6 | BW54: =IF((BU54>0),(IF((BU54>300000),(300000*7%),(BU54*7%))),(BQ54*1%)) -> 21000 | BX54: =IF((BU54-300000)>0,(IF((BU54>600000),(300000*11%),((BU54-300000)*11%))),("")) -> 33000 | BY54: =IF(((BU54-600000)>0),(IF((BU54>1100000),(500000*15%),((BU54-600000)*15%))),("")) -> 75000 | BZ54: =IF(((BU54-(1100000))>0),(IF((BU54>(1600000)),((500000)*19%),((BU54-(1100000))*19%))),("")) -> 95000 | CA54: =IF(((BU54-(1600000))>0),(IF((BU54>(3200000)),((1600000)*21%),((BU54-(1600000))*21%))),("")) -> 336000 | CB54: =IF(((BU54-(3200000))>0),(IF((BU54>(3200000)),((BU54-(3200000))*24%),(0))),("")) -> 649838.54 | CC54: =SUM(BW54:CB54) -> 1209838.5 | CD54: =1%*BQ54 -> 76345.757 | CE54: =MAX(CC54:CD54) -> 1209838.5 | CF54: =+CE54/12 -> 100819.88
A55: 52 | B55: ABEKI SUNNY OKORO | C55: Ag. DEAN FACULTY OF MANAGEMENT SCIENCE (PUBLIC ADMINISTRATION) | D55: FULL TIME PROFESSOR | E55: CONUAS 7/2 | F55: UBA | G55: 2008477330 | H55: 4432861 | I55: 5073220 | J55: 369405.08 | K55: 92351.27 | L55: 30000 | M55: 620624.58 | N55: =M55*0.35/3 -> 72406.201 | O55: 8333.33 | P55: 41667 | R55: 2500 | Z55: 2500 | AM55: =M55*0.02 -> 12412.492 | AN55: 500 | AP55: 11000 | AW55: 1000 | BA55: 200303.36 | BE55: 2000 | BH55: =BL55*0.02 -> 14960.622 | BK55: 121648.64 | BL55: =M55+N55+O55+P55+R55+S55+T55+U55+V55+W55+Y55+Z55+AA55 -> 748031.11 | BM55: =AI55+AJ55+AK55+AL55+AM55+AN55+AP55++AQ55+AR55+AS55+AT55+AU55+AV55+AW55+AX55+AY55+AZ55+BA55+BB55+BC55+BD55+BE55+BG55+BH55+BK55 -> 363825.12 | BP55: =BL55-BM55 -> 384205.99 | BQ55: =BL55*12 -> 8976373.3 | BR55: =200000+(0.2*BQ55) -> 1995274.7 | BS55: =BI55*12 -> 0 | BT55: =SUM(BR55:BS55) -> 1995274.7 | BU55: =+BQ55-BT55 -> 6981098.7 | BW55: =IF((BU55>0),(IF((BU55>300000),(300000*7%),(BU55*7%))),(BQ55*1%)) -> 21000 | BX55: =IF((BU55-300000)>0,(IF((BU55>600000),(300000*11%),((BU55-300000)*11%))),("")) -> 33000 | BY55: =IF(((BU55-600000)>0),(IF((BU55>1100000),(500000*15%),((BU55-600000)*15%))),("")) -> 75000 | BZ55: =IF(((BU55-(1100000))>0),(IF((BU55>(1600000)),((500000)*19%),((BU55-(1100000))*19%))),("")) -> 95000 | CA55: =IF(((BU55-(1600000))>0),(IF((BU55>(3200000)),((1600000)*21%),((BU55-(1600000))*21%))),("")) -> 336000 | CB55: =IF(((BU55-(3200000))>0),(IF((BU55>(3200000)),((BU55-(3200000))*24%),(0))),("")) -> 907463.68 | CC55: =SUM(BW55:CB55) -> 1467463.7 | CD55: =1%*BQ55 -> 89763.733 | CE55: =MAX(CC55:CD55) -> 1467463.7 | CF55: =+CE55/12 -> 122288.64
A56: 53 | B56: ELEKE MELBOUNE EBIMIE | C56: INDUSTRAL RELATION AND PERSONAL MGT | D56: LECTURER I | E56: CONUAS 4/5 | F56: GTB | G56: 0042414976 | H56: 2254203 | I56: 2688069 | J56: 224005.75 | K56: 56001.438 | L56: 30000 | M56: 319130.33 | N56: =M56*0.35/3 -> 37231.872 | O56: 5000 | P56: 41667 | R56: 2500 | Z56: 2500 | AM56: =M56*0.02 -> 6382.6066 | AN56: 500 | AW56: 1000 | BA56: 0 | BE56: 1500 | BH56: =BL56*0.02 -> 8160.584 | BK56: 57008.27 | BL56: =M56+N56+O56+P56+R56+S56+T56+U56+V56+W56+Y56+Z56+AA56 -> 408029.2 | BM56: =AI56+AJ56+AK56+AL56+AM56+AN56+AP56++AQ56+AR56+AS56+AT56+AU56+AV56+AW56+AX56+AY56+AZ56+BA56+BB56+BC56+BD56+BE56+BG56+BH56+BK56 -> 74551.461 | BP56: =BL56-BM56 -> 333477.74 | BQ56: =BL56*12 -> 4896350.4 | BR56: =200000+(0.2*BQ56) -> 1179270.1 | BS56: =BI56*12 -> 0 | BT56: =SUM(BR56:BS56) -> 1179270.1 | BU56: =+BQ56-BT56 -> 3717080.3 | BW56: =IF((BU56>0),(IF((BU56>300000),(300000*7%),(BU56*7%))),(BQ56*1%)) -> 21000 | BX56: =IF((BU56-300000)>0,(IF((BU56>600000),(300000*11%),((BU56-300000)*11%))),("")) -> 33000 | BY56: =IF(((BU56-600000)>0),(IF((BU56>1100000),(500000*15%),((BU56-600000)*15%))),("")) -> 75000 | BZ56: =IF(((BU56-(1100000))>0),(IF((BU56>(1600000)),((500000)*19%),((BU56-(1100000))*19%))),("")) -> 95000 | CA56: =IF(((BU56-(1600000))>0),(IF((BU56>(3200000)),((1600000)*21%),((BU56-(1600000))*21%))),("")) -> 336000 | CB56: =IF(((BU56-(3200000))>0),(IF((BU56>(3200000)),((BU56-(3200000))*24%),(0))),("")) -> 124099.28 | CC56: =SUM(BW56:CB56) -> 684099.28 | CD56: =1%*BQ56 -> 48963.504 | CE56: =MAX(CC56:CD56) -> 684099.28 | CF56: =+CE56/12 -> 57008.273
A57: 54 | B57: OKUTALUKWE TIMOTHY CHIDEIEBERE | C57: POLITICAL SCIENCE | D57: LECTURER I | E57: CONUAS 4/3 | F57: UNION | G57: 0030658333 | H57: =M57*12 -> 3610607 | I57: 2688069 | J57: 224005.75 | K57: 56001.438 | L57: 30000 | M57: 300883.92 | N57: =M57*0.35/3 -> 35103.124 | O57: 5000 | R57: 2500 | Z57: 2500 | AM57: =M57*0.02 -> 6017.6784 | AN57: 500 | AX57: 1000 | BA57: 75834 | BC57: 3750 | BD57: 7500 | BE57: 1500 | BH57: =BL57*0.02 -> 6919.7409 | BK57: 45292.49 | BL57: =M57+N57+O57+P57+R57+S57+T57+U57+V57+W57+Y57+Z57+AA57 -> 345987.04 | BM57: =AI57+AJ57+AK57+AL57+AM57+AN57+AP57++AQ57+AR57+AS57+AT57+AU57+AV57+AW57+AX57+AY57+AZ57+BA57+BB57+BC57+BD57+BE57+BG57+BH57+BK57 -> 148313.91 | BP57: =BL57-BM57 -> 197673.13 | BQ57: =BL57*12 -> 4151844.5 | BR57: =200000+(0.2*BQ57) -> 1030368.9 | BS57: =BI57*12 -> 0 | BT57: =SUM(BR57:BS57) -> 1030368.9 | BU57: =+BQ57-BT57 -> 3121475.6 | BW57: =IF((BU57>0),(IF((BU57>300000),(300000*7%),(BU57*7%))),(BQ57*1%)) -> 21000 | BX57: =IF((BU57-300000)>0,(IF((BU57>600000),(300000*11%),((BU57-300000)*11%))),("")) -> 33000 | BY57: =IF(((BU57-600000)>0),(IF((BU57>1100000),(500000*15%),((BU57-600000)*15%))),("")) -> 75000 | BZ57: =IF(((BU57-(1100000))>0),(IF((BU57>(1600000)),((500000)*19%),((BU57-(1100000))*19%))),("")) -> 95000 | CA57: =IF(((BU57-(1600000))>0),(IF((BU57>(3200000)),((1600000)*21%),((BU57-(1600000))*21%))),("")) -> 319509.88 | CB57: =IF(((BU57-(3200000))>0),(IF((BU57>(3200000)),((BU57-(3200000))*24%),(0))),("")) | CC57: =SUM(BW57:CB57) -> 543509.88 | CD57: =1%*BQ57 -> 41518.445 | CE57: =MAX(CC57:CD57) -> 543509.88 | CF57: =+CE57/12 -> 45292.49
A58: 55 | B58: GOVERNOR ROSEMARY EBIERE | C58: MASS COMMUNICATION | D58: SENIOR LECTURER | E58: CONUAS 5/3 | F58: GTB | G58: 0123891546 | H58: =H80 -> 2600486 | I58: 2688069 | J58: 224005.75 | K58: 56001.438 | L58: 30000 | M58: 413255.25 | N58: =M58*0.35/3 -> 48213.113 | O58: 5000 | R58: 2500 | Z58: 2500 | AM58: =M58*0.02 -> 8265.105 | AN58: 500 | AX58: 1000 | AY58: 2000 | BA58: 350000 | BC58: 5000 | BD58: 10000 | BE58: 1500 | BH58: =BL58*0.02 -> 9429.3672 | BK58: 69198.59 | BL58: =M58+N58+O58+P58+R58+S58+T58+U58+V58+W58+Y58+Z58+AA58 -> 471468.36 | BM58: =AI58+AJ58+AK58+AL58+AM58+AN58+AP58++AQ58+AR58+AS58+AT58+AU58+AV58+AW58+AX58+AY58+AZ58+BA58+BB58+BC58+BD58+BE58+BG58+BH58+BK58 -> 456893.06 | BP58: =BL58-BM58 -> 14575.3 | BQ58: =BL58*12 -> 5657620.3 | BR58: =200000+(0.2*BQ58) -> 1331524.1 | BS58: =BI58*12 -> 0 | BT58: =SUM(BR58:BS58) -> 1331524.1 | BU58: =+BQ58-BT58 -> 4326096.3 | BW58: =IF((BU58>0),(IF((BU58>300000),(300000*7%),(BU58*7%))),(BQ58*1%)) -> 21000 | BX58: =IF((BU58-300000)>0,(IF((BU58>600000),(300000*11%),((BU58-300000)*11%))),("")) -> 33000 | BY58: =IF(((BU58-600000)>0),(IF((BU58>1100000),(500000*15%),((BU58-600000)*15%))),("")) -> 75000 | BZ58: =IF(((BU58-(1100000))>0),(IF((BU58>(1600000)),((500000)*19%),((BU58-(1100000))*19%))),("")) -> 95000 | CA58: =IF(((BU58-(1600000))>0),(IF((BU58>(3200000)),((1600000)*21%),((BU58-(1600000))*21%))),("")) -> 336000 | CB58: =IF(((BU58-(3200000))>0),(IF((BU58>(3200000)),((BU58-(3200000))*24%),(0))),("")) -> 270263.11 | CC58: =SUM(BW58:CB58) -> 830263.11 | CD58: =1%*BQ58 -> 56576.204 | CE58: =MAX(CC58:CD58) -> 830263.11 | CF58: =+CE58/12 -> 69188.592
A59: 56 | B59: ANEM IGIRIGI KOKINBO | C59: ANIMAL PRODUCTION AND HEALTH | D59: LECTURER I | E59: CONUAS 3/5 | F59: GTB | G59: 0236337085 | H59: 2048214 | I59: 2144788 | J59: 174173.42 | K59: 43543.354 | L59: 30000 | M59: 253415.5 | N59: =M59*0.35/3 -> 29565.142 | O59: 5000 | R59: 2500 | Z59: 2500 | AM59: =M59*0.02 -> 5068.31 | AN59: 500 | BA59: 30834 | BE59: 1000 | BH59: =BL59*0.02 -> 5859.6128 | BK59: 36387.41 | BL59: =M59+N59+O59+P59+R59+S59+T59+U59+V59+W59+Y59+Z59+AA59 -> 292980.64 | BM59: =AI59+AJ59+AK59+AL59+AM59+AN59+AP59++AQ59+AR59+AS59+AT59+AU59+AV59+AW59+AX59+AY59+AZ59+BA59+BB59+BC59+BD59+BE59+BG59+BH59+BK59 -> 79649.333 | BP59: =BL59-BM59 -> 213331.31 | BQ59: =BL59*12 -> 3515767.7 | BR59: =200000+(0.2*BQ59) -> 903153.54 | BS59: =BI59*12 -> 0 | BT59: =SUM(BR59:BS59) -> 903153.54 | BU59: =+BQ59-BT59 -> 2612614.2 | BW59: =IF((BU59>0),(IF((BU59>300000),(300000*7%),(BU59*7%))),(BQ59*1%)) -> 21000 | BX59: =IF((BU59-300000)>0,(IF((BU59>600000),(300000*11%),((BU59-300000)*11%))),("")) -> 33000 | BY59: =IF(((BU59-600000)>0),(IF((BU59>1100000),(500000*15%),((BU59-600000)*15%))),("")) -> 75000 | BZ59: =IF(((BU59-(1100000))>0),(IF((BU59>(1600000)),((500000)*19%),((BU59-(1100000))*19%))),("")) -> 95000 | CA59: =IF(((BU59-(1600000))>0),(IF((BU59>(3200000)),((1600000)*21%),((BU59-(1600000))*21%))),("")) -> 212648.97 | CB59: =IF(((BU59-(3200000))>0),(IF((BU59>(3200000)),((BU59-(3200000))*24%),(0))),("")) | CC59: =SUM(BW59:CB59) -> 436648.97 | CD59: =1%*BQ59 -> 35157.677 | CE59: =MAX(CC59:CD59) -> 436648.97 | CF59: =+CE59/12 -> 36387.414
A60: 57 | B60: TAMBOU TAMBRA JOSEPH | C60: PUBLIC ADMINISTRATION | D60: LECTURER I | E60: CONUAS 4/5 | F60: FIDELITY | G60: 6019233197 | H60: =H58 -> 2600486 | I60: 2688069 | J60: 224005.75 | K60: 56001.438 | L60: 30000 | M60: 319130.33 | N60: =M60*0.35/3 -> 37231.872 | O60: 5000 | P60: =P40 -> 20833.33 | R60: 2500 | Z60: 2500 | AM60: =M60*0.02 -> 6382.6066 | AN60: 500 | AP60: 52250 | AW60: 1000 | BA60: 121875 | BC60: 3750 | BD60: 7500 | BE60: 1500 | BH60: =BL60*0.02 -> 7743.9106 | BK60: 53008.21 | BL60: =M60+N60+O60+P60+R60+S60+T60+U60+V60+W60+Y60+Z60+AA60 -> 387195.53 | BM60: =AI60+AJ60+AK60+AL60+AM60+AN60+AP60++AQ60+AR60+AS60+AT60+AU60+AV60+AW60+AX60+AY60+AZ60+BA60+BB60+BC60+BD60+BE60+BG60+BH60+BK60 -> 255509.73 | BP60: =BL60-BM60 -> 131685.8 | BQ60: =BL60*12 -> 4646346.4 | BR60: =200000+(0.2*BQ60) -> 1129269.3 | BS60: =BI60*12 -> 0 | BT60: =SUM(BR60:BS60) -> 1129269.3 | BU60: =+BQ60-BT60 -> 3517077.1 | BW60: =IF((BU60>0),(IF((BU60>300000),(300000*7%),(BU60*7%))),(BQ60*1%)) -> 21000 | BX60: =IF((BU60-300000)>0,(IF((BU60>600000),(300000*11%),((BU60-300000)*11%))),("")) -> 33000 | BY60: =IF(((BU60-600000)>0),(IF((BU60>1100000),(500000*15%),((BU60-600000)*15%))),("")) -> 75000 | BZ60: =IF(((BU60-(1100000))>0),(IF((BU60>(1600000)),((500000)*19%),((BU60-(1100000))*19%))),("")) -> 95000 | CA60: =IF(((BU60-(1600000))>0),(IF((BU60>(3200000)),((1600000)*21%),((BU60-(1600000))*21%))),("")) -> 336000 | CB60: =IF(((BU60-(3200000))>0),(IF((BU60>(3200000)),((BU60-(3200000))*24%),(0))),("")) -> 76098.505 | CC60: =SUM(BW60:CB60) -> 636098.51 | CD60: =1%*BQ60 -> 46463.464 | CE60: =MAX(CC60:CD60) -> 636098.51 | CF60: =+CE60/12 -> 53008.209
A61: 58 | B61: ODOGU TERRY KEME ZUODE | C61: ACCOUNTING | D61: SENIOR LECTURER | E61: CONUAS 5/7 | F61: STERLING | G61: 0073932676 | H61: 3125980 | I61: 3125980 | J61: 260498.33 | K61: 65124.583 | L61: 30000 | M61: 465589.33 | N61: =M61*0.35/3 -> 54318.755 | O61: 5000 | P61: 20833.33 | R61: 2500 | Y61: 30000 | Z61: 2500 | AM61: =M61*0.02 -> 9311.7866 | AN61: 500 | AW61: 1000 | BA61: 12500 | BC61: 7500 | BD61: 15000 | BE61: 1500 | BH61: 10337.169 | BK61: 90169.018 | BL61: =M61+N61+O61+P61+R61+S61+T61+U61+V61+W61+Y61+Z61+AA61 -> 580741.42 | BM61: =AI61+AJ61+AK61+AL61+AM61+AN61+AP61++AQ61+AR61+AS61+AT61+AU61+AV61+AW61+AX61+AY61+AZ61+BA61+BB61+BC61+BD61+BE61+BG61+BH61+BK61 -> 147817.97 | BP61: =BL61-BM61 -> 432923.44 | BQ61: =BL61*12 -> 6968897 | BR61: =200000+(0.2*BQ61) -> 1593779.4 | BS61: =BI61*12 -> 0 | BT61: =SUM(BR61:BS61) -> 1593779.4 | BU61: =+BQ61-BT61 -> 5375117.6 | BW61: =IF((BU61>0),(IF((BU61>300000),(300000*7%),(BU61*7%))),(BQ61*1%)) -> 21000 | BX61: =IF((BU61-300000)>0,(IF((BU61>600000),(300000*11%),((BU61-300000)*11%))),("")) -> 33000 | BY61: =IF(((BU61-600000)>0),(IF((BU61>1100000),(500000*15%),((BU61-600000)*15%))),("")) -> 75000 | BZ61: =IF(((BU61-(1100000))>0),(IF((BU61>(1600000)),((500000)*19%),((BU61-(1100000))*19%))),("")) -> 95000 | CA61: =IF(((BU61-(1600000))>0),(IF((BU61>(3200000)),((1600000)*21%),((BU61-(1600000))*21%))),("")) -> 336000 | CB61: =IF(((BU61-(3200000))>0),(IF((BU61>(3200000)),((BU61-(3200000))*24%),(0))),("")) -> 522028.22 | CC61: =SUM(BW61:CB61) -> 1082028.2 | CD61: =1%*BQ61 -> 69688.97 | CE61: =MAX(CC61:CD61) -> 1082028.2 | CF61: =+CE61/12 -> 90169.018
A62: 59 | B62: TEKE CALYDAY ENEGBOGIENEGHA | C62: BIOLOGICAL SCIENCE | D62: LECTURER I | E62: CONUAS 4/5 | F62: UBA | G62: 2022811512 | H62: 2600486 | I62: 2688069 | J62: 224005.75 | K62: 56001.438 | L62: 30000 | M62: 319130.33 | N62: =M62*0.35/3 -> 37231.872 | O62: 5000 | P62: 20833.33 | R62: 2500 | Z62: 2500 | AM62: =M62*0.02 -> 6382.6066 | AN62: 500 | AP62: 71667 | AQ62: 1000 | BA62: 71667 | BE62: 1500 | BH62: =BL62*0.02 -> 7743.9106 | BK62: 53008.21 | BL62: =M62+N62+O62+P62+R62+S62+T62+U62+V62+W62+Y62+Z62+AA62 -> 387195.53 | BM62: =AI62+AJ62+AK62+AL62+AM62+AN62+AP62++AQ62+AR62+AS62+AT62+AU62+AV62+AW62+AX62+AY62+AZ62+BA62+BB62+BC62+BD62+BE62+BG62+BH62+BK62 -> 213468.73 | BP62: =BL62-BM62 -> 173726.8 | BQ62: =BL62*12 -> 4646346.4 | BR62: =200000+(0.2*BQ62) -> 1129269.3 | BS62: =BI62*12 -> 0 | BT62: =SUM(BR62:BS62) -> 1129269.3 | BU62: =+BQ62-BT62 -> 3517077.1 | BW62: =IF((BU62>0),(IF((BU62>300000),(300000*7%),(BU62*7%))),(BQ62*1%)) -> 21000 | BX62: =IF((BU62-300000)>0,(IF((BU62>600000),(300000*11%),((BU62-300000)*11%))),("")) -> 33000 | BY62: =IF(((BU62-600000)>0),(IF((BU62>1100000),(500000*15%),((BU62-600000)*15%))),("")) -> 75000 | BZ62: =IF(((BU62-(1100000))>0),(IF((BU62>(1600000)),((500000)*19%),((BU62-(1100000))*19%))),("")) -> 95000 | CA62: =IF(((BU62-(1600000))>0),(IF((BU62>(3200000)),((1600000)*21%),((BU62-(1600000))*21%))),("")) -> 336000 | CB62: =IF(((BU62-(3200000))>0),(IF((BU62>(3200000)),((BU62-(3200000))*24%),(0))),("")) -> 76098.505 | CC62: =SUM(BW62:CB62) -> 636098.51 | CD62: =1%*BQ62 -> 46463.464 | CE62: =MAX(CC62:CD62) -> 636098.51 | CF62: =+CE62/12 -> 53008.209
A63: 60 | B63: AKWARANDU UZOCHUKWU | C63: BANKING AND FINANCE | D63: SENIOR LECTURER | E63: CONUAS 5/1 | F63: UNION | G63: 0139319511 | H63: 2254203 | I63: 2688069 | J63: 224005.75 | K63: 56001.438 | L63: 30000 | M63: 387088.17 | N63: =M63*0.35/3 -> 45160.287 | O63: 5000 | R63: 2500 | Z63: 2500 | AM63: =M63*0.02 -> 7741.7634 | AN63: 500 | AP63: 88334 | AW63: 1000 | BA63: 50000 | BC63: 3750 | BD63: 7500 | BE63: 1500 | BH63: =BL63*0.02 -> 8844.9691 | BK63: 63578.37 | BL63: =M63+N63+O63+P63+R63+S63+T63+U63+V63+W63+Y63+Z63+AA63 -> 442248.46 | BM63: =AI63+AJ63+AK63+AL63+AM63+AN63+AP63++AQ63+AR63+AS63+AT63+AU63+AV63+AW63+AX63+AY63+AZ63+BA63+BB63+BC63+BD63+BE63+BG63+BH63+BK63 -> 232749.1 | BP63: =BL63-BM63 -> 209499.35 | BQ63: =BL63*12 -> 5306981.5 | BR63: =200000+(0.2*BQ63) -> 1261396.3 | BS63: =BI63*12 -> 0 | BT63: =SUM(BR63:BS63) -> 1261396.3 | BU63: =+BQ63-BT63 -> 4045585.2 | BW63: =IF((BU63>0),(IF((BU63>300000),(300000*7%),(BU63*7%))),(BQ63*1%)) -> 21000 | BX63: =IF((BU63-300000)>0,(IF((BU63>600000),(300000*11%),((BU63-300000)*11%))),("")) -> 33000 | BY63: =IF(((BU63-600000)>0),(IF((BU63>1100000),(500000*15%),((BU63-600000)*15%))),("")) -> 75000 | BZ63: =IF(((BU63-(1100000))>0),(IF((BU63>(1600000)),((500000)*19%),((BU63-(1100000))*19%))),("")) -> 95000 | CA63: =IF(((BU63-(1600000))>0),(IF((BU63>(3200000)),((1600000)*21%),((BU63-(1600000))*21%))),("")) -> 336000 | CB63: =IF(((BU63-(3200000))>0),(IF((BU63>(3200000)),((BU63-(3200000))*24%),(0))),("")) -> 202940.44 | CC63: =SUM(BW63:CB63) -> 762940.44 | CD63: =1%*BQ63 -> 53069.815 | CE63: =MAX(CC63:CD63) -> 762940.44 | CF63: =+CE63/12 -> 63578.37
A64: 61 | B64: NIMIZIGHA AKPOUNIMIBOFA ALI | C64: PUBLIC ADMINISTRATION | D64: LECTURER I | E64: CONUAS 4/1 | F64: STERLING | G64: 0078534068 | H64: 2035373 | I64: 2090081 | J64: 174173.42 | K64: 43543.354 | L64: 30000 | M64: 282637.75 | N64: =M64*0.35/3 -> 32974.404 | O64: 5000 | R64: 2500 | Z64: 2500 | AM64: =M64*0.02 -> 5652.755 | AN64: 500 | AW64: 1000 | BA64: 12500 | BE64: 1500 | BH64: =BL64*0.02 -> 6512.2431 | BK64: 41869.51 | BL64: =M64+N64+O64+P64+R64+S64+T64+U64+V64+W64+Y64+Z64+AA64 -> 325612.15 | BM64: =AI64+AJ64+AK64+AL64+AM64+AN64+AP64++AQ64+AR64+AS64+AT64+AU64+AV64+AW64+AX64+AY64+AZ64+BA64+BB64+BC64+BD64+BE64+BG64+BH64+BK64 -> 69534.508 | BP64: =BL64-BM64 -> 256077.65 | BQ64: =BL64*12 -> 3907345.9 | BR64: =200000+(0.2*BQ64) -> 981469.17 | BS64: =BI64*12 -> 0 | BT64: =SUM(BR64:BS64) -> 981469.17 | BU64: =+BQ64-BT64 -> 2925876.7 | BW64: =IF((BU64>0),(IF((BU64>300000),(300000*7%),(BU64*7%))),(BQ64*1%)) -> 21000 | BX64: =IF((BU64-300000)>0,(IF((BU64>600000),(300000*11%),((BU64-300000)*11%))),("")) -> 33000 | BY64: =IF(((BU64-600000)>0),(IF((BU64>1100000),(500000*15%),((BU64-600000)*15%))),("")) -> 75000 | BZ64: =IF(((BU64-(1100000))>0),(IF((BU64>(1600000)),((500000)*19%),((BU64-(1100000))*19%))),("")) -> 95000 | CA64: =IF(((BU64-(1600000))>0),(IF((BU64>(3200000)),((1600000)*21%),((BU64-(1600000))*21%))),("")) -> 278434.1 | CB64: =IF(((BU64-(3200000))>0),(IF((BU64>(3200000)),((BU64-(3200000))*24%),(0))),("")) | CC64: =SUM(BW64:CB64) -> 502434.1 | CD64: =1%*BQ64 -> 39073.459 | CE64: =MAX(CC64:CD64) -> 502434.1 | CF64: =+CE64/12 -> 41869.509
A65: 62 | B65: ALAGOA BIOBELEMOYE MINADUM | C65: BIOLOGICAL SCIENCE | D65: LECTURER I | E65: CONUAS 4/4 | F65: GTB | G65: 0125565342 | H65: 2254203 | I65: 2308911 | J65: 192409.25 | K65: 48102.312 | L65: 30000 | M65: 310007.17 | N65: =M65*0.35/3 -> 36167.503 | O65: 5000 | R65: 2500 | Z65: 2500 | AM65: =M65*0.02 -> 6200.1434 | AN65: 500 | AQ65: 1000 | AY65: 2000 | BA65: 0 | BE65: 1500 | BH65: =BL65*0.02 -> 7123.4935 | BK65: 47052.2 | BL65: =M65+N65+O65+P65+R65+S65+T65+U65+V65+W65+Y65+Z65+AA65 -> 356174.67 | BM65: =AI65+AJ65+AK65+AL65+AM65+AN65+AP65++AQ65+AR65+AS65+AT65+AU65+AV65+AW65+AX65+AY65+AZ65+BA65+BB65+BC65+BD65+BE65+BG65+BH65+BK65 -> 65375.837 | BP65: =BL65-BM65 -> 290798.84 | BQ65: =BL65*12 -> 4274096.1 | BR65: =200000+(0.2*BQ65) -> 1054819.2 | BS65: =BI65*12 -> 0 | BT65: =SUM(BR65:BS65) -> 1054819.2 | BU65: =+BQ65-BT65 -> 3219276.9 | BW65: =IF((BU65>0),(IF((BU65>300000),(300000*7%),(BU65*7%))),(BQ65*1%)) -> 21000 | BX65: =IF((BU65-300000)>0,(IF((BU65>600000),(300000*11%),((BU65-300000)*11%))),("")) -> 33000 | BY65: =IF(((BU65-600000)>0),(IF((BU65>1100000),(500000*15%),((BU65-600000)*15%))),("")) -> 75000 | BZ65: =IF(((BU65-(1100000))>0),(IF((BU65>(1600000)),((500000)*19%),((BU65-(1100000))*19%))),("")) -> 95000 | CA65: =IF(((BU65-(1600000))>0),(IF((BU65>(3200000)),((1600000)*21%),((BU65-(1600000))*21%))),("")) -> 336000 | CB65: =IF(((BU65-(3200000))>0),(IF((BU65>(3200000)),((BU65-(3200000))*24%),(0))),("")) -> 4626.447 | CC65: =SUM(BW65:CB65) -> 564626.45 | CD65: =1%*BQ65 -> 42740.961 | CE65: =MAX(CC65:CD65) -> 564626.45 | CF65: =+CE65/12 -> 47052.204
A66: 63 | B66: FELIX IZIRIN UYABARA | C66: POLITICAL SCIENCE | D66: LECTURER I | E66: CONUAS 4/4 | F66: FIRST | G66: 3050764643 | H66: 2199106 | I66: 2254203 | J66: 187850.25 | K66: 46962.562 | L66: 30000 | M66: 310007.17 | N66: =M66*0.35/3 -> 36167.503 | O66: 5000 | R66: 2500 | Z66: 2500 | AM66: =M66*0.02 -> 6200.1434 | AN66: 500 | AX66: 1000 | BA66: 0 | BE66: 1500 | BH66: =BL66*0.02 -> 7123.4935 | BK66: 47052.2 | BL66: =M66+N66+O66+P66+R66+S66+T66+U66+V66+W66+Y66+Z66+AA66 -> 356174.67 | BM66: =AI66+AJ66+AK66+AL66+AM66+AN66+AP66++AQ66+AR66+AS66+AT66+AU66+AV66+AW66+AX66+AY66+AZ66+BA66+BB66+BC66+BD66+BE66+BG66+BH66+BK66 -> 63375.837 | BP66: =BL66-BM66 -> 292798.84 | BQ66: =BL66*12 -> 4274096.1 | BR66: =200000+(0.2*BQ66) -> 1054819.2 | BS66: =BI66*12 -> 0 | BT66: =SUM(BR66:BS66) -> 1054819.2 | BU66: =+BQ66-BT66 -> 3219276.9 | BW66: =IF((BU66>0),(IF((BU66>300000),(300000*7%),(BU66*7%))),(BQ66*1%)) -> 21000 | BX66: =IF((BU66-300000)>0,(IF((BU66>600000),(300000*11%),((BU66-300000)*11%))),("")) -> 33000 | BY66: =IF(((BU66-600000)>0),(IF((BU66>1100000),(500000*15%),((BU66-600000)*15%))),("")) -> 75000 | BZ66: =IF(((BU66-(1100000))>0),(IF((BU66>(1600000)),((500000)*19%),((BU66-(1100000))*19%))),("")) -> 95000 | CA66: =IF(((BU66-(1600000))>0),(IF((BU66>(3200000)),((1600000)*21%),((BU66-(1600000))*21%))),("")) -> 336000 | CB66: =IF(((BU66-(3200000))>0),(IF((BU66>(3200000)),((BU66-(3200000))*24%),(0))),("")) -> 4626.447 | CC66: =SUM(BW66:CB66) -> 564626.45 | CD66: =1%*BQ66 -> 42740.961 | CE66: =MAX(CC66:CD66) -> 564626.45 | CF66: =+CE66/12 -> 47052.204
A67: 64 | B67: AKINOLA STELLA TONYO | C67: LINGUISTICS AND NIGERIAN LANGUAGES | D67: SENIOR LECTURER | E67: CONUAS 5/7 | F67: GTB | G67: 0039347458 | H67: 3125980 | I67: 3125980 | J67: 260498.33 | K67: 65124.583 | L67: 30000 | M67: 465589.33 | N67: =M67*0.35/3 -> 54318.755 | O67: 5000 | P67: 41667 | R67: 2500 | Z67: 2500 | AM67: =M67*0.02 -> 9311.7866 | AN67: 500 | AP67: 100000 | AS67: 1000 | AY67: 2000 | BA67: 70000 | BC67: 12500 | BD67: 25000 | BE67: 1500 | BH67: =BL67*0.02 -> 11431.502 | BK67: 88409.08 | BL67: =M67+N67+O67+P67+R67+S67+T67+U67+V67+W67+Y67+Z67+AA67 -> 571575.09 | BM67: =AI67+AJ67+AK67+AL67+AM67+AN67+AP67++AQ67+AR67+AS67+AT67+AU67+AV67+AW67+AX67+AY67+AZ67+BA67+BB67+BC67+BD67+BE67+BG67+BH67+BK67 -> 321652.37 | BP67: =BL67-BM67 -> 249922.72 | BQ67: =BL67*12 -> 6858901 | BR67: =200000+(0.2*BQ67) -> 1571780.2 | BS67: =BI67*12 -> 0 | BT67: =SUM(BR67:BS67) -> 1571780.2 | BU67: =+BQ67-BT67 -> 5287120.8 | BW67: =IF((BU67>0),(IF((BU67>300000),(300000*7%),(BU67*7%))),(BQ67*1%)) -> 21000 | BX67: =IF((BU67-300000)>0,(IF((BU67>600000),(300000*11%),((BU67-300000)*11%))),("")) -> 33000 | BY67: =IF(((BU67-600000)>0),(IF((BU67>1100000),(500000*15%),((BU67-600000)*15%))),("")) -> 75000 | BZ67: =IF(((BU67-(1100000))>0),(IF((BU67>(1600000)),((500000)*19%),((BU67-(1100000))*19%))),("")) -> 95000 | CA67: =IF(((BU67-(1600000))>0),(IF((BU67>(3200000)),((1600000)*21%),((BU67-(1600000))*21%))),("")) -> 336000 | CB67: =IF(((BU67-(3200000))>0),(IF((BU67>(3200000)),((BU67-(3200000))*24%),(0))),("")) -> 500909 | CC67: =SUM(BW67:CB67) -> 1060909 | CD67: =1%*BQ67 -> 68589.01 | CE67: =MAX(CC67:CD67) -> 1060909 | CF67: =+CE67/12 -> 88409.083 | CN67: DIRECTORS ALLOWANCE ADDED
A68: 65 | B68: ROSE BINI OKIY | C68: EDUCATIONAL MANAGEMENT | D68: PROFESSOR | E68: CONUAS 7/2 SP | F68: GTB | G68: 0255024937 | J68: 555351.17 | K68: 194372.91 | L68: 30000 | M68: =SUM(J68:L68) -> 779724.08 | N68: =M68*0.35/3 -> 90967.809 | O68: =8333.33 -> 8333.33 | P68: 41667 | R68: 2500 | Z68: 2500 | AM68: =M68*0.02 -> 15594.482 | AN68: 500 | AS68: 1000 | AY68: 2000 | BA68: 10000 | BC68: 7500 | BD68: 15000 | BE68: 3500 | BH68: =BL68*0.02 -> 18513.844 | BK68: 156399.57 | BL68: =M68+N68+O68+P68+R68+S68+T68+U68+V68+W68+Y68+Z68+AA68 -> 925692.22 | BM68: =AI68+AJ68+AK68+AL68+AM68+AN68+AP68++AQ68+AR68+AS68+AT68+AU68+AV68+AW68+AX68+AY68+AZ68+BA68+BB68+BC68+BD68+BE68+BG68+BH68+BK68 -> 230007.9 | BP68: =BL68-BM68 -> 695684.32 | BQ68: =BL68*12 -> 11108307 | BR68: =200000+(0.2*BQ68) -> 2421661.3 | BS68: =BI68*12 -> 0 | BT68: =SUM(BR68:BS68) -> 2421661.3 | BU68: =+BQ68-BT68 -> 8686645.3 | BW68: =IF((BU68>0),(IF((BU68>300000),(300000*7%),(BU68*7%))),(BQ68*1%)) -> 21000 | BX68: =IF((BU68-300000)>0,(IF((BU68>600000),(300000*11%),((BU68-300000)*11%))),("")) -> 33000 | BY68: =IF(((BU68-600000)>0),(IF((BU68>1100000),(500000*15%),((BU68-600000)*15%))),("")) -> 75000 | BZ68: =IF(((BU68-(1100000))>0),(IF((BU68>(1600000)),((500000)*19%),((BU68-(1100000))*19%))),("")) -> 95000 | CA68: =IF(((BU68-(1600000))>0),(IF((BU68>(3200000)),((1600000)*21%),((BU68-(1600000))*21%))),("")) -> 336000 | CB68: =IF(((BU68-(3200000))>0),(IF((BU68>(3200000)),((BU68-(3200000))*24%),(0))),("")) -> 1316794.9 | CC68: =SUM(BW68:CB68) -> 1876794.9 | CD68: =1%*BQ68 -> 111083.07 | CE68: =MAX(CC68:CD68) -> 1876794.9 | CF68: =+CE68/12 -> 156399.57
A69: 66 | B69: SOLOMON TAMARABRAKEMI EBOBRAH | C69: VICE-CHANCELLOR | D69: VICE-CHANCELLOR | E69: SP | F69: GTB | G69: 0106451794 | M69: 1000000 | N69: =M69*0.35 -> 350000 | R69: 2500 | U69: 250000 | Z69: 2500 | AA69: 62500 | AM69: =M69*0.02 -> 20000 | AN69: 500 | AV69: 5000 | BA69: 100000 | BC69: =M69*0.04 -> 40000 | BE69: 3500 | BH69: =BL69*0.02 -> 33350 | BK69: ='[2]TEACHING STAFF'!$BA$74 -> 298420.27 | BL69: =M69+N69+O69+P69+R69+S69+T69+U69+V69+W69+Y69+Z69+AA69 -> 1667500 | BM69: =AI69+AJ69+AK69+AL69+AM69+AN69+AP69++AQ69+AR69+AS69+AT69+AU69+AV69+AW69+AX69+AY69+AZ69+BA69+BB69+BC69+BD69+BE69+BG69+BH69+BK69 -> 500770.27 | BP69: =BL69-BM69 -> 1166729.7
A70: 67 | B70: AUGUSTINE ADINOYI MATHEW | C70: CROP SOIL AND PEST MGT | D70: LECTURER I | E70: CONUAS 4/3 | F70: GTB | G70: 0226553877 | H70: 2425322 | I70: 2512904 | J70: 209408.67 | K70: 52352.167 | L70: 30000 | M70: 300883.92 | N70: =M70*0.35/3 -> 35103.124 | O70: 5000 | R70: 2500 | S70: 145880.41 | Z70: 2500 | AI70: 25000 | AM70: =M70*0.02 -> 6017.6784 | AN70: 500 | AV70: 5000 | BA70: 76848.955 | BC70: 7500 | BD70: 15000 | BE70: 1500 | BH70: =BL70*0.02 -> 9837.3491 | BK70: 73105.22 | BL70: =M70+N70+O70+P70+R70+S70+T70+U70+V70+W70+Y70+Z70+AA70 -> 491867.45 | BM70: =AI70+AJ70+AK70+AL70+AM70+AN70+AP70++AQ70+AR70+AS70+AT70+AU70+AV70+AW70+AX70+AY70+AZ70+BA70+BB70+BC70+BD70+BE70+BG70+BH70+BK70 -> 220309.2 | BP70: =BL70-BM70 -> 271558.25 | BQ70: =BL70*12 -> 5902409.4 | BR70: =200000+(0.2*BQ70) -> 1380481.9 | BS70: =BI70*12 -> 0 | BT70: =SUM(BR70:BS70) -> 1380481.9 | BU70: =+BQ70-BT70 -> 4521927.6 | BW70: =IF((BU70>0),(IF((BU70>300000),(300000*7%),(BU70*7%))),(BQ70*1%)) -> 21000 | BX70: =IF((BU70-300000)>0,(IF((BU70>600000),(300000*11%),((BU70-300000)*11%))),("")) -> 33000 | BY70: =IF(((BU70-600000)>0),(IF((BU70>1100000),(500000*15%),((BU70-600000)*15%))),("")) -> 75000 | BZ70: =IF(((BU70-(1100000))>0),(IF((BU70>(1600000)),((500000)*19%),((BU70-(1100000))*19%))),("")) -> 95000 | CA70: =IF(((BU70-(1600000))>0),(IF((BU70>(3200000)),((1600000)*21%),((BU70-(1600000))*21%))),("")) -> 336000 | CB70: =IF(((BU70-(3200000))>0),(IF((BU70>(3200000)),((BU70-(3200000))*24%),(0))),("")) -> 317262.61 | CC70: =SUM(BW70:CB70) -> 877262.61 | CD70: =1%*BQ70 -> 59024.094 | CE70: =MAX(CC70:CD70) -> 877262.61 | CF70: =+CE70/12 -> 73105.218
A71: 68 | B71: EBIKABOWEI MUSAH | C71: GUIDANCE AND COUNSELLING | D71: LECTURER I | E71: CONUAS 4/3 | F71: FCMB | G71: 2908285016 | J71: 209408.67 | K71: 52352.168 | L71: 30000 | M71: 300883.92 | N71: =M71*0.35/3 -> 35103.124 | O71: 5000 | R71: 2500 | Z71: 2500 | AM71: =M71*0.02 -> 6017.6784 | AN71: 500 | AP71: 21667 | AS71: 1000 | AV71: 5000 | BA71: 45000 | BC71: 3750 | BD71: 7500 | BE71: 1500 | BH71: =BL71*0.02 -> 6919.7409 | BK71: 45292.49 | BL71: =M71+N71+O71+P71+R71+S71+T71+U71+V71+W71+Y71+Z71+AA71 -> 345987.04 | BM71: =AI71+AJ71+AK71+AL71+AM71+AN71+AP71++AQ71+AR71+AS71+AT71+AU71+AV71+AW71+AX71+AY71+AZ71+BA71+BB71+BC71+BD71+BE71+BG71+BH71+BK71 -> 144146.91 | BP71: =BL71-BM71 -> 201840.13
A72: 69 | B72: OTOBO FIRSTMAN NOAH | C72: MATHEMATICS AND COMPUTER SCIENCE | D72: LECTURER I | E72: CONUAS 4/4 | F72: ACCESS | G72: 0022777800 | H72: 2254203 | J72: 187850.25 | K72: 46962.562 | L72: 30000 | M72: 310007.17 | N72: =M72*0.35/3 -> 36167.503 | O72: 5000 | R72: 2500 | Z72: 2500 | AM72: =M72*0.02 -> 6200.1434 | AN72: 500 | AQ72: 1000 | BA72: 0 | BE72: 1500 | BH72: =BL72*0.02 -> 7123.4935 | BK72: 47052.2 | BL72: =M72+N72+O72+P72+R72+S72+T72+U72+V72+W72+Y72+Z72+AA72 -> 356174.67 | BM72: =AI72+AJ72+AK72+AL72+AM72+AN72+AP72++AQ72+AR72+AS72+AT72+AU72+AV72+AW72+AX72+AY72+AZ72+BA72+BB72+BC72+BD72+BE72+BG72+BH72+BK72 -> 63375.837 | BP72: =BL72-BM72 -> 292798.84 | BQ72: =BL72*12 -> 4274096.1 | BR72: =200000+(0.2*BQ72) -> 1054819.2 | BS72: =BI72*12 -> 0 | BT72: =SUM(BR72:BS72) -> 1054819.2 | BU72: =+BQ72-BT72 -> 3219276.9 | BW72: =IF((BU72>0),(IF((BU72>300000),(300000*7%),(BU72*7%))),(BQ72*1%)) -> 21000 | BX72: =IF((BU72-300000)>0,(IF((BU72>600000),(300000*11%),((BU72-300000)*11%))),("")) -> 33000 | BY72: =IF(((BU72-600000)>0),(IF((BU72>1100000),(500000*15%),((BU72-600000)*15%))),("")) -> 75000 | BZ72: =IF(((BU72-(1100000))>0),(IF((BU72>(1600000)),((500000)*19%),((BU72-(1100000))*19%))),("")) -> 95000 | CA72: =IF(((BU72-(1600000))>0),(IF((BU72>(3200000)),((1600000)*21%),((BU72-(1600000))*21%))),("")) -> 336000 | CB72: =IF(((BU72-(3200000))>0),(IF((BU72>(3200000)),((BU72-(3200000))*24%),(0))),("")) -> 4626.447 | CC72: =SUM(BW72:CB72) -> 564626.45 | CD72: =1%*BQ72 -> 42740.961 | CE72: =MAX(CC72:CD72) -> 564626.45 | CF72: =+CE72/12 -> 47052.204
A73: 70 | B73: ADEDIRE TUNDE PETER | C73: BUSINESS ADMINISTRATION | D73: LECTURER I | E73: CONUAS 4/5 | F73: FIRST | G73: 3036135498 | H73: =M73*12 -> 3829564 | I73: 2688069 | J73: 224005.75 | K73: 56001.438 | L73: 30000 | M73: 319130.33 | N73: =M73*0.35/3 -> 37231.872 | O73: 5000 | R73: 2500 | Z73: 2500 | AI73: 25000 | AM73: =M73*0.02 -> 6382.6066 | AN73: 500 | AW73: 1000 | BA73: 215000 | BC73: 7500 | BD73: 15000 | BE73: 1500 | BH73: =BL73*0.02 -> 7327.244 | BK73: 49008.21 | BL73: =M73+N73+O73+P73+R73+S73+T73+U73+V73+W73+Y73+Z73+AA73 -> 366362.2 | BM73: =AI73+AJ73+AK73+AL73+AM73+AN73+AP73++AQ73+AR73+AS73+AT73+AU73+AV73+AW73+AX73+AY73+AZ73+BA73+BB73+BC73+BD73+BE73+BG73+BH73+BK73 -> 328218.06 | BP73: =BL73-BM73 -> 38144.145 | BQ73: =BL73*12 -> 4396346.4 | BR73: =200000+(0.2*BQ73) -> 1079269.3 | BS73: =BI73*12 -> 0 | BT73: =SUM(BR73:BS73) -> 1079269.3 | BU73: =+BQ73-BT73 -> 3317077.1 | BW73: =IF((BU73>0),(IF((BU73>300000),(300000*7%),(BU73*7%))),(BQ73*1%)) -> 21000 | BX73: =IF((BU73-300000)>0,(IF((BU73>600000),(300000*11%),((BU73-300000)*11%))),("")) -> 33000 | BY73: =IF(((BU73-600000)>0),(IF((BU73>1100000),(500000*15%),((BU73-600000)*15%))),("")) -> 75000 | BZ73: =IF(((BU73-(1100000))>0),(IF((BU73>(1600000)),((500000)*19%),((BU73-(1100000))*19%))),("")) -> 95000 | CA73: =IF(((BU73-(1600000))>0),(IF((BU73>(3200000)),((1600000)*21%),((BU73-(1600000))*21%))),("")) -> 336000 | CB73: =IF(((BU73-(3200000))>0),(IF((BU73>(3200000)),((BU73-(3200000))*24%),(0))),("")) -> 28098.513 | CC73: =SUM(BW73:CB73) -> 588098.51 | CD73: =1%*BQ73 -> 43963.464 | CE73: =MAX(CC73:CD73) -> 588098.51 | CF73: =+CE73/12 -> 49008.209
A74: 71 | B74: UKACHUKU SAMUEL | C74: PHYSICS | D74: LECTURER I | E74: CONUAS 4/5 | F74: GTB | G74: 0117332949 | H74: 2600486 | I74: 2688069 | J74: 224005.75 | K74: 56001.438 | L74: 30000 | M74: 319130.33 | N74: =M74*0.35/3 -> 37231.872 | O74: 5000 | R74: 2500 | Z74: 2500 | AM74: =M74*0.02 -> 6382.6066 | AN74: 500 | AQ74: 1000 | BA74: 0 | BE74: 1500 | BH74: =BL74*0.02 -> 7327.244 | BK74: 49008.21 | BL74: =M74+N74+O74+P74+R74+S74+T74+U74+V74+W74+Y74+Z74+AA74 -> 366362.2 | BM74: =AI74+AJ74+AK74+AL74+AM74+AN74+AP74++AQ74+AR74+AS74+AT74+AU74+AV74+AW74+AX74+AY74+AZ74+BA74+BB74+BC74+BD74+BE74+BG74+BH74+BK74 -> 65718.061 | BP74: =BL74-BM74 -> 300644.14 | BQ74: =BL74*12 -> 4396346.4 | BR74: =200000+(0.2*BQ74) -> 1079269.3 | BS74: =BI74*12 -> 0 | BT74: =SUM(BR74:BS74) -> 1079269.3 | BU74: =+BQ74-BT74 -> 3317077.1 | BW74: =IF((BU74>0),(IF((BU74>300000),(300000*7%),(BU74*7%))),(BQ74*1%)) -> 21000 | BX74: =IF((BU74-300000)>0,(IF((BU74>600000),(300000*11%),((BU74-300000)*11%))),("")) -> 33000 | BY74: =IF(((BU74-600000)>0),(IF((BU74>1100000),(500000*15%),((BU74-600000)*15%))),("")) -> 75000 | BZ74: =IF(((BU74-(1100000))>0),(IF((BU74>(1600000)),((500000)*19%),((BU74-(1100000))*19%))),("")) -> 95000 | CA74: =IF(((BU74-(1600000))>0),(IF((BU74>(3200000)),((1600000)*21%),((BU74-(1600000))*21%))),("")) -> 336000 | CB74: =IF(((BU74-(3200000))>0),(IF((BU74>(3200000)),((BU74-(3200000))*24%),(0))),("")) -> 28098.513 | CC74: =SUM(BW74:CB74) -> 588098.51 | CD74: =1%*BQ74 -> 43963.464 | CE74: =MAX(CC74:CD74) -> 588098.51 | CF74: =+CE74/12 -> 49008.209
A75: 72 | B75: ENIZE TINA | C75: FISHERIES | D75: LECTURER I | E75: CONUAS 4/5 | F75: FIRST | G75: 3053511556 | H75: 2254203 | I75: 2425322 | J75: 202110.17 | K75: 50527.542 | L75: 30000 | M75: 319130.33 | N75: =M75*0.35/3 -> 37231.872 | O75: 5000 | R75: 2500 | Z75: 2500 | AM75: =M75*0.02 -> 6382.6066 | AN75: 500 | AP75: 50000 | AY75: 2000 | BA75: 116818.18 | BC75: 7500 | BD75: 15000 | BE75: 1500 | BH75: =BL75*0.02 -> 7327.244 | BK75: 49008.21 | BL75: =M75+N75+O75+P75+R75+S75+T75+U75+V75+W75+Y75+Z75+AA75 -> 366362.2 | BM75: =AI75+AJ75+AK75+AL75+AM75+AN75+AP75++AQ75+AR75+AS75+AT75+AU75+AV75+AW75+AX75+AY75+AZ75+BA75+BB75+BC75+BD75+BE75+BG75+BH75+BK75 -> 256036.24 | BP75: =BL75-BM75 -> 110325.96 | BQ75: =BL75*12 -> 4396346.4 | BR75: =200000+(0.2*BQ75) -> 1079269.3 | BS75: =BI75*12 -> 0 | BT75: =SUM(BR75:BS75) -> 1079269.3 | BU75: =+BQ75-BT75 -> 3317077.1 | BW75: =IF((BU75>0),(IF((BU75>300000),(300000*7%),(BU75*7%))),(BQ75*1%)) -> 21000 | BX75: =IF((BU75-300000)>0,(IF((BU75>600000),(300000*11%),((BU75-300000)*11%))),("")) -> 33000 | BY75: =IF(((BU75-600000)>0),(IF((BU75>1100000),(500000*15%),((BU75-600000)*15%))),("")) -> 75000 | BZ75: =IF(((BU75-(1100000))>0),(IF((BU75>(1600000)),((500000)*19%),((BU75-(1100000))*19%))),("")) -> 95000 | CA75: =IF(((BU75-(1600000))>0),(IF((BU75>(3200000)),((1600000)*21%),((BU75-(1600000))*21%))),("")) -> 336000 | CB75: =IF(((BU75-(3200000))>0),(IF((BU75>(3200000)),((BU75-(3200000))*24%),(0))),("")) -> 28098.513 | CC75: =SUM(BW75:CB75) -> 588098.51 | CD75: =1%*BQ75 -> 43963.464 | CE75: =MAX(CC75:CD75) -> 588098.51 | CF75: =+CE75/12 -> 49008.209
A76: 73 | B76: OGBOLE FAITH AJIEBABHLO | C76: CHEMICAL SCIENCES | D76: SENIOR LECTURER | E76: CONUAS 5/3 | F76: GTB | G76: 0037050075 | H76: =H75 -> 2254203 | I76: 2688069 | J76: 224005.75 | K76: 56001.438 | L76: 30000 | M76: 413255.25 | N76: =M76*0.35/3 -> 48213.113 | O76: 5000 | P76: 20833.33 | R76: 2500 | Z76: 2500 | AM76: =M76*0.02 -> 8265.105 | AN76: 500 | AQ76: 1000 | AY76: 2000 | BA76: 0 | BC76: 5000 | BD76: 10000 | BE76: 1500 | BH76: =BL76*0.02 -> 9846.0338 | BK76: 73188.59 | BL76: =M76+N76+O76+P76+R76+S76+T76+U76+V76+W76+Y76+Z76+AA76 -> 492301.69 | BM76: =AI76+AJ76+AK76+AL76+AM76+AN76+AP76++AQ76+AR76+AS76+AT76+AU76+AV76+AW76+AX76+AY76+AZ76+BA76+BB76+BC76+BD76+BE76+BG76+BH76+BK76 -> 111299.73 | BP76: =BL76-BM76 -> 381001.96 | BQ76: =BL76*12 -> 5907620.3 | BR76: =200000+(0.2*BQ76) -> 1381524.1 | BS76: =BI76*12 -> 0 | BT76: =SUM(BR76:BS76) -> 1381524.1 | BU76: =+BQ76-BT76 -> 4526096.2 | BW76: =IF((BU76>0),(IF((BU76>300000),(300000*7%),(BU76*7%))),(BQ76*1%)) -> 21000 | BX76: =IF((BU76-300000)>0,(IF((BU76>600000),(300000*11%),((BU76-300000)*11%))),("")) -> 33000 | BY76: =IF(((BU76-600000)>0),(IF((BU76>1100000),(500000*15%),((BU76-600000)*15%))),("")) -> 75000 | BZ76: =IF(((BU76-(1100000))>0),(IF((BU76>(1600000)),((500000)*19%),((BU76-(1100000))*19%))),("")) -> 95000 | CA76: =IF(((BU76-(1600000))>0),(IF((BU76>(3200000)),((1600000)*21%),((BU76-(1600000))*21%))),("")) -> 336000 | CB76: =IF(((BU76-(3200000))>0),(IF((BU76>(3200000)),((BU76-(3200000))*24%),(0))),("")) -> 318263.1 | CC76: =SUM(BW76:CB76) -> 878263.1 | CD76: =1%*BQ76 -> 59076.203 | CE76: =MAX(CC76:CD76) -> 878263.1 | CF76: =+CE76/12 -> 73188.592
A77: 74 | B77: TOUNAREGHA AKPOSEIMOKUMO | C77: HISTORY AND INTERNATIONAL STUDIES | D77: SENIOR LECTURER | E77: CONUAS 5/3 | F77: FIRST | G77: 3068164624 | H77: 2600486 | I77: 2600486 | J77: 224005.75 | K77: 56001.438 | L77: 30000 | M77: 413255.25 | N77: =M77*0.35/3 -> 48213.113 | O77: 5000 | P77: 20833.33 | R77: 2500 | Z77: 2500 | AI77: 18333.33 | AM77: =M77*0.02 -> 8265.105 | AN77: 500 | AS77: 1000 | AT77: 42000 | BA77: 141250.33 | BC77: 7500 | BD77: 15000 | BE77: 1500 | BH77: =BL77*0.02 -> 9846.0338 | BK77: 73188.59 | BL77: =M77+N77+O77+P77+R77+S77+T77+U77+V77+W77+Y77+Z77+AA77 -> 492301.69 | BM77: =AI77+AJ77+AK77+AL77+AM77+AN77+AP77++AQ77+AR77+AS77+AT77+AU77+AV77+AW77+AX77+AY77+AZ77+BA77+BB77+BC77+BD77+BE77+BG77+BH77+BK77 -> 318383.39 | BP77: =BL77-BM77 -> 173918.3 | BQ77: =BL77*12 -> 5907620.3 | BR77: =200000+(0.2*BQ77) -> 1381524.1 | BS77: =BI77*12 -> 0 | BT77: =SUM(BR77:BS77) -> 1381524.1 | BU77: =+BQ77-BT77 -> 4526096.2 | BW77: =IF((BU77>0),(IF((BU77>300000),(300000*7%),(BU77*7%))),(BQ77*1%)) -> 21000 | BX77: =IF((BU77-300000)>0,(IF((BU77>600000),(300000*11%),((BU77-300000)*11%))),("")) -> 33000 | BY77: =IF(((BU77-600000)>0),(IF((BU77>1100000),(500000*15%),((BU77-600000)*15%))),("")) -> 75000 | BZ77: =IF(((BU77-(1100000))>0),(IF((BU77>(1600000)),((500000)*19%),((BU77-(1100000))*19%))),("")) -> 95000 | CA77: =IF(((BU77-(1600000))>0),(IF((BU77>(3200000)),((1600000)*21%),((BU77-(1600000))*21%))),("")) -> 336000 | CB77: =IF(((BU77-(3200000))>0),(IF((BU77>(3200000)),((BU77-(3200000))*24%),(0))),("")) -> 318263.1 | CC77: =SUM(BW77:CB77) -> 878263.1 | CD77: =1%*BQ77 -> 59076.203 | CE77: =MAX(CC77:CD77) -> 878263.1 | CF77: =+CE77/12 -> 73188.592
A78: 75 | B78: FAWEI OWEI EBIFAGHE | C78: THEATRE ARTS | D78: SENIOR LECTURER | E78: CONUAS 5/3 | F78: UBA | G78: 2021129919 | H78: 2775651 | I78: 2863233 | J78: 238602.75 | K78: 59650.688 | L78: 30000 | M78: 413255.25 | N78: =M78*0.35/3 -> 48213.113 | O78: 5000 | R78: 2500 | Z78: 2500 | AM78: =M78*0.02 -> 8265.105 | AN78: 500 | AP78: 61667 | AS78: 1000 | AY78: 2000 | BA78: 103333.33 | BE78: 1500 | BH78: =BL78*0.02 -> 9429.3672 | BK78: 69188.59 | BL78: =M78+N78+O78+P78+R78+S78+T78+U78+V78+W78+Y78+Z78+AA78 -> 471468.36 | BM78: =AI78+AJ78+AK78+AL78+AM78+AN78+AP78++AQ78+AR78+AS78+AT78+AU78+AV78+AW78+AX78+AY78+AZ78+BA78+BB78+BC78+BD78+BE78+BG78+BH78+BK78 -> 256883.39 | BP78: =BL78-BM78 -> 214584.97 | BQ78: =BL78*12 -> 5657620.3 | BR78: =200000+(0.2*BQ78) -> 1331524.1 | BS78: =BI78*12 -> 0 | BT78: =SUM(BR78:BS78) -> 1331524.1 | BU78: =+BQ78-BT78 -> 4326096.3 | BW78: =IF((BU78>0),(IF((BU78>300000),(300000*7%),(BU78*7%))),(BQ78*1%)) -> 21000 | BX78: =IF((BU78-300000)>0,(IF((BU78>600000),(300000*11%),((BU78-300000)*11%))),("")) -> 33000 | BY78: =IF(((BU78-600000)>0),(IF((BU78>1100000),(500000*15%),((BU78-600000)*15%))),("")) -> 75000 | BZ78: =IF(((BU78-(1100000))>0),(IF((BU78>(1600000)),((500000)*19%),((BU78-(1100000))*19%))),("")) -> 95000 | CA78: =IF(((BU78-(1600000))>0),(IF((BU78>(3200000)),((1600000)*21%),((BU78-(1600000))*21%))),("")) -> 336000 | CB78: =IF(((BU78-(3200000))>0),(IF((BU78>(3200000)),((BU78-(3200000))*24%),(0))),("")) -> 270263.11 | CC78: =SUM(BW78:CB78) -> 830263.11 | CD78: =1%*BQ78 -> 56576.204 | CE78: =MAX(CC78:CD78) -> 830263.11 | CF78: =+CE78/12 -> 69188.592
A79: 76 | B79: UDO SAMUEL JACKSON | C79: THEATRE ARTS | D79: SENIOR LECTURER | E79: CONUAS 5/7 | F79: ZENITH | G79: 2048397326 | H79: 3125980 | I79: 3125980 | J79: 260498.33 | K79: 65124.583 | L79: 30000 | M79: =M67 -> 465589.33 | N79: =M79*0.35/3 -> 54318.755 | O79: 5000 | R79: 2500 | Z79: 2500 | AM79: =M79*0.02 -> 9311.7866 | AN79: 500 | AP79: 10000 | AS79: 1000 | BA79: 5000 | BC79: 5000 | BD79: 10000 | BE79: 1500 | BH79: =BL79*0.02 -> 10598.162 | BK79: 80409.02 | BL79: =M79+N79+O79+P79+R79+S79+T79+U79+V79+W79+Y79+Z79+AA79 -> 529908.09 | BM79: =AI79+AJ79+AK79+AL79+AM79+AN79+AP79++AQ79+AR79+AS79+AT79+AU79+AV79+AW79+AX79+AY79+AZ79+BA79+BB79+BC79+BD79+BE79+BG79+BH79+BK79 -> 133318.97 | BP79: =BL79-BM79 -> 396589.12 | BQ79: =BL79*12 -> 6358897 | BR79: =200000+(0.2*BQ79) -> 1471779.4 | BS79: =BI79*12 -> 0 | BT79: =SUM(BR79:BS79) -> 1471779.4 | BU79: =+BQ79-BT79 -> 4887117.6 | BW79: =IF((BU79>0),(IF((BU79>300000),(300000*7%),(BU79*7%))),(BQ79*1%)) -> 21000 | BX79: =IF((BU79-300000)>0,(IF((BU79>600000),(300000*11%),((BU79-300000)*11%))),("")) -> 33000 | BY79: =IF(((BU79-600000)>0),(IF((BU79>1100000),(500000*15%),((BU79-600000)*15%))),("")) -> 75000 | BZ79: =IF(((BU79-(1100000))>0),(IF((BU79>(1600000)),((500000)*19%),((BU79-(1100000))*19%))),("")) -> 95000 | CA79: =IF(((BU79-(1600000))>0),(IF((BU79>(3200000)),((1600000)*21%),((BU79-(1600000))*21%))),("")) -> 336000 | CB79: =IF(((BU79-(3200000))>0),(IF((BU79>(3200000)),((BU79-(3200000))*24%),(0))),("")) -> 404908.23 | CC79: =SUM(BW79:CB79) -> 964908.23 | CD79: =1%*BQ79 -> 63588.97 | CE79: =MAX(CC79:CD79) -> 964908.23 | CF79: =+CE79/12 -> 80409.019
A80: 77 | B80: STANLEY LEADER | C80: MASS COMMUNICATION | D80: SENIOR LECTURER | E80: CONUAS 5/3 | F80: STERLING | G80: 0072348209 | H80: 2600486 | I80: 2688069 | J80: 224005.75 | K80: 56001.438 | L80: 30000 | M80: 413255.25 | N80: =M80*0.35/3 -> 48213.113 | O80: 5000 | P80: 20833.33 | R80: 2500 | S80: 192999.01 | Z80: 2500 | AM80: =M80*0.02 -> 8265.105 | AN80: 500 | AP80: 5000 | AU80: 10000 | AV80: 5000 | AX80: 1000 | BA80: 60000 | BC80: 3750 | BD80: 7500 | BE80: 1500 | BH80: =BL80*0.02 -> 13706.014 | BK80: 77188.46 | BL80: =M80+N80+O80+P80+R80+S80+T80+U80+V80+W80+Y80+Z80+AA80 -> 685300.7 | BM80: =AI80+AJ80+AK80+AL80+AM80+AN80+AP80++AQ80+AR80+AS80+AT80+AU80+AV80+AW80+AX80+AY80+AZ80+BA80+BB80+BC80+BD80+BE80+BG80+BH80+BK80 -> 193409.58 | BP80: =BL80-BM80 -> 491891.12 | BQ80: =BL80*12 -> 8223608.4 | BR80: =200000+(0.2*BQ80) -> 1844721.7 | BS80: =BI80*12 -> 0 | BT80: =SUM(BR80:BS80) -> 1844721.7 | BU80: =+BQ80-BT80 -> 6378886.7 | BW80: =IF((BU80>0),(IF((BU80>300000),(300000*7%),(BU80*7%))),(BQ80*1%)) -> 21000 | BX80: =IF((BU80-300000)>0,(IF((BU80>600000),(300000*11%),((BU80-300000)*11%))),("")) -> 33000 | BY80: =IF(((BU80-600000)>0),(IF((BU80>1100000),(500000*15%),((BU80-600000)*15%))),("")) -> 75000 | BZ80: =IF(((BU80-(1100000))>0),(IF((BU80>(1600000)),((500000)*19%),((BU80-(1100000))*19%))),("")) -> 95000 | CA80: =IF(((BU80-(1600000))>0),(IF((BU80>(3200000)),((1600000)*21%),((BU80-(1600000))*21%))),("")) -> 336000 | CB80: =IF(((BU80-(3200000))>0),(IF((BU80>(3200000)),((BU80-(3200000))*24%),(0))),("")) -> 762932.82 | CC80: =SUM(BW80:CB80) -> 1322932.8 | CD80: =1%*BQ80 -> 82236.084 | CE80: =MAX(CC80:CD80) -> 1322932.8 | CF80: =+CE80/12 -> 110244.4 | CN80: BEING ADDITION OF HOD ALLOWANCE ARREARS
A81: 78 | B81: THOMPSON OLUSEGUN EWATA | C81: LINGUISTICS AND NIGERIAN LANGUAGES | D81: PROFESSOR | E81: CONUAS 7/1 | F81: STERLING | G81: 0078855831 | H81: 4783091 | I81: 4934909 | J81: 411242.42 | K81: 102810.6 | L81: 30000 | M81: 600737.25 | N81: =M81*0.35/3 -> 70086.012 | O81: 6666.67 | P81: 41666 | R81: 2500 | Z81: 2500 | AI81: 25000 | AM81: =M81*0.02 -> 12014.745 | AN81: 500 | AP81: 130625 | AS81: 1000 | BA81: 190000 | BC81: 12500 | BD81: 25000 | BE81: 2500 | BH81: =BL81*0.02 -> 14483.119 | BK81: 117704.61 | BL81: =M81+N81+O81+P81+R81+S81+T81+U81+V81+W81+Y81+Z81+AA81 -> 724155.93 | BM81: =AI81+AJ81+AK81+AL81+AM81+AN81+AP81++AQ81+AR81+AS81+AT81+AU81+AV81+AW81+AX81+AY81+AZ81+BA81+BB81+BC81+BD81+BE81+BG81+BH81+BK81 -> 531327.47 | BP81: =BL81-BM81 -> 192828.46 | BQ81: =BL81*12 -> 8689871.2 | BR81: =200000+(0.2*BQ81) -> 1937974.2 | BS81: =BI81*12 -> 0 | BT81: =SUM(BR81:BS81) -> 1937974.2 | BU81: =+BQ81-BT81 -> 6751897 | BW81: =IF((BU81>0),(IF((BU81>300000),(300000*7%),(BU81*7%))),(BQ81*1%)) -> 21000 | BX81: =IF((BU81-300000)>0,(IF((BU81>600000),(300000*11%),((BU81-300000)*11%))),("")) -> 33000 | BY81: =IF(((BU81-600000)>0),(IF((BU81>1100000),(500000*15%),((BU81-600000)*15%))),("")) -> 75000 | BZ81: =IF(((BU81-(1100000))>0),(IF((BU81>(1600000)),((500000)*19%),((BU81-(1100000))*19%))),("")) -> 95000 | CA81: =IF(((BU81-(1600000))>0),(IF((BU81>(3200000)),((1600000)*21%),((BU81-(1600000))*21%))),("")) -> 336000 | CB81: =IF(((BU81-(3200000))>0),(IF((BU81>(3200000)),((BU81-(3200000))*24%),(0))),("")) -> 852455.27 | CC81: =SUM(BW81:CB81) -> 1412455.3 | CD81: =1%*BQ81 -> 86898.712 | CE81: =MAX(CC81:CD81) -> 1412455.3 | CF81: =+CE81/12 -> 117704.61
A82: 79 | B82: JAMES ONUKWU NWABIANKE | C82: INDUSTRAL RELATION AND PERSONAL MGT | D82: SENIOR LECTURER | E82: CONUAS 5/4 | F82: FIDELITY | G82: 6230686439 | H82: 3804852 | I82: 3804852 | J82: 317071 | K82: 79267.75 | L82: 30000 | M82: =SUM(J82:L82) -> 426338.75 | N82: =M82*0.35/3 -> 49739.521 | O82: 5000 | R82: 2500 | Z82: 2500 | AM82: =M82*0.02 -> 8526.775 | AN82: 500 | BA82: 0 | BE82: 2000 | BH82: =BL82*0.02 -> 9721.5654 | BK82: 71993.695 | BL82: =M82+N82+O82+P82+R82+S82+T82+U82+V82+W82+Y82+Z82+AA82 -> 486078.27 | BM82: =AI82+AJ82+AK82+AL82+AM82+AN82+AP82++AQ82+AR82+AS82+AT82+AU82+AV82+AW82+AX82+AY82+AZ82+BA82+BB82+BC82+BD82+BE82+BG82+BH82+BK82 -> 92742.035 | BP82: =BL82-BM82 -> 393336.24 | BQ82: =BL82*12 -> 5832939.2 | BR82: =200000+(0.2*BQ82) -> 1366587.9 | BS82: =BI82*12 -> 0 | BT82: =SUM(BR82:BS82) -> 1366587.9 | BU82: =+BQ82-BT82 -> 4466351.4 | BW82: =IF((BU82>0),(IF((BU82>300000),(300000*7%),(BU82*7%))),(BQ82*1%)) -> 21000 | BX82: =IF((BU82-300000)>0,(IF((BU82>600000),(300000*11%),((BU82-300000)*11%))),("")) -> 33000 | BY82: =IF(((BU82-600000)>0),(IF((BU82>1100000),(500000*15%),((BU82-600000)*15%))),("")) -> 75000 | BZ82: =IF(((BU82-(1100000))>0),(IF((BU82>(1600000)),((500000)*19%),((BU82-(1100000))*19%))),("")) -> 95000 | CA82: =IF(((BU82-(1600000))>0),(IF((BU82>(3200000)),((1600000)*21%),((BU82-(1600000))*21%))),("")) -> 336000 | CB82: =IF(((BU82-(3200000))>0),(IF((BU82>(3200000)),((BU82-(3200000))*24%),(0))),("")) -> 303924.34 | CC82: =SUM(BW82:CB82) -> 863924.34 | CD82: =1%*BQ82 -> 58329.393 | CE82: =MAX(CC82:CD82) -> 863924.34 | CF82: =+CE82/12 -> 71993.695
A83: 80 | B83: GODWIN POI | C83: BUSINESS ADMINISTRATION | D83: CONTRACT PROFESSOR | E83: CONUAS 7/1 | F83: STERLING | G83: 0005457479 | H83: 4327636 | I83: 4327636 | J83: 360636.33 | K83: 90159.083 | L83: 30000 | M83: 600737.25 | N83: =M83*0.35/3 -> 70086.012 | O83: 6666.67 | P83: 41667 | R83: 2500 | Z83: 2500 | AM83: =M83*0.02 -> 12014.745 | AN83: 500 | AW83: 1000 | BA83: 0 | BC83: 7500 | BD83: 15000 | BE83: 2500 | BH83: =BL83*0.02 -> 18343.119 | BK83: 117704.8 | BL83: =M83+N83+O83+P83+R83+S80+T83+U83+V83+W83+Y83+Z83+AA83 -> 917155.94 | BM83: =AI83+AJ83+AK83+AL83+AM83+AN83+AP83++AQ83+AR83+AS83+AT83+AU83+AV83+AW83+AX83+AY83+AZ83+BA83+BB83+BC83+BD83+BE83+BG83+BH83+BK83 -> 174562.66 | BP83: =BL83-BM83 -> 742593.28 | BQ83: =BL83*12 -> 11005871 | BR83: =200000+(0.2*BQ83) -> 2401174.3 | BS83: =BI83*12 -> 0 | BT83: =SUM(BR83:BS83) -> 2401174.3 | BU83: =+BQ83-BT83 -> 8604697 | BW83: =IF((BU83>0),(IF((BU83>300000),(300000*7%),(BU83*7%))),(BQ83*1%)) -> 21000 | BX83: =IF((BU83-300000)>0,(IF((BU83>600000),(300000*11%),((BU83-300000)*11%))),("")) -> 33000 | BY83: =IF(((BU83-600000)>0),(IF((BU83>1100000),(500000*15%),((BU83-600000)*15%))),("")) -> 75000 | BZ83: =IF(((BU83-(1100000))>0),(IF((BU83>(1600000)),((500000)*19%),((BU83-(1100000))*19%))),("")) -> 95000 | CA83: =IF(((BU83-(1600000))>0),(IF((BU83>(3200000)),((1600000)*21%),((BU83-(1600000))*21%))),("")) -> 336000 | CB83: =IF(((BU83-(3200000))>0),(IF((BU83>(3200000)),((BU83-(3200000))*24%),(0))),("")) -> 1297127.3 | CC83: =SUM(BW83:CB83) -> 1857127.3 | CD83: =1%*BQ83 -> 110058.71 | CE83: =MAX(CC83:CD83) -> 1857127.3 | CF83: =+CE83/12 -> 154760.61
A84: 81 | B84: AGWI, CELESTINE UCHE | C84: MATHEMATICS AND COMPUTER SCIENCE | D84: SENIOR LECTURER | E84: CONUAS 5/5 | F84: FIRST | G84: 2022988252 | H84: 3679250 | I84: 3804852 | J84: 317071 | K84: 79267.75 | L84: 30000 | M84: 439422.33 | N84: =M84*0.35/3 -> 51265.938 | O84: 5000 | P84: 20833.33 | R84: =2500 -> 2500 | Z84: 2500 | AM84: =M84*0.02 -> 8788.4466 | AN84: 500 | AQ84: 1000 | BA84: 20000 | BC84: =BD84/2 -> 4166.665 | BD84: 8333.33 | BE84: 2000 | BH84: =BL84*0.02 -> 10430.432 | BK84: 78798.81 | BL84: =M84+N84+O84+P84+R84+S84+T84+U84+V84+W84+Y84+Z84+AA84 -> 521521.6 | BM84: =AI84+AJ84+AK84+AL84+AM84+AN84+AP84++AQ84+AR84+AS84+AT84+AU84+AV84+AW84+AX84+AY84+AZ84+BA84+BB84+BC84+BD84+BE84+BG84+BH84+BK84 -> 134017.68 | BP84: =BL84-BM84 -> 387503.91 | BQ84: =BL84*12 -> 6258259.2 | BR84: =200000+(0.2*BQ84) -> 1451651.8 | BS84: =BI84*12 -> 0 | BT84: =SUM(BR84:BS84) -> 1451651.8 | BU84: =+BQ84-BT84 -> 4806607.3 | BW84: =IF((BU84>0),(IF((BU84>300000),(300000*7%),(BU84*7%))),(BQ84*1%)) -> 21000 | BX84: =IF((BU84-300000)>0,(IF((BU84>600000),(300000*11%),((BU84-300000)*11%))),("")) -> 33000 | BY84: =IF(((BU84-600000)>0),(IF((BU84>1100000),(500000*15%),((BU84-600000)*15%))),("")) -> 75000 | BZ84: =IF(((BU84-(1100000))>0),(IF((BU84>(1600000)),((500000)*19%),((BU84-(1100000))*19%))),("")) -> 95000 | CA84: =IF(((BU84-(1600000))>0),(IF((BU84>(3200000)),((1600000)*21%),((BU84-(1600000))*21%))),("")) -> 336000 | CB84: =IF(((BU84-(3200000))>0),(IF((BU84>(3200000)),((BU84-(3200000))*24%),(0))),("")) -> 385585.76 | CC84: =SUM(BW84:CB84) -> 945585.76 | CD84: =1%*BQ84 -> 62582.592 | CE84: =MAX(CC84:CD84) -> 945585.76 | CF84: =+CE84/12 -> 78798.814
A85: 82 | B85: JACKSON AKPOJARO | C85: MATHEMATICS AND COMPUTER SCIENCE | D85: FULL TIME PROFESSOR | E85: CONUAS 7/10 | F85: STERLING | G85: 0078675839 | H85: =M85*12 -> 9356702.4 | J85: 555352 | K85: 194373.2 | L85: 30000 | M85: =SUM(J85:L85) -> 779725.2 | N85: =M85*0.35/3 -> 90967.94 | O85: =O4 -> 8333.33 | R85: 2500 | Z85: 2500 | AM85: =M85*0.02 -> 15594.504 | AN85: 500 | AP85: 135000 | AQ85: 1000 | BA85: 522222.2 | BC85: 12500 | BD85: 25000 | BE85: 3500 | BH85: =BL85*0.02 -> 17680.529 | BK85: 148399.75 | BL85: =M85+N85+O85+P85+R85+S85+T85+U85+V85+W85+Y85+Z85+AA85 -> 884026.47 | BM85: =AI85+AJ85+AK85+AL85+AM85+AN85+AP85++AQ85+AR85+AS85+AT85+AU85+AV85+AW85+AX85+AY85+AZ85+BA85+BB85+BC85+BD85+BE85+BG85+BH85+BK85 -> 881396.98 | BP85: =BL85-BM85 -> 2629.4899 | BQ85: =BL85*12 -> 10608318 | BR85: =200000+(0.2*BQ85) -> 2321663.5 | BS85: =BI85*12 -> 0 | BT85: =SUM(BR85:BS85) -> 2321663.5 | BU85: =+BQ85-BT85 -> 8286654.1 | BW85: =IF((BU85>0),(IF((BU85>300000),(300000*7%),(BU85*7%))),(BQ85*1%)) -> 21000 | BX85: =IF((BU85-300000)>0,(IF((BU85>600000),(300000*11%),((BU85-300000)*11%))),("")) -> 33000 | BY85: =IF(((BU85-600000)>0),(IF((BU85>1100000),(500000*15%),((BU85-600000)*15%))),("")) -> 75000 | BZ85: =IF(((BU85-(1100000))>0),(IF((BU85>(1600000)),((500000)*19%),((BU85-(1100000))*19%))),("")) -> 95000 | CA85: =IF(((BU85-(1600000))>0),(IF((BU85>(3200000)),((1600000)*21%),((BU85-(1600000))*21%))),("")) -> 336000 | CB85: =IF(((BU85-(3200000))>0),(IF((BU85>(3200000)),((BU85-(3200000))*24%),(0))),("")) -> 1220797 | CC85: =SUM(BW85:CB85) -> 1780797 | CD85: =1%*BQ85 -> 106083.18 | CE85: =MAX(CC85:CD85) -> 1780797 | CF85: =+CE85/12 -> 148399.75
A86: 83 | B86: TONY EBIMOWEI GANAGANA | C86: GUIDANCE AND COUNSELLING | D86: FULL TIME PROFESSOR | E86: CONUAS 7/7 | F86: UBA | G86: 2090470273 | H86: =M86*12 -> 8640742 | J86: 555352 | K86: 194373.2 | L86: 30000 | M86: 720061.83 | N86: =M86*0.35/3 -> 84007.213 | O86: 8333.33 | P86: 20833.33 | R86: 2500 | Z86: 2500 | AM86: =M86*0.02 -> 14401.237 | AN86: 500 | BA86: 50000 | BC86: 12500 | BD86: 25000 | BE86: 3500 | BH86: =BL86*0.02 -> 16764.714 | BK86: 139607.92 | BL86: =M86+N86+O86+P86+R86+S86+T86+U86+V86+W86+Y86+Z86+AA86 -> 838235.7 | BM86: =AI86+AJ86+AK86+AL86+AM86+AN86+AP86++AQ86+AR86+AS86+AT86+AU86+AV86+AW86+AX86+AY86+AZ86+BA86+BB86+BC86+BD86+BE86+BG86+BH86+BK86 -> 262273.87 | BP86: =BL86-BM86 -> 575961.83
A87: 84 | B87: IBB ANDREW ALI | C87: Ag. DEAN FACULTY OF SOCIAL SCIENCE (MASS COMMUNICATION) | D87: ASSOCIATE PROFESSOR | E87: CONUAS 6/6 | F87: GTB | G87: 0018837194 | H87: 4631272 | I87: 4783091 | J87: 398590.92 | K87: 99647.729 | L87: 30000 | M87: 544053 | N87: =M87*0.35/3 -> 63472.85 | O87: 6666.67 | P87: 41667 | R87: 2500 | Z87: 2500 | AM87: =M87*0.02 -> 10881.06 | AN87: 500 | AX87: 1000 | BA87: 201960 | BC87: 12500 | BD87: 25000 | BE87: 2500 | BH87: =BL87*0.02 -> 13217.19 | BK87: 105551.69 | BL87: =M87+N87+O87+P87+R87+S87+T87+U87+V87+W87+Y87+Z87+AA87 -> 660859.52 | BM87: =AI87+AJ87+AK87+AL87+AM87+AN87+AP87++AQ87+AR87+AS87+AT87+AU87+AV87+AW87+AX87+AY87+AZ87+BA87+BB87+BC87+BD87+BE87+BG87+BH87+BK87 -> 373109.94 | BP87: =BL87-BM87 -> 287749.58 | BQ87: =BL87*12 -> 7930314.2 | BR87: =200000+(0.2*BQ87) -> 1786062.8 | BS87: =BI87*12 -> 0 | BT87: =SUM(BR87:BS87) -> 1786062.8 | BU87: =+BQ87-BT87 -> 6144251.4 | BW87: =IF((BU87>0),(IF((BU87>300000),(300000*7%),(BU87*7%))),(BQ87*1%)) -> 21000 | BX87: =IF((BU87-300000)>0,(IF((BU87>600000),(300000*11%),((BU87-300000)*11%))),("")) -> 33000 | BY87: =IF(((BU87-600000)>0),(IF((BU87>1100000),(500000*15%),((BU87-600000)*15%))),("")) -> 75000 | BZ87: =IF(((BU87-(1100000))>0),(IF((BU87>(1600000)),((500000)*19%),((BU87-(1100000))*19%))),("")) -> 95000 | CA87: =IF(((BU87-(1600000))>0),(IF((BU87>(3200000)),((1600000)*21%),((BU87-(1600000))*21%))),("")) -> 336000 | CB87: =IF(((BU87-(3200000))>0),(IF((BU87>(3200000)),((BU87-(3200000))*24%),(0))),("")) -> 706620.33 | CC87: =SUM(BW87:CB87) -> 1266620.3 | CD87: =1%*BQ87 -> 79303.142 | CE87: =MAX(CC87:CD87) -> 1266620.3 | CF87: =+CE87/12 -> 105551.69
A88: 85 | B88: OPOMU FELIX EBIKETONMOR | C88: ENGLISH AND LITERARY STUDIES | D88: LECTURER I | E88: CONUAS 4/5 | F88: STERLING | G88: 0086611904 | H88: =M88*12 -> 3829564 | I88: 2600486 | J88: 224005.75 | K88: 56001.438 | L88: 30000 | M88: 319130.33 | N88: =M88*0.35/3 -> 37231.872 | O88: 5000 | R88: 2500 | Z88: 2500 | AM88: =M88*0.02 -> 6382.6066 | AN88: 500 | AS88: 1000 | BA88: 35000 | BE88: 1500 | BH88: =BL88*0.02 -> 7327.244 | BK88: 49008.21 | BL88: =M88+N88+O88+P88+R88+S88+T88+U88+V88+W88+Y88+Z88+AA88 -> 366362.2 | BM88: =AI88+AJ88+AK88+AL88+AM88+AN88+AP88++AQ88+AR88+AS88+AT88+AU88+AV88+AW88+AX88+AY88+AZ88+BA88+BB88+BC88+BD88+BE88+BG88+BH88+BK88 -> 100718.06 | BP88: =BL88-BM88 -> 265644.14 | BQ88: =BL88*12 -> 4396346.4 | BR88: =200000+(0.2*BQ88) -> 1079269.3 | BS88: =BI88*12 -> 0 | BT88: =SUM(BR88:BS88) -> 1079269.3 | BU88: =+BQ88-BT88 -> 3317077.1 | BW88: =IF((BU88>0),(IF((BU88>300000),(300000*7%),(BU88*7%))),(BQ88*1%)) -> 21000 | BX88: =IF((BU88-300000)>0,(IF((BU88>600000),(300000*11%),((BU88-300000)*11%))),("")) -> 33000 | BY88: =IF(((BU88-600000)>0),(IF((BU88>1100000),(500000*15%),((BU88-600000)*15%))),("")) -> 75000 | BZ88: =IF(((BU88-(1100000))>0),(IF((BU88>(1600000)),((500000)*19%),((BU88-(1100000))*19%))),("")) -> 95000 | CA88: =IF(((BU88-(1600000))>0),(IF((BU88>(3200000)),((1600000)*21%),((BU88-(1600000))*21%))),("")) -> 336000 | CB88: =IF(((BU88-(3200000))>0),(IF((BU88>(3200000)),((BU88-(3200000))*24%),(0))),("")) -> 28098.513 | CC88: =SUM(BW88:CB88) -> 588098.51 | CD88: =1%*BQ88 -> 43963.464 | CE88: =MAX(CC88:CD88) -> 588098.51 | CF88: =+CE88/12 -> 49008.209
A89: 86 | B89: ABOMA GLORIA | C89: LIBRARY | D89: GRADUATE ASSIST | E89: CONUAS 1/6 | F89: KEYSTONE | G89: 6016293250 | H89: 1691938 | J89: 140994.83 | K89: 35248.708 | L89: 30000 | M89: =SUM(J89:L89) -> 206243.54 | N89: =M89*0.35/3 -> 24061.747 | O89: 5000 | R89: 2500 | Z89: 2500 | AM89: =M89*0.02 -> 4124.8708 | AN89: 500 | AY89: 2000 | BA89: 88333.33 | BC89: 5000 | BD89: 10000 | BE89: 1000 | BH89: =BL89*0.02 -> 4806.1058 | BK89: 27537.955 | BL89: =M89+N89+O89+P89+R89+S89+T89+U89+V89+W89+Y89+Z89+AA89 -> 240305.29 | BM89: =AI89+AJ89+AK89+AL89+AM89+AN89+AP89++AQ89+AR89+AS89+AT89+AU89+AV89+AW89+AX89+AY89+AZ89+BA89+BB89+BC89+BD89+BE89+BG89+BH89+BK89 -> 143302.26 | BP89: =BL89-BM89 -> 97003.027 | BQ89: =BL89*12 -> 2883663.5 | BR89: =200000+(0.2*BQ89) -> 776732.69 | BS89: =BI89*12 -> 0 | BT89: =SUM(BR89:BS89) -> 776732.69 | BU89: =+BQ89-BT89 -> 2106930.8 | BW89: =IF((BU89>0),(IF((BU89>300000),(300000*7%),(BU89*7%))),(BQ89*1%)) -> 21000 | BX89: =IF((BU89-300000)>0,(IF((BU89>600000),(300000*11%),((BU89-300000)*11%))),("")) -> 33000 | BY89: =IF(((BU89-600000)>0),(IF((BU89>1100000),(500000*15%),((BU89-600000)*15%))),("")) -> 75000 | BZ89: =IF(((BU89-(1100000))>0),(IF((BU89>(1600000)),((500000)*19%),((BU89-(1100000))*19%))),("")) -> 95000 | CA89: =IF(((BU89-(1600000))>0),(IF((BU89>(3200000)),((1600000)*21%),((BU89-(1600000))*21%))),("")) -> 106455.46 | CB89: =IF(((BU89-(3200000))>0),(IF((BU89>(3200000)),((BU89-(3200000))*24%),(0))),("")) | CC89: =SUM(BW89:CB89) -> 330455.46 | CD89: =1%*BQ89 -> 28836.635 | CE89: =MAX(CC89:CD89) -> 330455.46 | CF89: =+CE89/12 -> 27537.955
A90: 87 | B90: SIGAH DONY AYEBAZUOMUNO | C90: ECONOMICS | D90: SENIOR LECTURER | E90: CONUAS 5/3 | F90: STERLING | G90: 0078336901 | H90: 2600486 | I90: 2688069 | J90: 224005.75 | K90: 56001.438 | L90: 30000 | M90: 413255.25 | N90: =M90*0.35/3 -> 48213.113 | O90: 5000 | P90: 20833.33 | R90: 2500 | Z90: 2500 | AI90: 83500 | AM90: =M90*0.02 -> 8265.105 | AN90: 500 | AP90: 106250 | AX90: 1000 | AZ90: 1000 | BA90: 174803 | BC90: 3750 | BD90: 7500 | BE90: 1500 | BH90: =BL90*0.02 -> 9846.0338 | BK90: 73188.59 | BL90: =M90+N90+O90+P90+R90+S90+T90+U90+V90+W90+Y90+Z90+AA90 -> 492301.69 | BM90: =AI90+AJ90+AK90+AL90+AM90+AN90+AP90++AQ90+AR90+AS90+AT90+AU90+AV90+AW90+AX90+AY90+AZ90+BA90+BB90+BC90+BD90+BE90+BG90+BH90+BK90 -> 471102.73 | BP90: =BL90-BM90 -> 21198.964 | BQ90: =BL90*12 -> 5907620.3 | BR90: =200000+(0.2*BQ90) -> 1381524.1 | BS90: =BI90*12 -> 0 | BT90: =SUM(BR90:BS90) -> 1381524.1 | BU90: =+BQ90-BT90 -> 4526096.2 | BW90: =IF((BU90>0),(IF((BU90>300000),(300000*7%),(BU90*7%))),(BQ90*1%)) -> 21000 | BX90: =IF((BU90-300000)>0,(IF((BU90>600000),(300000*11%),((BU90-300000)*11%))),("")) -> 33000 | BY90: =IF(((BU90-600000)>0),(IF((BU90>1100000),(500000*15%),((BU90-600000)*15%))),("")) -> 75000 | BZ90: =IF(((BU90-(1100000))>0),(IF((BU90>(1600000)),((500000)*19%),((BU90-(1100000))*19%))),("")) -> 95000 | CA90: =IF(((BU90-(1600000))>0),(IF((BU90>(3200000)),((1600000)*21%),((BU90-(1600000))*21%))),("")) -> 336000 | CB90: =IF(((BU90-(3200000))>0),(IF((BU90>(3200000)),((BU90-(3200000))*24%),(0))),("")) -> 318263.1 | CC90: =SUM(BW90:CB90) -> 878263.1 | CD90: =1%*BQ90 -> 59076.203 | CE90: =MAX(CC90:CD90) -> 878263.1 | CF90: =+CE90/12 -> 73188.592
A91: 88 | B91: EDE TIEKUMO | C91: PHYSICS | D91: LECTURER I | E91: CONUAS 4/4 | F91: GTB | G91: 0041596422 | H91: 2254203 | I91: 2308911 | J91: 192409.25 | K91: 48102.312 | L91: 30000 | M91: 310007.17 | N91: =M91*0.35/3 -> 36167.503 | O91: 5000 | P91: 20833.33 | R91: 2500 | Z91: 2500 | AM91: =M91*0.02 -> 6200.1434 | AN91: 500 | AQ91: 1000 | BA91: 32917 | BE91: 1500 | BH91: =BL91*0.02 -> 7540.1601 | BK91: 51052.2 | BL91: =M91+N91+O91+P91+R91+S91+T91+U91+V91+W91+Y91+Z91+AA91 -> 377008 | BM91: =AI91+AJ91+AK91+AL91+AM91+AN91+AP91++AQ91+AR91+AS91+AT91+AU91+AV91+AW91+AX91+AY91+AZ91+BA91+BB91+BC91+BD91+BE91+BG91+BH91+BK91 -> 100709.5 | BP91: =BL91-BM91 -> 276298.5 | BQ91: =BL91*12 -> 4524096 | BR91: =200000+(0.2*BQ91) -> 1104819.2 | BS91: =BI91*12 -> 0 | BT91: =SUM(BR91:BS91) -> 1104819.2 | BU91: =+BQ91-BT91 -> 3419276.8 | BW91: =IF((BU91>0),(IF((BU91>300000),(300000*7%),(BU91*7%))),(BQ91*1%)) -> 21000 | BX91: =IF((BU91-300000)>0,(IF((BU91>600000),(300000*11%),((BU91-300000)*11%))),("")) -> 33000 | BY91: =IF(((BU91-600000)>0),(IF((BU91>1100000),(500000*15%),((BU91-600000)*15%))),("")) -> 75000 | BZ91: =IF(((BU91-(1100000))>0),(IF((BU91>(1600000)),((500000)*19%),((BU91-(1100000))*19%))),("")) -> 95000 | CA91: =IF(((BU91-(1600000))>0),(IF((BU91>(3200000)),((1600000)*21%),((BU91-(1600000))*21%))),("")) -> 336000 | CB91: =IF(((BU91-(3200000))>0),(IF((BU91>(3200000)),((BU91-(3200000))*24%),(0))),("")) -> 52626.439 | CC91: =SUM(BW91:CB91) -> 612626.44 | CD91: =1%*BQ91 -> 45240.96 | CE91: =MAX(CC91:CD91) -> 612626.44 | CF91: =+CE91/12 -> 51052.203
A92: 89 | B92: BRAKEMI CHRISTABEL OVIA | C92: INDUSTRAL RELATION AND PERSONAL MGT | D92: LECTURER II | E92: CONUAS 3/8 | F92: ZENITH | G92: 2008091891 | H92: 2308911 | I92: 2308911 | J92: 192409.25 | K92: 48102.312 | L92: 30000 | M92: =SUM(J92:L92) -> 270511.56 | N92: =M92*0.35/3 -> 31559.682 | O92: 5000 | R92: 2500 | Z92: 2500 | AM92: =M92*0.02 -> 5410.2312 | AN92: 500 | AW92: 1000 | AY92: 2000 | BA92: 70000 | BE92: 1500 | BH92: =BL92*0.02 -> 6241.4249 | BK92: 39594.636 | BL92: =M92+N92+O92+P92+R92+S92+T92+U92+V92+W92+Y92+Z92+AA92 -> 312071.24 | BM92: =AI92+AJ92+AK92+AL92+AM92+AN92+AP92++AQ92+AR92+AS92+AT92+AU92+AV92+AW92+AX92+AY92+AZ92+BA92+BB92+BC92+BD92+BE92+BG92+BH92+BK92 -> 126246.29 | BP92: =BL92-BM92 -> 185824.95 | BQ92: =BL92*12 -> 3744854.9 | BR92: =200000+(0.2*BQ92) -> 948970.99 | BS92: =BI92*12 -> 0 | BT92: =SUM(BR92:BS92) -> 948970.99 | BU92: =+BQ92-BT92 -> 2795884 | BW92: =IF((BU92>0),(IF((BU92>300000),(300000*7%),(BU92*7%))),(BQ92*1%)) -> 21000 | BX92: =IF((BU92-300000)>0,(IF((BU92>600000),(300000*11%),((BU92-300000)*11%))),("")) -> 33000 | BY92: =IF(((BU92-600000)>0),(IF((BU92>1100000),(500000*15%),((BU92-600000)*15%))),("")) -> 75000 | BZ92: =IF(((BU92-(1100000))>0),(IF((BU92>(1600000)),((500000)*19%),((BU92-(1100000))*19%))),("")) -> 95000 | CA92: =IF(((BU92-(1600000))>0),(IF((BU92>(3200000)),((1600000)*21%),((BU92-(1600000))*21%))),("")) -> 251135.63 | CB92: =IF(((BU92-(3200000))>0),(IF((BU92>(3200000)),((BU92-(3200000))*24%),(0))),("")) | CC92: =SUM(BW92:CB92) -> 475135.63 | CD92: =1%*BQ92 -> 37448.549 | CE92: =MAX(CC92:CD92) -> 475135.63 | CF92: =+CE92/12 -> 39594.636
A93: 90 | B93: AKOLOH-ISAAC JOSEPHINE TIMIPRE | C93: HOTEL MANAGEMENT AND TOURISM | D93: PART-TIME LECT II | E93: CONUAS 3/3 | F93: ACCESS | G93: 0694547829 | H93: =M93*12 -> 1632111.3 | J93: 84807.42 | K93: 21201.855 | L93: 30000 | M93: =SUM(J93:L93) -> 136009.27 | R93: 2500 | Z93: 2500 | AM93: =M93*0.02 -> 2720.1855 | AN93: 500 | AY93: 2000 | BA93: 0 | BE93: 500 | BH93: =BL93*0.02 -> 2820.1855 | BK93: 11600.076 | BL93: =M93+N93+O93+P93+R93+S93+T93+U93+V93+W93+Y93+Z93+AA93 -> 141009.27 | BM93: =AI93+AJ93+AK93+AL93+AM93+AN93+AP93++AQ93+AR93+AS93+AT93+AU93+AV93+AW93+AX93+AY93+AZ93+BA93+BB93+BC93+BD93+BE93+BG93+BH93+BK93 -> 20140.447 | BP93: =BL93-BM93 -> 120868.83 | BQ93: =BL93*12 -> 1692111.3 | BR93: =200000+(0.2*BQ93) -> 538422.26 | BS93: =BI93*12 -> 0 | BT93: =SUM(BR93:BS93) -> 538422.26 | BU93: =+BQ93-BT93 -> 1153689 | BW93: =IF((BU93>0),(IF((BU93>300000),(300000*7%),(BU93*7%))),(BQ93*1%)) -> 21000 | BX93: =IF((BU93-300000)>0,(IF((BU93>600000),(300000*11%),((BU93-300000)*11%))),("")) -> 33000 | BY93: =IF(((BU93-600000)>0),(IF((BU93>1100000),(500000*15%),((BU93-600000)*15%))),("")) -> 75000 | BZ93: =IF(((BU93-(1100000))>0),(IF((BU93>(1600000)),((500000)*19%),((BU93-(1100000))*19%))),("")) -> 10200.918 | CA93: =IF(((BU93-(1600000))>0),(IF((BU93>(3200000)),((1600000)*21%),((BU93-(1600000))*21%))),("")) | CB93: =IF(((BU93-(3200000))>0),(IF((BU93>(3200000)),((BU93-(3200000))*24%),(0))),("")) | CC93: =SUM(BW93:CB93) -> 139200.92 | CD93: =1%*BQ93 -> 16921.113 | CE93: =MAX(CC93:CD93) -> 139200.92 | CF93: =+CE93/12 -> 11600.076
A94: 91 | B94: OMAMOKE EKEREKE LAYEFA | C94: MATHEMATICS AND COMPUTER SCIENCE | D94: LECTURER I | E94: CONUAS 4/5 | F94: STERLING | G94: 0006180620 | H94: 2199196 | I94: 2688069 | J94: 224005.75 | K94: 56001.438 | L94: 30000 | M94: 319130.33 | N94: =M94*0.35/3 -> 37231.872 | O94: 5000 | R94: 2500 | Z94: 2500 | AM94: =M94*0.02 -> 6382.6066 | AN94: 500 | AQ94: 1000 | AY94: 2000 | BA94: 0 | BC94: 3750 | BD94: 7500 | BE94: 1500 | BH94: =BL94*0.02 -> 7327.244 | BK94: 49008.21 | BL94: =M94+N94+O94+P94+R94+S94+T94+U94+V94+W94+Y94+Z94+AA94 -> 366362.2 | BM94: =AI94+AJ94+AK94+AL94+AM94+AN94+AP94++AQ94+AR94+AS94+AT94+AU94+AV94+AW94+AX94+AY94+AZ94+BA94+BB94+BC94+BD94+BE94+BG94+BH94+BK94 -> 78968.061 | BP94: =BL94-BM94 -> 287394.14 | BQ94: =BL94*12 -> 4396346.4 | BR94: =200000+(0.2*BQ94) -> 1079269.3 | BS94: =BI94*12 -> 0 | BT94: =SUM(BR94:BS94) -> 1079269.3 | BU94: =+BQ94-BT94 -> 3317077.1 | BW94: =IF((BU94>0),(IF((BU94>300000),(300000*7%),(BU94*7%))),(BQ94*1%)) -> 21000 | BX94: =IF((BU94-300000)>0,(IF((BU94>600000),(300000*11%),((BU94-300000)*11%))),("")) -> 33000 | BY94: =IF(((BU94-600000)>0),(IF((BU94>1100000),(500000*15%),((BU94-600000)*15%))),("")) -> 75000 | BZ94: =IF(((BU94-(1100000))>0),(IF((BU94>(1600000)),((500000)*19%),((BU94-(1100000))*19%))),("")) -> 95000 | CA94: =IF(((BU94-(1600000))>0),(IF((BU94>(3200000)),((1600000)*21%),((BU94-(1600000))*21%))),("")) -> 336000 | CB94: =IF(((BU94-(3200000))>0),(IF((BU94>(3200000)),((BU94-(3200000))*24%),(0))),("")) -> 28098.513 | CC94: =SUM(BW94:CB94) -> 588098.51 | CD94: =1%*BQ94 -> 43963.464 | CE94: =MAX(CC94:CD94) -> 588098.51 | CF94: =+CE94/12 -> 49008.209
A95: 92 | B95: EBITARI WOLO | C95: INDUSTRAL RELATION AND PERSONAL MGT | D95: LECTURER I | E95: CONUAS 4/1 | F95: STERLING | G95: 0080567834 | H95: 2090081 | I95: 2144788 | J95: 178732.33 | K95: 44683.083 | L95: 30000 | M95: 259114.17 | N95: =M95*0.35/3 -> 30229.986 | O95: 5000 | P95: =P91 -> 20833.33 | R95: 2500 | Z95: 2500 | AM95: =M95*0.02 -> 5182.2834 | AN95: 500 | AP95: 70000 | AW95: 1000 | BA95: 105499.86 | BE95: 1500 | BH95: =BL95*0.02 -> 6403.5497 | BK95: 40956.48 | BL95: =M95+N95+O95+P95+R95+S95+T95+U95+V95+W95+Y95+Z95+AA95 -> 320177.49 | BM95: =AI95+AJ95+AK95+AL95+AM95+AN95+AP95++AQ95+AR95+AS95+AT95+AU95+AV95+AW95+AX95+AY95+AZ95+BA95+BB95+BC95+BD95+BE95+BG95+BH95+BK95 -> 231042.17 | BP95: =BL95-BM95 -> 89135.312 | BQ95: =BL95*12 -> 3842129.8 | BR95: =200000+(0.2*BQ95) -> 968425.97 | BS95: =BI95*12 -> 0 | BT95: =SUM(BR95:BS95) -> 968425.97 | BU95: =+BQ95-BT95 -> 2873703.9 | BW95: =IF((BU95>0),(IF((BU95>300000),(300000*7%),(BU95*7%))),(BQ95*1%)) -> 21000 | BX95: =IF((BU95-300000)>0,(IF((BU95>600000),(300000*11%),((BU95-300000)*11%))),("")) -> 33000 | BY95: =IF(((BU95-600000)>0),(IF((BU95>1100000),(500000*15%),((BU95-600000)*15%))),("")) -> 75000 | BZ95: =IF(((BU95-(1100000))>0),(IF((BU95>(1600000)),((500000)*19%),((BU95-(1100000))*19%))),("")) -> 95000 | CA95: =IF(((BU95-(1600000))>0),(IF((BU95>(3200000)),((1600000)*21%),((BU95-(1600000))*21%))),("")) -> 267477.81 | CB95: =IF(((BU95-(3200000))>0),(IF((BU95>(3200000)),((BU95-(3200000))*24%),(0))),("")) | CC95: =SUM(BW95:CB95) -> 491477.81 | CD95: =1%*BQ95 -> 38421.298 | CE95: =MAX(CC95:CD95) -> 491477.81 | CF95: =+CE95/12 -> 40956.484
A96: 93 | B96: KOMONIBO ERNEST BOLOUEBI | C96: MATHEMATICS AND COMPUTER SCIENCE | D96: LECTURER I | E96: CONUAS 4/4 | F96: STERLING | G96: 0081837918 | H96: 2308911 | I96: 2308911 | J96: 192409.25 | K96: 48102.312 | L96: 30000 | M96: 310007.17 | N96: =M96*0.35/3 -> 36167.503 | O96: 5000 | R96: 2500 | Z96: 2500 | AM96: =M96*0.02 -> 6200.1434 | AN96: 500 | AQ96: 1000 | BA96: 5000 | BE96: 1500 | BH96: =BL96*0.02 -> 7123.4935 | BK96: 47052.2 | BL96: =M96+N96+O96+P96+R96+S96+T96+U96+V96+W96+Y96+Z96+AA96 -> 356174.67 | BM96: =AI96+AJ96+AK96+AL96+AM96+AN96+AP96++AQ96+AR96+AS96+AT96+AU96+AV96+AW96+AX96+AY96+AZ96+BA96+BB96+BC96+BD96+BE96+BG96+BH96+BK96 -> 68375.837 | BP96: =BL96-BM96 -> 287798.84 | BQ96: =BL96*12 -> 4274096.1 | BR96: =200000+(0.2*BQ96) -> 1054819.2 | BS96: =BI96*12 -> 0 | BT96: =SUM(BR96:BS96) -> 1054819.2 | BU96: =+BQ96-BT96 -> 3219276.9 | BW96: =IF((BU96>0),(IF((BU96>300000),(300000*7%),(BU96*7%))),(BQ96*1%)) -> 21000 | BX96: =IF((BU96-300000)>0,(IF((BU96>600000),(300000*11%),((BU96-300000)*11%))),("")) -> 33000 | BY96: =IF(((BU96-600000)>0),(IF((BU96>1100000),(500000*15%),((BU96-600000)*15%))),("")) -> 75000 | BZ96: =IF(((BU96-(1100000))>0),(IF((BU96>(1600000)),((500000)*19%),((BU96-(1100000))*19%))),("")) -> 95000 | CA96: =IF(((BU96-(1600000))>0),(IF((BU96>(3200000)),((1600000)*21%),((BU96-(1600000))*21%))),("")) -> 336000 | CB96: =IF(((BU96-(3200000))>0),(IF((BU96>(3200000)),((BU96-(3200000))*24%),(0))),("")) -> 4626.447 | CC96: =SUM(BW96:CB96) -> 564626.45 | CD96: =1%*BQ96 -> 42740.961 | CE96: =MAX(CC96:CD96) -> 564626.45 | CF96: =+CE96/12 -> 47052.204
A97: 94 | B97: ONUCHE UNEKWU | C97: AGRICULTURAL ECONOMICS AND EXTENSION | D97: FULL-TIME PROFESSOR | E97: CONUAS 7/1 | F97: ZENITH | G97: 2005960363 | H97: 4479454 | I97: 4631272 | J97: 385939.33 | K97: 96484.833 | L97: 30000 | M97: 600737.25 | N97: =M97*0.35/3 -> 70086.012 | O97: 6666.67 | P97: 20833.33 | R97: 2500 | Z97: 2500 | AM97: =M97*0.02 -> 12014.745 | AN97: 500 | AP97: 71667 | BA97: 55000 | BC97: 5000 | BD97: 10000 | BE97: 2500 | BH97: =BL97*0.02 -> 14066.465 | BK97: 113704.73 | BL97: =M97+N97+O97+P97+R97+S97+T97+U97+V97+W97+Y97+Z97+AA97 -> 703323.26 | BM97: =AI97+AJ97+AK97+AL97+AM97+AN97+AP97++AQ97+AR97+AS97+AT97+AU97+AV97+AW97+AX97+AY97+AZ97+BA97+BB97+BC97+BD97+BE97+BG97+BH97+BK97 -> 284452.94 | BP97: =BL97-BM97 -> 418870.32 | BQ97: =BL97*12 -> 8439879.2 | BR97: =200000+(0.2*BQ97) -> 1887975.8 | BS97: =BI97*12 -> 0 | BT97: =SUM(BR97:BS97) -> 1887975.8 | BU97: =+BQ97-BT97 -> 6551903.3 | BW97: =IF((BU97>0),(IF((BU97>300000),(300000*7%),(BU97*7%))),(BQ97*1%)) -> 21000 | BX97: =IF((BU97-300000)>0,(IF((BU97>600000),(300000*11%),((BU97-300000)*11%))),("")) -> 33000 | BY97: =IF(((BU97-600000)>0),(IF((BU97>1100000),(500000*15%),((BU97-600000)*15%))),("")) -> 75000 | BZ97: =IF(((BU97-(1100000))>0),(IF((BU97>(1600000)),((500000)*19%),((BU97-(1100000))*19%))),("")) -> 95000 | CA97: =IF(((BU97-(1600000))>0),(IF((BU97>(3200000)),((1600000)*21%),((BU97-(1600000))*21%))),("")) -> 336000 | CB97: =IF(((BU97-(3200000))>0),(IF((BU97>(3200000)),((BU97-(3200000))*24%),(0))),("")) -> 804456.8 | CC97: =SUM(BW97:CB97) -> 1364456.8 | CD97: =1%*BQ97 -> 84398.792 | CE97: =MAX(CC97:CD97) -> 1364456.8 | CF97: =+CE97/12 -> 113704.73
A98: 95 | B98: IGOLI TIMIPA | C98: POLITICAL SCIENCE | D98: LECTURER I | E98: CONUAS 4/2 | F98: STERLING | G98: 0080669855 | H98: 2090081 | I98: 2144788 | J98: 178732.33 | K98: 44683.083 | L98: 30000 | M98: 291760.83 | N98: =M98*0.35/3 -> 34038.764 | O98: 5000 | P98: 41667 | R98: 2500 | Z98: 2500 | AM98: =M98*0.02 -> 5835.2166 | AN98: 500 | AP98: 35000 | AV98: 5000 | AW98: 1000 | BA98: 60000 | BC98: 3750 | BD98: 7500 | BE98: 1500 | BH98: =BL98*0.02 -> 7549.3319 | BK98: 51140.253 | BL98: =M98+N98+O98+P98+R98+S98+T98+U98+V98+W98+Y98+Z98+AA98 -> 377466.59 | BM98: =AI98+AJ98+AK98+AL98+AM98+AN98+AP98++AQ98+AR98+AS98+AT98+AU98+AV98+AW98+AX98+AY98+AZ98+BA98+BB98+BC98+BD98+BE98+BG98+BH98+BK98 -> 178774.8 | BP98: =BL98-BM98 -> 198691.79 | BQ98: =BL98*12 -> 4529599.1 | BR98: =200000+(0.2*BQ98) -> 1105919.8 | BS98: =BI98*12 -> 0 | BT98: =SUM(BR98:BS98) -> 1105919.8 | BU98: =+BQ98-BT98 -> 3423679.3 | BW98: =IF((BU98>0),(IF((BU98>300000),(300000*7%),(BU98*7%))),(BQ98*1%)) -> 21000 | BX98: =IF((BU98-300000)>0,(IF((BU98>600000),(300000*11%),((BU98-300000)*11%))),("")) -> 33000 | BY98: =IF(((BU98-600000)>0),(IF((BU98>1100000),(500000*15%),((BU98-600000)*15%))),("")) -> 75000 | BZ98: =IF(((BU98-(1100000))>0),(IF((BU98>(1600000)),((500000)*19%),((BU98-(1100000))*19%))),("")) -> 95000 | CA98: =IF(((BU98-(1600000))>0),(IF((BU98>(3200000)),((1600000)*21%),((BU98-(1600000))*21%))),("")) -> 336000 | CB98: =IF(((BU98-(3200000))>0),(IF((BU98>(3200000)),((BU98-(3200000))*24%),(0))),("")) -> 53683.031 | CC98: =SUM(BW98:CB98) -> 613683.03 | CD98: =1%*BQ98 -> 45295.991 | CE98: =MAX(CC98:CD98) -> 613683.03 | CF98: =+CE98/12 -> 51140.253
A99: 96 | B99: AYAKEME TRINNAH IYEBIMOWEI | C99: MATHEMATICS AND COMPUTER SCIENCE | D99: LECTURER II | E99: CONUAS 3/1 | F99: STANBIC | G99: 0036984290 | H99: 1796468 | I99: 1846818 | J99: 153901.5 | K99: 38475.375 | L99: 30000 | M99: 230620.67 | N99: =M99*0.35/3 -> 26905.745 | O99: 5000 | R99: 2500 | Z99: 2500 | AI99: 20833.33 | AM99: =M99*0.02 -> 4612.4134 | AN99: 500 | AP99: 74167 | AQ99: 1000 | BA99: 85000 | BE99: 1000 | BH99: =BL99*0.02 -> 5350.5283 | BK99: 32111.1 | BL99: =M99+N99+O99+P99+R99+S99+T99+U99+V99+W99+Y99+Z99+AA99 -> 267526.41 | BM99: =AI99+AJ99+AK99+AL99+AM99+AN99+AP99++AQ99+AR99+AS99+AT99+AU99+AV99+AW99+AX99+AY99+AZ99+BA99+BB99+BC99+BD99+BE99+BG99+BH99+BK99 -> 224574.37 | BP99: =BL99-BM99 -> 42952.043 | BQ99: =BL99*12 -> 3210317 | BR99: =200000+(0.2*BQ99) -> 842063.4 | BS99: =BI99*12 -> 0 | BT99: =SUM(BR99:BS99) -> 842063.4 | BU99: =+BQ99-BT99 -> 2368253.6 | BW99: =IF((BU99>0),(IF((BU99>300000),(300000*7%),(BU99*7%))),(BQ99*1%)) -> 21000 | BX99: =IF((BU99-300000)>0,(IF((BU99>600000),(300000*11%),((BU99-300000)*11%))),("")) -> 33000 | BY99: =IF(((BU99-600000)>0),(IF((BU99>1100000),(500000*15%),((BU99-600000)*15%))),("")) -> 75000 | BZ99: =IF(((BU99-(1100000))>0),(IF((BU99>(1600000)),((500000)*19%),((BU99-(1100000))*19%))),("")) -> 95000 | CA99: =IF(((BU99-(1600000))>0),(IF((BU99>(3200000)),((1600000)*21%),((BU99-(1600000))*21%))),("")) -> 161333.25 | CB99: =IF(((BU99-(3200000))>0),(IF((BU99>(3200000)),((BU99-(3200000))*24%),(0))),("")) | CC99: =SUM(BW99:CB99) -> 385333.25 | CD99: =1%*BQ99 -> 32103.17 | CE99: =MAX(CC99:CD99) -> 385333.25 | CF99: =+CE99/12 -> 32111.104
A100: 97 | B100: AYAKOROMA FOUBIRI BARCLAYS | C100: THEATRE ARTS | D100: DVC ACADEMICS CONTRACT | E100: CONUAS 7/10 | F100: ZENITH | G100: 1005655901 | H100: =M100*12 -> 7200000 | J100: 600000 | K100: 0 | L100: 0 | M100: =SUM(J100:L100) -> 600000 | R100: 2500 | Z100: 2500 | AD100: 62500 | AM100: =M100*0.02 -> 12000 | AN100: 500 | AS100: 1000 | AV100: 5000 | BA100: 207334 | BC100: =M100*0.04 -> 24000 | BE100: 3500 | BH100: =BL100*0.02 -> 12100 | BK100: 99434.67 | BL100: =M100+N100+O100+P100+R100+S100+T100+U100+V100+W100+Y100+Z100+AA100 -> 605000 | BM100: =AI100+AJ100+AK100+AL100+AM100+AN100+AP100++AQ100+AR100+AS100+AT100+AU100+AV100+AW100+AX100+AY100+AZ100+BA100+BB100+BC100+BD100+BE100+BG100+BH100+BK100 -> 364868.67 | BP100: =BL100-BM100 -> 240131.33 | BQ100: =BL100*12 -> 7260000 | BR100: =200000+(0.2*BQ100) -> 1652000 | BS100: =BI100*12 -> 0 | BT100: =SUM(BR100:BS100) -> 1652000 | BU100: =+BQ100-BT100 -> 5608000 | BW100: =IF((BU100>0),(IF((BU100>300000),(300000*7%),(BU100*7%))),(BQ100*1%)) -> 21000 | BX100: =IF((BU100-300000)>0,(IF((BU100>600000),(300000*11%),((BU100-300000)*11%))),("")) -> 33000 | BY100: =IF(((BU100-600000)>0),(IF((BU100>1100000),(500000*15%),((BU100-600000)*15%))),("")) -> 75000 | BZ100: =IF(((BU100-(1100000))>0),(IF((BU100>(1600000)),((500000)*19%),((BU100-(1100000))*19%))),("")) -> 95000 | CA100: =IF(((BU100-(1600000))>0),(IF((BU100>(3200000)),((1600000)*21%),((BU100-(1600000))*21%))),("")) -> 336000 | CB100: =IF(((BU100-(3200000))>0),(IF((BU100>(3200000)),((BU100-(3200000))*24%),(0))),("")) -> 577920 | CC100: =SUM(BW100:CB100) -> 1137920 | CD100: =1%*BQ100 -> 72600 | CE100: =MAX(CC100:CD100) -> 1137920 | CF100: =+CE100/12 -> 94826.667
...

Sheet BANK SCH
A1: BANK SCHEDULE FOR THE MONTH OF FEBRUARY, 2026
A2: S/N | B2: NAMES OF STAFF | C2: BANK | D2: ACCOUNT NUMBER | E2: AMOUNT
A3: 1 | B3: ADEMOLA AYODEJI JOLAYEMI | C3: FIRST | D3: 2017212564 | E3: 329935.29
A4: 2 | B4: SIKOKI FRANCIS DAVID | C4: ACCESS | D4: 0055002341 | E4: 610935.88
A5: 3 | B5: ABUMERE OAMEN ERONMOSELE | C5: ECOBANK | D5: 0072045836 | E5: 623018.96
A6: 4 | B6: DONBEBE WANKASI | C6: ACCESS | D6: 0026574605 | E6: 267286.12
A7: 5 | B7: CHINYERE P. ONONUGBO | C7: UBA | D7: 2088596893 | E7: 267286.12
A8: 6 | B8: DANIEL I. OLORUNFEMI | C8: ACCESS | D8: 0030621811 | E8: 313800.61
A9: 7 | B9: OKOROBIA MARK ATEI | C9: UBA | D9: 1006415522 | E9: 321437.38
A10: 8 | B10: EBISEITEI PRECIOUS | C10: STANBIC IBTC | D10: 0035529328 | E10: 409418.89
A11: 9 | B11: ZIAKEDE SOLOMON KOROYE | C11: GTB | D11: 0237212657 | E11: 243218.51
A12: 10 | B12: DEINGIMO KEME | C12: UBA | D12: 2067246166 | E12: 279644.14
A13: 11 | B13: TARIEBIBO ENAI GEDE | C13: STERLING | D13: 0077840928 | E13: 289156.06
A14: 12 | B14: LAWAL BABATUNDE YUSUF | C14: STERLING | D14: 0071870439 | E14: 216399
A15: 13 | B15: NEIN GODKNOWS | C15: UNION | D15: 0029213035 | E15: 459007.74
A16: 14 | B16: ECHETA O SYDNEY | C16: FIRST | D16: 3013002388 | E16: 397502.9
A17: 15 | B17: OGBUTA ANTHONY ANWULI | C17: FIRST | D17: 3041696126 | E17: 283489.39
A18: 16 | B18: WAIDOR KEITH TAMARAEBI | C18: WEMA | D18: 0227351994 | E18: 301680.09
A19: 17 | B19: ODUBO CHARITY TAMARAUEBI | C19: STANBIC IBTC | D19: 0019236855 | E19: 257459.55
A20: 18 | B20: OLADIPO ABOSEDE MOJISOLA | C20: ZENITH | D20: 2178561969 | E20: 292489.39
A21: 19 | B21: BOLOUPREMO TARILA | C21: STERLING | D21: 0077210321 | E21: 344675.66
A22: 20 | B22: EKOKEME TAMARAUKRO TIMIPRE | C22: GTB | D22: 0036064176 | E22: 370334.36
A23: 21 | B23: KROKEME OKOYAN | C23: STANBIC IBTC | D23: 0033854745 | E23: 216857.87
A24: 22 | B24: ADIM CHIDIEBERE VICTOR | C24: GTB | D24: 0035615588 | E24: 390751.96
A25: 23 | B25: LUBO EBISINE | C25: STERLING | D25: 0079015111 | E25: 64000.055
A26: 24 | B26: OKABA EBIKONBOWEI ALEX | C26: STERLING | D26: 0059407958 | E26: 26884.054
A27: 25 | B27: ORIBHABOR BLESSING CHINELO | C27: FIRST | D27: 2035909165 | E27: 108831.35
A28: 26 | B28: FRANK SAPELE FUNKEYE | C28: STERLING | D28: 0073394429 | E28: 350566.05
A29: 27 | B29: BENSON DUNU TONBRAPADE | C29: UNION | D29: 0010851185 | E29: 284649.26
A30: 28 | B30: IYE RONAMI SAMUEL | C30: ZENITH | D30: 2007556061 | E30: 193142.28
A31: 29 | B31: ANDERSON BLESSING PERE-ERE | C31: STERLING | D31: 0071139983 | E31: 190409.7
A32: 30 | B32: EREBI BOMIEGHA CLEMENT | C32: UBA | D32: 2104479346 | E32: 192409.7
A33: 31 | B33: BRISIBE FRED EMI | C33: ZENITH | D33: 1002357668 | E33: 126445.03
A34: 32 | B34: DISEYE ISOWO | C34: GLOBUS | D34: 2003332007 | E34: 223058.83
A35: 33 | B35: OGUNBODEDE FRANCIS KOLAWOLE | C35: STERLING | D35: 0081963426
A36: 34 | B36: KPODOH DANIEL OYINMIEBI | C36: UBA | D36: 1018108205 | E36: 203142.28
A37: 35 | B37: RICHARD BRILLIANT | C37: STERLING | D37: 0028949995 | E37: 187167.39
A38: 36 | B38: NAPOLEON EBIYEFA | C38: UBA | D38: 2108025545 | E38: 216642.28
A39: 37 | B39: NWOSU NNBUIHE NANCY | C39: FIRST | D39: 3051864825 | E39: 325780.69
A40: 38 | B40: DONATUS OTAIGBE ONOGBOSELE | C40: ZENITH | D40: 1005415103 | E40: 280650.96
A41: 39 | B41: JASPER EZENWAKA | C41: ACCESS | D41: 0016880418 | E41: 577324.36
A42: 40 | B42: PROF. KAYWOOD ELIJAH LEIZOU | C42: STERLING | D42: 0078905710 | E42: 512424.77
A43: 41 | B43: EVANS F.OSAISAI | C43: UBA | D43: 1003548777 | E43: 592424.85
A44: 42 | B44: MATHEW O WEGWU | C44: UBA | D44: 1005008228 | E44: 275162.24
A45: 43 | B45: BUNAKIYE RICHARD JAPHETH | C45: GTB | D45: 0042255731 | E45: 367504.36
A46: 44 | B46: EBINIMI J ANSA | C46: STANBIC IBTC | D46: 9200480279 | E46: 229788.77
A47: 45 | B47: JULIANA IWORIKUMO CONSUL | C47: GTB | D47: 0112692440 | E47: 203788.32
A48: 46 | B48: OLAJIDE ROTIMI | C48: GTB | D48: 0110692501 | E48: 714871
A49: 47 | B49: GOIN LINDA | C49: FIRST | D49: 2019013002 | E49: 227353.17
A50: 48 | B50: TORUPERE KOROYE | C50: FIDELITY | D50: 4021365312 | E50: 478594.92
A51: 49 | B51: UZAKAH RICHARD PREYE | C51: FIRST | D51: 2003315491 | E51: 267254.29
A52: 50 | B52: SUNDAY DUTIMIARIYE ABRAYE | C52: UBA | D52: 2031755814 | E52: 251470.38
A53: 51 | B53: COURT OGELE TIMIEPERE | C53: GTB | D53: 0264701713 | E53: 417988.27
A54: 52 | B54: ABEKI SUNNY OKORO | C54: UBA | D54: 2008477330 | E54: 384205.99
A55: 53 | B55: ELEKE MELBOUNE EBIMIE | C55: GTB | D55: 0042414976 | E55: 333477.74
A56: 54 | B56: OKUTALUKWE TIMOTHY CHIDEIEBERE | C56: UNION | D56: 0030658333 | E56: 197673.13
A57: 55 | B57: GOVERNOR ROSEMARY EBIERE | C57: GTB | D57: 0123891546 | E57: 14575.3
A58: 56 | B58: ANEM IGIRIGI KOKINBO | C58: GTB | D58: 0236337085 | E58: 213331.31
A59: 57 | B59: TAMBOU TAMBRA JOSEPH | C59: FIDELITY | D59: 6019233197 | E59: 131685.8
A60: 58 | B60: ODOGU TERRY KEME ZUODE | C60: STERLING | D60: 0073932676 | E60: 432923.44
A61: 59 | B61: TEKE CALYDAY ENEGBOGIENEGHA | C61: UBA | D61: 2022811512 | E61: 173726.8
A62: 60 | B62: AKWARANDU UZOCHUKWU | C62: UNION | D62: 0139319511 | E62: 209499.35
A63: 61 | B63: NIMIZIGHA AKPOUNIMIBOFA ALI | C63: STERLING | D63: 0078534068 | E63: 256077.65
A64: 62 | B64: ALAGOA BIOBELEMOYE MINADUM | C64: GTB | D64: 0125565342 | E64: 290798.84
A65: 63 | B65: FELIX IZIRIN UYABARA | C65: FIRST | D65: 3050764643 | E65: 292798.84
A66: 64 | B66: AKINOLA STELLA TONYO | C66: GTB | D66: 0039347458 | E66: 249922.72
A67: 65 | B67: ROSE BINI OKIY | C67: GTB | D67: 0255024937 | E67: 695684.32
A68: 66 | B68: SOLOMON TAMARABRAKEMI EBOBRAH | C68: GTB | D68: 0106451794 | E68: 1166729.7
A69: 67 | B69: AUGUSTINE ADINOYI MATHEW | C69: GTB | D69: 0226553877 | E69: 271558.25
A70: 68 | B70: EBIKABOWEI MUSAH | C70: FCMB | D70: 2908285016 | E70: 201840.13
A71: 69 | B71: OTOBO FIRSTMAN NOAH | C71: ACCESS | D71: 0022777800 | E71: 292798.84
A72: 70 | B72: ADEDIRE TUNDE PETER | C72: FIRST | D72: 3036135498 | E72: 38144.145
A73: 71 | B73: UKACHUKU SAMUEL | C73: GTB | D73: 0117332949 | E73: 300644.14
A74: 72 | B74: ENIZE TINA | C74: FIRST | D74: 3053511556 | E74: 110325.96
A75: 73 | B75: OGBOLE FAITH AJIEBABHLO | C75: GTB | D75: 0037050075 | E75: 381001.96
A76: 74 | B76: TOUNAREGHA AKPOSEIMOKUMO | C76: FIRST | D76: 3068164624 | E76: 173918.3
A77: 75 | B77: FAWEI OWEI EBIFAGHE | C77: UBA | D77: 2021129919 | E77: 214584.97
A78: 76 | B78: UDO SAMUEL JACKSON | C78: ZENITH | D78: 2048397326 | E78: 396589.12
A79: 77 | B79: STANLEY LEADER | C79: STERLING | D79: 0072348209 | E79: 491891.12
A80: 78 | B80: THOMPSON OLUSEGUN EWATA | C80: STERLING | D80: 0078855831 | E80: 192828.46
A81: 79 | B81: JAMES ONUKWU NWABIANKE | C81: FIDELITY | D81: 6230686439 | E81: 393336.24
A82: 80 | B82: GODWIN POI | C82: STERLING | D82: 0005457479 | E82: 742593.28
A83: 81 | B83: AGWI, CELESTINE UCHE | C83: FIRST | D83: 2022988252 | E83: 387503.91
A84: 82 | B84: JACKSON AKPOJARO | C84: STERLING | D84: 0078675839 | E84: 2629.4899
A85: 83 | B85: TONY EBIMOWEI GANAGANA | C85: UBA | D85: 2090470273 | E85: 575961.83
A86: 84 | B86: IBB ANDREW ALI | C86: GTB | D86: 0018837194 | E86: 287749.58
A87: 85 | B87: OPOMU FELIX EBIKETONMOR | C87: STERLING | D87: 0086611904 | E87: 265644.14
A88: 86 | B88: ABOMA GLORIA | C88: KEYSTONE | D88: 6016293250 | E88: 97003.027
A89: 87 | B89: SIGAH DONY AYEBAZUOMUNO | C89: STERLING | D89: 0078336901 | E89: 21198.964
A90: 88 | B90: EDE TIEKUMO | C90: GTB | D90: 0041596422 | E90: 276298.5
A91: 89 | B91: BRAKEMI CHRISTABEL OVIA | C91: ZENITH | D91: 2008091891 | E91: 185824.95
A92: 90 | B92: AKOLOH-ISAAC JOSEPHINE TIMIPRE | C92: ACCESS | D92: 0694547829 | E92: 120868.83
A93: 91 | B93: OMAMOKE EKEREKE LAYEFA | C93: STERLING | D93: 0006180620 | E93: 287394.14
A94: 92 | B94: EBITARI WOLO | C94: STERLING | D94: 0080567834 | E94: 89135.312
A95: 93 | B95: KOMONIBO ERNEST BOLOUEBI | C95: STERLING | D95: 0081837918 | E95: 287798.84
A96: 94 | B96: ONUCHE UNEKWU | C96: ZENITH | D96: 2005960363 | E96: 418870.32
A97: 95 | B97: IGOLI TIMIPA | C97: STERLING | D97: 0080669855 | E97: 198691.79
A98: 96 | B98: AYAKEME TRINNAH IYEBIMOWEI | C98: STANBIC | D98: 0036984290 | E98: 42952.043
A99: 97 | B99: AYAKOROMA FOUBIRI BARCLAYS | C99: ZENITH | D99: 1005655901 | E99: 240131.33
A100: 98 | B100: OYINKEPREYE SAWYERR-GEORGE | C100: FIRST | D100: 2014998139 | E100: 524111.5
...

Sheet NON TEACHING STAFF
A1: UNIVERSITY OF AFRICA, TORU-ORUA.
A2: NON-TEACHING STAFF SALARY FEBRUARY,2026 | CV2: =CC342 -> 7307490
A3: S/N | B3: NAME OF STAFF | C3: DEPARTMENT | D3: JOB DESCRIPTION | E3: BANK | F3: ACCOUNT NUMBE | G3: GRADE/STEP | H3: scalestep | I3: BANK NAME | J3: ACCT NO | K3: BVN | L3: ANNUAL SALARY | M3: MINIMUM WAGE DIFFERENCE | O3: NEW BASIC | Q3: 25/35% INCREMENT | R3: MINIMUM WAGE | S3: NEW BASIC | T3: SHIFT/CALL DUTY | U3: ARREARS | V3: STIPEND FOR PER TIME TEACHING | W3: FIELD TRIP | X3: EXTRA TEACHING | Y3: PERSONAL OWINGRREARS | Z3: PECULIAR | AA3: EXCESS WORK LOAD | AB3: RESPONSIBILITY | AC3: GENERAL HAZARD | AD3: COMMUNITY RELATION/OTHER ALLOW. | AE3: ='[5] NON-TEACHING STAFF'!$R$2 -> LABOTRATORY HAZARD | AF3: OCCUPATIONAL HARZARD | AG3: DOMESTIC STAFF | AH3: INDUCEMENT | AJ3: MEDICAL ALLOWANCE | AK3: Teaching | AL3: HAZARD | AM3: DOMESTIC STAFF | AN3: Lab wkld | AO3: Rent | AP3: swep | AQ3: Clinical | AR3: NEWSPAPER | AS3: FLORISH WELFARE | AT3: BASIC AND APPLIED SCIENCE WELFARE | AU3: TRANSPORTATION/UTITIY | AV3: SEREBA DIMENSIONAL NIG LTD | AW3: ANUPA | AX3: SSANU | AY3: ECONOMICS DEDUCTION | AZ3: FAE WELFARE DEDUCTION | BA3: SCHOOL FEES GURANTEES | BB3: SALARY ADVANCE | BC3: FSMS WELFARE | BD3: FSS WELFARE | BE3: NASU | BF3: NASU welfare | BG3: FASTGROW | BH3: BURSARY WELFARE | BI3: NAAT DEDUCTION | BJ3: NAAT WELFARE | BK3: ASUU | BL3: UAT RENT | BM3: TOP LIFTERS LIMITED | BN3: BSMICROFINANCE | BO3: UAT CORPORATIVE DEDUCTIONS | BP3: UTILITY | BQ3: DEPENT | BR3: BSETF | BS3: FLORSHINE GLOBAL LIMITED | BT3: BELKARI LOANS | BU3: REFUNDS TO UAT | BV3: EXTRA DEPEND BHIS | BW3: ASUU WELFARE | BX3: UAT CRESTED POLO | BY3: UAT FEMALE FORUM | BZ3: BSETF | CA3: BHIS | CB3: NHF | CC3: P.A.Y.E. | CD3: GROSS PAY | CE3: TOTAL DEDUCTIONS | CF3: NET PAY | CG3: NET PAY | CH3: Gosss Earnings | CI3: Personal Allowance | CJ3: NHF | CK3: Total Non-Taxable Income | CL3: Total Taxable Income | CM3: Minimum tax | CN3: 1st 300K @ 7% | CO3: next 300k @ 11% | CP3: next 500k @ 15% | CQ3: next 500k @ 19% | CR3: next 1.6m @ 21% | CS3: above 3.2m @ 24% | CT3: Min Tax | CU3: Total PAYE Tax | CV3: Monthly PAYE Tax | CW3: 20% Rebate | CX3: ETR | CY3: Current deductions | CZ3: Underpayment (monthly) | DA3: Underpayment (annual) | DB3: REMARK
A4: 327 | B4: MANDA EBIMOBOERE ALICE | C4: LAB TECHNOLOGIST | D4: LABORATORY SENIOR TECHNOLOGIST | E4: GTB | F4: 0112610086 | G4: CONTISS 9/8 | I4: GTB | J4: 0112610086 | K4: 22183492504 | L4: 1967327 | M4: #REF! | N4: 2022036 | O4: 168503 | Q4: 42125.75 | R4: 30000 | S4: 246327.33 | AB4: 25000 | AC4: 2500 | AE4: 30000 | AJ4: 2500 | AL4: 383.33 | AT4: 1000 | AU4: =S4*0.04 -> 9853.0932 | BI4: =S4*0.04 -> 9853.0932 | BL4: 10000 | BO4: 0 | BY4: 2000 | BZ4: 1500 | CA4: 5520.2416 | CC4: 38629.66 | CD4: =AR4+AJ4+AH4+AG4+AE4+AF4+AD4+AC4+AB4+AA4+Z4+Y4+X4+W4+V4+U4+U4+T4+S4 -> 306327.33 | CE4: 78356.09 | CF4: =CD4-CE4 -> 227971.24 | CG4: =CD4-CF4 -> 78356.09
A5: 328 | B5: IYIDE AFOKOGENE | C5: LAB TECHNOLOGIST | D5: LABORATORY SENIOR TECHNOLOGIST | E5: UBA | F5: 2067399897 | G5: CONTISS 9/8 | I5: UBA | J5: 2067399897 | K5: ='[5] NON-TEACHING STAFF'!$J$4 -> 22271942001 | L5: 1967327 | M5: =S5-#REF! -> #REF! | N5: 2022036 | O5: 168503 | Q5: 42125.75 | R5: 30000 | S5: 246327.33 | AC5: 2500 | AE5: 30000 | AJ5: 2500 | AL5: 383.33 | AO5: 0 | AT5: 1000 | AU5: =S5*0.04 -> 9853.0932 | BI5: =S5*0.04 -> 9853.0932 | BO5: 20000 | BZ5: 1500 | CA5: =CD5*0.02 -> 5626.5466 | CC5: 34429.66 | CD5: =AR5+AJ5+AH5+AG5+AE5+AF5+AD5+AC5+AB5+AA5+Z5+Y5+X5+W5+V5+U5+U5+T5+S5 -> 281327.33 | CE5: =SUM(AU5:CC5)+AT5 -> 82262.393 | CF5: =CD5-CE5 -> 199064.94 | CG5: =CD5-CF5 -> 82262.393 | CH5: ='[6]JACKSON AKPOJARO '!C163*12 -> #REF! | CI5: =200000+(0.2*CH5) -> #REF! | CJ5: =CB5*12 -> 0 | CK5: =SUM(CI5:CJ5) -> #REF! | CL5: =+CH5-CK5 -> #REF! | CN5: =IF((CL5>0),(IF((CL5>300000),(300000*7%),(CL5*7%))),(CH5*1%)) -> #REF! | CO5: =IF((CL5-300000)>0,(IF((CL5>600000),(300000*11%),((CL5-300000)*11%))),("")) -> #REF! | CP5: =IF(((CL5-600000)>0),(IF((CL5>1100000),(500000*15%),((CL5-600000)*15%))),("")) -> #REF! | CQ5: =IF(((CL5-(1100000))>0),(IF((CL5>(1600000)),((500000)*19%),((CL5-(1100000))*19%))),("")) -> #REF! | CR5: =IF(((CL5-(1600000))>0),(IF((CL5>(3200000)),((1600000)*21%),((CL5-(1600000))*21%))),("")) -> #REF! | CS5: =IF(((CL5-(3200000))>0),(IF((CL5>(3200000)),((CL5-(3200000))*24%),(0))),("")) -> #REF! | CT5: =1%*CH5 -> #REF! | CU5: =MAX(CT5:CT5) -> #REF! | CV5: =CC5 -> 34429.66
A6: 329 | B6: DANIEL IKOROMO ZIKIRI | C6: LAB TECHNOLOGIST | D6: LABORATORY SENIOR TECHNOLOGIST I | E6: FIDELITY | F6: 6017466005 | G6: CONTISS 9/8 | I6: FIDELITY | J6: 6017466005 | K6: ='[5] NON-TEACHING STAFF'!$J$5 -> 22297388274 | L6: 1967327 | M6: =S6-#REF! -> #REF! | N6: 2022036 | O6: 168503 | Q6: 42125.75 | R6: 30000 | S6: 246327.33 | AB6: 25000 | AC6: 2500 | AE6: 30000 | AJ6: 2500 | AL6: 383.33 | AO6: 0 | AT6: 1000 | AU6: =S6*0.04 -> 9853.0932 | BI6: 9625.15 | BO6: 100000 | BZ6: 1500 | CA6: =CD6*0.02 -> 6126.5466 | CB6: 0 | CC6: 38629.66 | CD6: =AR6+AJ6+AH6+AG6+AE6+AF6+AD6+AC6+AB6+AA6+Z6+Y6+X6+W6+V6+U6+U6+T6+S6 -> 306327.33 | CE6: =SUM(AU6:CC6)+AT6 -> 166734.45 | CF6: =CD6-CE6 -> 139592.88 | CG6: =CD6-CF6 -> 166734.45 | CH6: ='[6]JACKSON AKPOJARO '!C166*12 -> #REF! | CI6: =200000+(0.2*CH6) -> #REF! | CJ6: =CB6*12 -> 0 | CK6: =SUM(CI6:CJ6) -> #REF! | CL6: =+CH6-CK6 -> #REF! | CN6: =IF((CL6>0),(IF((CL6>300000),(300000*7%),(CL6*7%))),(CH6*1%)) -> #REF! | CO6: =IF((CL6-300000)>0,(IF((CL6>600000),(300000*11%),((CL6-300000)*11%))),("")) -> #REF! | CP6: =IF(((CL6-600000)>0),(IF((CL6>1100000),(500000*15%),((CL6-600000)*15%))),("")) -> #REF! | CQ6: =IF(((CL6-(1100000))>0),(IF((CL6>(1600000)),((500000)*19%),((CL6-(1100000))*19%))),("")) -> #REF! | CR6: =IF(((CL6-(1600000))>0),(IF((CL6>(3200000)),((1600000)*21%),((CL6-(1600000))*21%))),("")) -> #REF! | CS6: =IF(((CL6-(3200000))>0),(IF((CL6>(3200000)),((CL6-(3200000))*24%),(0))),("")) -> #REF! | CT6: =1%*CH6 -> #REF! | CU6: =MAX(CT6:CT6) -> #REF! | CV6: =CC6 -> 38629.66
A7: 330 | B7: TAIGER A BIBOWEI | C7: REGISTRY | D7: PRINCIPAL ASSISTANT REGISTRAR | E7: GTB | F7: 0042413711 | G7: CONTISS 13/5 | I7: GTB | J7: 0042413711 | K7: ='[5] NON-TEACHING STAFF'!$J$7 -> 22179869639 | L7: 2652896 | M7: =S7-#REF! -> #REF! | N7: 3397732 | O7: 283144.33 | Q7: 70786.083 | R7: 30000 | S7: 397013.92 | AA7: =S7*0.35/3 -> 46318.291 | AB7: 25000 | AC7: 2500 | AJ7: 2500 | AL7: 383.33 | AO7: 0 | AU7: =S7*0.04 -> 15880.557 | AW7: 2500 | AX7: =S7*0.02 -> 7940.2784 | BL7: 7500 | BO7: 35000 | BZ7: 2500 | CA7: =CD7*0.02 -> 9466.6442 | CC7: 69546.45 | CD7: =AR7+AJ7+AH7+AG7+AE7+AF7+AD7+AC7+AB7+AA7+Z7+Y7+X7+W7+V7+U7+U7+T7+S7 -> 473332.21 | CE7: =SUM(AU7:CC7)+AT7 -> 150333.93 | CF7: =CD7-CE7 -> 322998.28 | CG7: =CD7-CF7 -> 150333.93 | CH7: ='[6]JACKSON AKPOJARO '!C167*12 -> #REF! | CI7: =200000+(0.2*CH7) -> #REF! | CJ7: =CB7*12 -> 0 | CK7: =SUM(CI7:CJ7) -> #REF! | CL7: =+CH7-CK7 -> #REF! | CN7: =IF((CL7>0),(IF((CL7>300000),(300000*7%),(CL7*7%))),(CH7*1%)) -> #REF! | CO7: =IF((CL7-300000)>0,(IF((CL7>600000),(300000*11%),((CL7-300000)*11%))),("")) -> #REF! | CP7: =IF(((CL7-600000)>0),(IF((CL7>1100000),(500000*15%),((CL7-600000)*15%))),("")) -> #REF! | CQ7: =IF(((CL7-(1100000))>0),(IF((CL7>(1600000)),((500000)*19%),((CL7-(1100000))*19%))),("")) -> #REF! | CR7: =IF(((CL7-(1600000))>0),(IF((CL7>(3200000)),((1600000)*21%),((CL7-(1600000))*21%))),("")) -> #REF! | CS7: =IF(((CL7-(3200000))>0),(IF((CL7>(3200000)),((CL7-(3200000))*24%),(0))),("")) -> #REF! | CT7: =1%*CH7 -> #REF! | CU7: =MAX(CT7:CT7) -> #REF! | CV7: =CC7 -> 69546.45
A8: 331 | B8: AMAEGBE F. IDUATE O | C8: REGISTRY | D8: ADMIN OFFICR | E8: FIDELITY | F8: 5331903472 | G8: CONTISS 8/6 | I8: FIDELITY | J8: 5331903472 | K8: ='[5] NON-TEACHING STAFF'!$J$9 -> 22343652566 | L8: 1556908 | M8: =S8-#REF! -> #REF! | N8: 1661433 | O8: 138452.75 | Q8: 34613.188 | R8: 30000 | S8: 208310.75 | AC8: 2500 | AE8: =AE6 -> 30000 | AJ8: 2500 | AL8: 383.33 | AU8: =S8*0.04 -> 8332.43 | AW8: 1500 | BL8: 10000 | BO8: 82500 | BZ8: 1000 | CA8: =CD8*0.02 -> 4866.215 | CC8: 28042.87 | CD8: =AR8+AJ8+AH8+AG8+AE8+AF8+AD8+AC8+AB8+AA8+Z8+Y8+X8+W8+V8+U8+U8+T8+S8 -> 243310.75 | CE8: =SUM(AU8:CC8)+AT8 -> 136241.52 | CF8: =CD8-CE8 -> 107069.24 | CG8: =CD8-CF8 -> 136241.52 | CH8: ='[6]JACKSON AKPOJARO '!C168*12 -> #REF! | CI8: =200000+(0.2*CH8) -> #REF! | CJ8: =CB8*12 -> 0 | CK8: =SUM(CI8:CJ8) -> #REF! | CL8: =+CH8-CK8 -> #REF! | CN8: =IF((CL8>0),(IF((CL8>300000),(300000*7%),(CL8*7%))),(CH8*1%)) -> #REF! | CO8: =IF((CL8-300000)>0,(IF((CL8>600000),(300000*11%),((CL8-300000)*11%))),("")) -> #REF! | CP8: =IF(((CL8-600000)>0),(IF((CL8>1100000),(500000*15%),((CL8-600000)*15%))),("")) -> #REF! | CQ8: =IF(((CL8-(1100000))>0),(IF((CL8>(1600000)),((500000)*19%),((CL8-(1100000))*19%))),("")) -> #REF! | CR8: =IF(((CL8-(1600000))>0),(IF((CL8>(3200000)),((1600000)*21%),((CL8-(1600000))*21%))),("")) -> #REF! | CS8: =IF(((CL8-(3200000))>0),(IF((CL8>(3200000)),((CL8-(3200000))*24%),(0))),("")) -> #REF! | CT8: =1%*CH8 -> #REF! | CU8: =MAX(CT8:CT8) -> #REF! | CV8: =CC8 -> 28042.87
A9: 332 | B9: CHRISTIAN ARUOTU PORIPO | C9: REGISTRY | D9: PRINCIPAL ASSISTANT REGISTRAR | E9: STERLING | F9: 0076214212 | G9: CONTISS 13/1 | I9: STERLING | J9: 0076214212 | K9: ='[5] NON-TEACHING STAFF'!$J$9 -> 22343652566 | L9: 2915643 | M9: =S9-#REF! -> #REF! | N9: 3003155 | O9: 191880.5 | Q9: 47970.125 | R9: 30000 | S9: 344679.75 | AA9: 46318.29 | AB9: 25000 | AC9: 2500 | AH9: 46000 | AJ9: 2500 | AL9: 383.33 | AU9: =S9*0.04 -> 13787.19 | AW9: 2500 | AX9: =S9*0.02 -> 6893.595 | BL9: 7500 | BO9: 96912.25 | BZ9: 2000 | CA9: =CD9*0.02 -> 9339.9608 | CC9: 68330.29 | CD9: =AR9+AJ9+AH9+AG9+AE9+AF9+AD9+AC9+AB9+AA9+Z9+Y9+X9+W9+V9+U9+U9+T9+S9 -> 466998.04 | CE9: =SUM(AU9:CC9)+AT9 -> 207263.29 | CF9: =CD9-CE9 -> 259734.75 | CG9: =CD9-CF9 -> 207263.29 | CH9: ='[6]JACKSON AKPOJARO '!C169*12 -> #REF! | CI9: =200000+(0.2*CH9) -> #REF! | CJ9: =CB9*12 -> 0 | CK9: =SUM(CI9:CJ9) -> #REF! | CL9: =+CH9-CK9 -> #REF! | CN9: =IF((CL9>0),(IF((CL9>300000),(300000*7%),(CL9*7%))),(CH9*1%)) -> #REF! | CO9: =IF((CL9-300000)>0,(IF((CL9>600000),(300000*11%),((CL9-300000)*11%))),("")) -> #REF! | CP9: =IF(((CL9-600000)>0),(IF((CL9>1100000),(500000*15%),((CL9-600000)*15%))),("")) -> #REF! | CQ9: =IF(((CL9-(1100000))>0),(IF((CL9>(1600000)),((500000)*19%),((CL9-(1100000))*19%))),("")) -> #REF! | CR9: =IF(((CL9-(1600000))>0),(IF((CL9>(3200000)),((1600000)*21%),((CL9-(1600000))*21%))),("")) -> #REF! | CS9: =IF(((CL9-(3200000))>0),(IF((CL9>(3200000)),((CL9-(3200000))*24%),(0))),("")) -> #REF! | CT9: =1%*CH9 -> #REF! | CU9: =MAX(CT9:CT9) -> #REF! | CV9: =CC9 -> 68330.29
A10: 333 | B10: KENIGUA SUOTON PRECIOUS | C10: WORKS AND SERVICES | D10: PRINCIPAL ENGINEER | E10: UBA | F10: 2047902019 | G10: CONTISS 13/1 | I10: UBA | J10: 2047902019 | K10: ='[5] NON-TEACHING STAFF'!$J$10 -> 22326449084 | L10: 2915643 | M10: =S10-#REF! -> #REF! | N10: 3003155 | O10: 191880.5 | Q10: 47970.125 | R10: 30000 | S10: 344679.75 | AA10: 46318.29 | AB10: 25000 | AC10: 2500 | AJ10: 2500 | AL10: 383.33 | AU10: =S10*0.04 -> 13787.19 | AX10: =S10*0.02 -> 6893.595 | BO10: 10000 | BZ10: 2000 | CA10: =CD10*0.02 -> 8419.9608 | CC10: 59498.29 | CD10: =AR10+AJ10+AH10+AG10+AE10+AF10+AD10+AC10+AB10+AA10+Z10+Y10+X10+W10+V10+U10+U10+T10+S10 -> 420998.04 | CE10: =SUM(AU10:CC10)+AT10 -> 100599.04 | CF10: =CD10-CE10 -> 320399 | CG10: =CD10-CF10 -> 100599.04 | CH10: ='[6]JACKSON AKPOJARO '!C170*12 -> #REF! | CI10: =200000+(0.2*CH10) -> #REF! | CJ10: =CB10*12 -> 0 | CK10: =SUM(CI10:CJ10) -> #REF! | CL10: =+CH10-CK10 -> #REF! | CN10: =IF((CL10>0),(IF((CL10>300000),(300000*7%),(CL10*7%))),(CH10*1%)) -> #REF! | CO10: =IF((CL10-300000)>0,(IF((CL10>600000),(300000*11%),((CL10-300000)*11%))),("")) -> #REF! | CP10: =IF(((CL10-600000)>0),(IF((CL10>1100000),(500000*15%),((CL10-600000)*15%))),("")) -> #REF! | CQ10: =IF(((CL10-(1100000))>0),(IF((CL10>(1600000)),((500000)*19%),((CL10-(1100000))*19%))),("")) -> #REF! | CR10: =IF(((CL10-(1600000))>0),(IF((CL10>(3200000)),((1600000)*21%),((CL10-(1600000))*21%))),("")) -> #REF! | CS10: =IF(((CL10-(3200000))>0),(IF((CL10>(3200000)),((CL10-(3200000))*24%),(0))),("")) -> #REF! | CT10: =1%*CH10 -> #REF! | CU10: =MAX(CT10:CT10) -> #REF! | CV10: =CC10 -> 59498.29
A11: 334 | B11: AGBALAIKO EBIOKENEMO | C11: REGISTRY | D11: PRINCIPAL ASSISTANT REGISTRAR | E11: FIDELITY | F11: 6170236860 | G11: CONTISS 13/1 | I11: FIDELITY | J11: 6170236860 | K11: ='[5] NON-TEACHING STAFF'!$J$11 -> 22309529464 | L11: 2915643 | M11: =S11-#REF! -> #REF! | N11: 3003155 | O11: 191880.5 | Q11: 47970.125 | R11: 30000 | S11: 344679.75 | AA11: 46318.29 | AB11: 25000 | AC11: 2500 | AJ11: 2500 | AL11: 383.33 | AU11: =S11*0.04 -> 13787.19 | AW11: 2500 | AX11: =S11*0.02 -> 6893.595 | BO11: 103750.33 | BZ11: 2000 | CA11: =CD11*0.02 -> 8419.9608 | CC11: 59498.29 | CD11: =AR11+AJ11+AH11+AG11+AE11+AF11+AD11+AC11+AB11+AA11+Z11+Y11+X11+W11+V11+U11+U11+T11+S11 -> 420998.04 | CE11: =SUM(AU11:CC11)+AT11 -> 196849.37 | CF11: =CD11-CE11 -> 224148.67 | CG11: =CD11-CF11 -> 196849.37 | CH11: ='[6]JACKSON AKPOJARO '!C171*12 -> #REF! | CI11: =200000+(0.2*CH11) -> #REF! | CJ11: =CB11*12 -> 0 | CK11: =SUM(CI11:CJ11) -> #REF! | CL11: =+CH11-CK11 -> #REF! | CN11: =IF((CL11>0),(IF((CL11>300000),(300000*7%),(CL11*7%))),(CH11*1%)) -> #REF! | CO11: =IF((CL11-300000)>0,(IF((CL11>600000),(300000*11%),((CL11-300000)*11%))),("")) -> #REF! | CP11: =IF(((CL11-600000)>0),(IF((CL11>1100000),(500000*15%),((CL11-600000)*15%))),("")) -> #REF! | CQ11: =IF(((CL11-(1100000))>0),(IF((CL11>(1600000)),((500000)*19%),((CL11-(1100000))*19%))),("")) -> #REF! | CR11: =IF(((CL11-(1600000))>0),(IF((CL11>(3200000)),((1600000)*21%),((CL11-(1600000))*21%))),("")) -> #REF! | CS11: =IF(((CL11-(3200000))>0),(IF((CL11>(3200000)),((CL11-(3200000))*24%),(0))),("")) -> #REF! | CT11: =1%*CH11 -> #REF! | CU11: =MAX(CT11:CT11) -> #REF! | CV11: =CC11 -> 59498.29
A12: 335 | B12: ORIANGO O IDIGIENENI | C12: REGISTRY | D12: SENIOR ASSISTANT REGISTRAR | E12: FIRST | F12: 3119660547 | G12: CONTISS 11/3 | I12: FIRST | J12: 3119660547 | K12: ='[5] NON-TEACHING STAFF'!$J$12 -> 22242094308 | L12: 2022036 | M12: =S12-#REF! -> #REF! | N12: 2214985 | O12: 184582.08 | Q12: 46145.521 | R12: 30000 | S12: 269850.63 | AC12: 2500 | AH12: 46000 | AJ12: 2500 | AL12: 383.33 | AU12: =S12*0.04 -> 10794.025 | AW12: 2000 | AX12: =S12*0.02 -> 5397.0126 | BL12: 10000 | BM12: ='TopLifters '!C7 -> 66667 | BO12: 30000 | BX12: 5000 | BY12: 2000 | BZ12: 2000 | CA12: =CD12*0.02 -> 6417.0126 | CC12: 41069.57 | CD12: =AR12+AJ12+AH12+AG12+AE12+AF12+AD12+AC12+AB12+AA12+Z12+Y12+X12+W12+V12+U12+U12+T12+S12 -> 320850.63 | CE12: =SUM(AU12:CC12)+AT12 -> 181344.62 | CF12: =CD12-CE12 -> 139506.01 | CG12: =CD12-CF12 -> 181344.62 | CH12: ='[6]JACKSON AKPOJARO '!C172*12 -> #REF! | CI12: =200000+(0.2*CH12) -> #REF! | CJ12: =CB12*12 -> 0 | CK12: =SUM(CI12:CJ12) -> #REF! | CL12: =+CH12-CK12 -> #REF! | CN12: =IF((CL12>0),(IF((CL12>300000),(300000*7%),(CL12*7%))),(CH12*1%)) -> #REF! | CO12: =IF((CL12-300000)>0,(IF((CL12>600000),(300000*11%),((CL12-300000)*11%))),("")) -> #REF! | CP12: =IF(((CL12-600000)>0),(IF((CL12>1100000),(500000*15%),((CL12-600000)*15%))),("")) -> #REF! | CQ12: =IF(((CL12-(1100000))>0),(IF((CL12>(1600000)),((500000)*19%),((CL12-(1100000))*19%))),("")) -> #REF! | CR12: =IF(((CL12-(1600000))>0),(IF((CL12>(3200000)),((1600000)*21%),((CL12-(1600000))*21%))),("")) -> #REF! | CS12: =IF(((CL12-(3200000))>0),(IF((CL12>(3200000)),((CL12-(3200000))*24%),(0))),("")) -> #REF! | CT12: =1%*CH12 -> #REF! | CU12: =MAX(CT12:CT12) -> #REF! | CV12: =CC12 -> 41069.57
A13: 336 | B13: NIMIFAA ISOBOYE WALTER | C13: REGISTRY | D13: ADMIN OFFICR | E13: FIDELITY | F13: 6239775462 | G13: CONTISS 13/1 | I13: FIDELITY | J13: 6239775462 | K13: ='[5] NON-TEACHING STAFF'!$J$13 -> 22282150042 | L13: =L11 -> 2915643 | M13: =S13-#REF! -> #REF! | N13: 3003155 | O13: 191880.5 | Q13: 47970.125 | R13: 30000 | S13: 344679.75 | AA13: 46318.29 | AB13: 12500 | AC13: 2500 | AJ13: 2500 | AL13: 383.33 | AU13: =S13*0.04 -> 13787.19 | AW13: 2500 | AX13: =S13*0.02 -> 6893.595 | BO13: 26666.667 | BZ13: 2000 | CA13: =CD13*0.02 -> 8169.9608 | CC13: 57098.29 | CD13: =AR13+AJ13+AH13+AG13+AE13+AF13+AD13+AC13+AB13+AA13+Z13+Y13+X13+W13+V13+U13+U13+T13+S13 -> 408498.04 | CE13: =SUM(AU13:CC13)+AT13 -> 117115.7 | CF13: =CD13-CE13 -> 291382.34 | CG13: =CD13-CF13 -> 117115.7 | CH13: ='[6]JACKSON AKPOJARO '!C173*12 -> #REF! | CI13: =200000+(0.2*CH13) -> #REF! | CJ13: =CB13*12 -> 0 | CK13: =SUM(CI13:CJ13) -> #REF! | CL13: =+CH13-CK13 -> #REF! | CN13: =IF((CL13>0),(IF((CL13>300000),(300000*7%),(CL13*7%))),(CH13*1%)) -> #REF! | CO13: =IF((CL13-300000)>0,(IF((CL13>600000),(300000*11%),((CL13-300000)*11%))),("")) -> #REF! | CP13: =IF(((CL13-600000)>0),(IF((CL13>1100000),(500000*15%),((CL13-600000)*15%))),("")) -> #REF! | CQ13: =IF(((CL13-(1100000))>0),(IF((CL13>(1600000)),((500000)*19%),((CL13-(1100000))*19%))),("")) -> #REF! | CR13: =IF(((CL13-(1600000))>0),(IF((CL13>(3200000)),((1600000)*21%),((CL13-(1600000))*21%))),("")) -> #REF! | CS13: =IF(((CL13-(3200000))>0),(IF((CL13>(3200000)),((CL13-(3200000))*24%),(0))),("")) -> #REF! | CT13: =1%*CH13 -> #REF! | CU13: =MAX(CT13:CT13) -> #REF! | CV13: =CC13 -> 57098.29
A14: 337 | B14: DESMOND FRESH | C14: WORKS AND SERVICES | D14: MASON | E14: ACCESS | F14: 0032325040 | G14: CONTISS 4/10 | I14: ACCESS | J14: 0032325040 | K14: ='[5] NON-TEACHING STAFF'!$J$14 -> 22344927920 | L14: 520773 | M14: =S14-#REF! -> #REF! | N14: 520773 | O14: 43397.75 | Q14: 10849.438 | R14: 42499.98 | S14: 99732.83 | AC14: 2500 | AJ14: 2500 | AL14: 383.33 | AU14: =S14*0.03 -> 2991.9849 | BB14: 25000 | BE14: =S14*0.03 -> 2991.9849 | BO14: 45625 | BZ14: 500 | CA14: =CD14*0.02 -> 2094.6566 | CC14: 7067.94 | CD14: =AR14+AJ14+AH14+AG14+AE14+AF14+AD14+AC14+AB14+AA14+Z14+Y14+X14+W14+V14+U14+U14+T14+S14 -> 104732.83 | CE14: =SUM(AU14:CC14)+AT14 -> 86271.566 | CF14: =CD14-CE14 -> 18461.264 | CG14: =CD14-CF14 -> 86271.566 | CH14: ='[6]JACKSON AKPOJARO '!C174*12 -> #REF! | CI14: =200000+(0.2*CH14) -> #REF! | CJ14: =CB14*12 -> 0 | CK14: =SUM(CI14:CJ14) -> #REF! | CL14: =+CH14-CK14 -> #REF! | CN14: =IF((CL14>0),(IF((CL14>300000),(300000*7%),(CL14*7%))),(CH14*1%)) -> #REF! | CO14: =IF((CL14-300000)>0,(IF((CL14>600000),(300000*11%),((CL14-300000)*11%))),("")) -> #REF! | CP14: =IF(((CL14-600000)>0),(IF((CL14>1100000),(500000*15%),((CL14-600000)*15%))),("")) -> #REF! | CQ14: =IF(((CL14-(1100000))>0),(IF((CL14>(1600000)),((500000)*19%),((CL14-(1100000))*19%))),("")) -> #REF! | CR14: =IF(((CL14-(1600000))>0),(IF((CL14>(3200000)),((1600000)*21%),((CL14-(1600000))*21%))),("")) -> #REF! | CS14: =IF(((CL14-(3200000))>0),(IF((CL14>(3200000)),((CL14-(3200000))*24%),(0))),("")) -> #REF! | CT14: =1%*CH14 -> #REF! | CU14: =MAX(CT14:CT14) -> #REF! | CV14: =CC14 -> 7067.94
A15: 338 | B15: TIMI OKPEKE | C15: WORKS AND SERVICES | D15: HIGHER TECHNICAL OFFICER | E15: ZENITH | F15: 2120701852 | G15: CONTISS 7/2 | I15: ZENITH | J15: 2120701852 | K15: ='[5] NON-TEACHING STAFF'!$J$15 -> 22433306432 | L15: 1194251 | M15: =S15-#REF! -> #REF! | N15: 1194251 | O15: 99520.917 | Q15: 24880.229 | R15: 30000.17 | S15: 165441.5 | AC15: 2500 | AJ15: 2500 | AL15: 383.33 | AU15: =S15*0.04 -> 6617.66 | BE15: =S15*0.03 -> 4963.245 | BL15: 7500 | BO15: 0 | BZ15: 500 | CA15: =CD15*0.02 -> 3408.83 | CC15: 16073.77 | CD15: =AR15+AJ15+AH15+AG15+AE15+AF15+AD15+AC15+AB15+AA15+Z15+Y15+X15+W15+V15+U15+U15+T15+S15 -> 170441.5 | CE15: =SUM(AU15:CC15)+AT15 -> 39063.505 | CF15: =CD15-CE15 -> 131377.99 | CG15: =CD15-CF15 -> 39063.505 | CH15: ='[6]JACKSON AKPOJARO '!C175*12 -> #REF! | CI15: =200000+(0.2*CH15) -> #REF! | CJ15: =CB15*12 -> 0 | CK15: =SUM(CI15:CJ15) -> #REF! | CL15: =+CH15-CK15 -> #REF! | CN15: =IF((CL15>0),(IF((CL15>300000),(300000*7%),(CL15*7%))),(CH15*1%)) -> #REF! | CO15: =IF((CL15-300000)>0,(IF((CL15>600000),(300000*11%),((CL15-300000)*11%))),("")) -> #REF! | CP15: =IF(((CL15-600000)>0),(IF((CL15>1100000),(500000*15%),((CL15-600000)*15%))),("")) -> #REF! | CQ15: =IF(((CL15-(1100000))>0),(IF((CL15>(1600000)),((500000)*19%),((CL15-(1100000))*19%))),("")) -> #REF! | CR15: =IF(((CL15-(1600000))>0),(IF((CL15>(3200000)),((1600000)*21%),((CL15-(1600000))*21%))),("")) -> #REF! | CS15: =IF(((CL15-(3200000))>0),(IF((CL15>(3200000)),((CL15-(3200000))*24%),(0))),("")) -> #REF! | CT15: =1%*CH15 -> #REF! | CU15: =MAX(CT15:CT15) -> #REF! | CV15: =CC15 -> 16073.77
A16: 339 | B16: DANIEL SMART AKUNA | C16: WORKS AND SERVICES | D16: CHIEF FOREMAN | E16: UBA | F16: 2185980269 | G16: CONTISS 7/1 | I16: UBA | J16: 2185980269 | K16: ='[5] NON-TEACHING STAFF'!$J$16 -> 22419981006 | L16: 1065971 | M16: =S16-#REF! -> #REF! | N16: 1098041 | O16: 91503.417 | Q16: 22875.854 | R16: 30000 | S16: 160985.42 | AC16: 2500 | AJ16: 2500 | AL16: 383.33 | AU16: =S16*0.04 -> 6439.4168 | BE16: =S16*0.03 -> 4829.5626 | BM16: 66667 | BO16: 0 | BS16: 50720 | BZ16: 500 | CA16: =CD16*0.02 -> 3319.7084 | CC16: 14636.45 | CD16: =AR16+AJ16+AH16+AG16+AE16+AF16+AD16+AC16+AB16+AA16+Z16+Y16+X16+W16+V16+U16+U16+T16+S16 -> 165985.42 | CE16: =SUM(AU16:CC16)+AT16 -> 147112.14 | CF16: =CD16-CE16 -> 18873.282 | CG16: =CD16-CF16 -> 147112.14 | CH16: ='[6]JACKSON AKPOJARO '!C176*12 -> #REF! | CI16: =200000+(0.2*CH16) -> #REF! | CJ16: =CB16*12 -> 0 | CK16: =SUM(CI16:CJ16) -> #REF! | CL16: =+CH16-CK16 -> #REF! | CN16: =IF((CL16>0),(IF((CL16>300000),(300000*7%),(CL16*7%))),(CH16*1%)) -> #REF! | CO16: =IF((CL16-300000)>0,(IF((CL16>600000),(300000*11%),((CL16-300000)*11%))),("")) -> #REF! | CP16: =IF(((CL16-600000)>0),(IF((CL16>1100000),(500000*15%),((CL16-600000)*15%))),("")) -> #REF! | CQ16: =IF(((CL16-(1100000))>0),(IF((CL16>(1600000)),((500000)*19%),((CL16-(1100000))*19%))),("")) -> #REF! | CR16: =IF(((CL16-(1600000))>0),(IF((CL16>(3200000)),((1600000)*21%),((CL16-(1600000))*21%))),("")) -> #REF! | CS16: =IF(((CL16-(3200000))>0),(IF((CL16>(3200000)),((CL16-(3200000))*24%),(0))),("")) -> #REF! | CT16: =1%*CH16 -> #REF! | CU16: =MAX(CT16:CT16) -> #REF! | CV16: =CC16 -> 14636.45
A17: 340 | B17: PEREKEBINA WEI-WEI | C17: WORKS AND SERVICES | D17: ELECTRICIAN | E17: STANBIC | F17: 0021897004 | G17: CONTISS 5/11 | I17: STANBIC IBTC | J17: 0021897004 | K17: ='[5] NON-TEACHING STAFF'!$J$17 -> 22435584786 | L17: 638685 | M17: =S17-#REF! -> #REF! | N17: 638685 | O17: 54679.17 | Q17: 13669.792 | R17: 40000 | S17: 110168.25 | AC17: 2500 | AJ17: 2500 | AL17: 383.33 | AU17: =S17*0.03 -> 3305.0475 | BE17: =S17*0.03 -> 3305.0475 | BO17: 0 | BZ17: 500 | CA17: =CD17*0.02 -> 2303.365 | CC17: 8320.19 | CD17: =AR17+AJ17+AH17+AG17+AE17+AF17+AD17+AC17+AB17+AA17+Z17+Y17+X17+W17+V17+U17+U17+T17+S17 -> 115168.25 | CE17: =SUM(AU17:CC17)+AT17 -> 17733.65 | CF17: =CD17-CE17 -> 97434.6 | CG17: =CD17-CF17 -> 17733.65 | CH17: ='[6]JACKSON AKPOJARO '!C177*12 -> #REF! | CI17: =200000+(0.2*CH17) -> #REF! | CJ17: =CB17*12 -> 0 | CK17: =SUM(CI17:CJ17) -> #REF! | CL17: =+CH17-CK17 -> #REF! | CN17: =IF((CL17>0),(IF((CL17>300000),(300000*7%),(CL17*7%))),(CH17*1%)) -> #REF! | CO17: =IF((CL17-300000)>0,(IF((CL17>600000),(300000*11%),((CL17-300000)*11%))),("")) -> #REF! | CP17: =IF(((CL17-600000)>0),(IF((CL17>1100000),(500000*15%),((CL17-600000)*15%))),("")) -> #REF! | CQ17: =IF(((CL17-(1100000))>0),(IF((CL17>(1600000)),((500000)*19%),((CL17-(1100000))*19%))),("")) -> #REF! | CR17: =IF(((CL17-(1600000))>0),(IF((CL17>(3200000)),((1600000)*21%),((CL17-(1600000))*21%))),("")) -> #REF! | CS17: =IF(((CL17-(3200000))>0),(IF((CL17>(3200000)),((CL17-(3200000))*24%),(0))),("")) -> #REF! | CT17: =1%*CH17 -> #REF! | CU17: =MAX(CT17:CT17) -> #REF! | CV17: =CC17 -> 8320.19
A18: 341 | B18: AKPOEBI ADESI | C18: PO | D18: REGISTRAR | E18: PREMIUM | F18: 0010089462 | G18: CONTISS 15/SP | I18: PREMIUM | J18: 0010089462 | L18: =#REF!*12 -> #REF! | M18: =S18-#REF! -> #REF! | O18: 555351.17 | Q18: 0 | R18: 0 | S18: =SUM(O18:R18) -> 555351.17 | Z18: =[7]Sheet5!$D$22 -> 83302.68 | AB18: ='[5] NON-TEACHING STAFF'!$O$19 -> 62500 | AC18: 2500 | AG18: 60000 | AH18: 52500 | AJ18: 2500 | AL18: 383.33 | AM18: ='[5] NON-TEACHING STAFF'!$P$19 -> 128000 | AU18: =S18*0.04 -> 22214.047 | AW18: 5000 | AX18: =S18*0.02 -> 11107.023 | BB18: 50000 | BO18: 200000 | BX18: 5000 | BZ18: 3500 | CA18: =CD18*0.02 -> 16373.077 | CC18: 135848.21 | CD18: =AR18+AJ18+AH18+AG18+AE18+AF18+AD18+AC18+AB18+AA18+Z18+Y18+X18+W18+V18+U18+U18+T18+S18 -> 818653.85 | CE18: =SUM(AU18:CC18)+AT18 -> 449042.35 | CF18: =CD18-CE18 -> 369611.5 | CG18: =CD18-CF18 -> 449042.35 | CH18: ='[6]JACKSON AKPOJARO '!C181*12 -> #REF! | CI18: =200000+(0.2*CH18) -> #REF! | CJ18: =CB18*12 -> 0 | CK18: =SUM(CI18:CJ18) -> #REF! | CL18: =+CH18-CK18 -> #REF! | CN18: =IF((CL18>0),(IF((CL18>300000),(300000*7%),(CL18*7%))),(CH18*1%)) -> #REF! | CO18: =IF((CL18-300000)>0,(IF((CL18>600000),(300000*11%),((CL18-300000)*11%))),("")) -> #REF! | CP18: =IF(((CL18-600000)>0),(IF((CL18>1100000),(500000*15%),((CL18-600000)*15%))),("")) -> #REF! | CQ18: =IF(((CL18-(1100000))>0),(IF((CL18>(1600000)),((500000)*19%),((CL18-(1100000))*19%))),("")) -> #REF! | CR18: =IF(((CL18-(1600000))>0),(IF((CL18>(3200000)),((1600000)*21%),((CL18-(1600000))*21%))),("")) -> #REF! | CS18: =IF(((CL18-(3200000))>0),(IF((CL18>(3200000)),((CL18-(3200000))*24%),(0))),("")) -> #REF! | CT18: 181556.94 | CU18: =MAX(CT18:CT18) -> 181556.94 | CV18: 181556.94
A19: 342 | B19: UMBE AYEKUROBOTAREGHA | C19: PO | D19: BURSAR | E19: ZENITH | F19: 2285959529 | G19: CONTISS 15/SP | I19: STANBIC IBTC | J19: 9304770409 | K19: ='[5] NON-TEACHING STAFF'!$J$23 -> 22252211997 | L19: 2828060 | M19: =S19-#REF! -> #REF! | O19: 555351.17 | Q19: 0 | R19: 0 | S19: =SUM(O19:R19) -> 555351.17 | V19: 40000 | Z19: =[7]Sheet5!$D$22 -> 83302.68 | AB19: ='[5] NON-TEACHING STAFF'!$O$19 -> 62500 | AC19: 2500 | AG19: 60000 | AH19: 52500 | AJ19: 2500 | AL19: 383.33 | AU19: =S19*0.04 -> 22214.047 | AX19: =S19*0.02 -> 11107.023 | BB19: =250000+83333.33 -> 333333.33 | BH19: 3000 | BO19: 243024 | BX19: 5000 | BZ19: 3500 | CA19: =CD19*0.02 -> 17173.077 | CC19: 143528.21 | CD19: =AR19+AJ19+AH19+AG19+AE19+AF19+AD19+AC19+AB19+AA19+Z19+Y19+X19+W19+V19+U19+U19+T19+S19 -> 858653.85 | CE19: =SUM(AU19:CC19)+AT19 -> 781879.68 | CF19: =CD19-CE19 -> 76774.167 | CG19: =CD19-CF19 -> 781879.68 | CH19: ='[6]JACKSON AKPOJARO '!C183*12 -> #REF! | CI19: =200000+(0.2*CH19) -> #REF! | CJ19: =CB19*12 -> 0 | CK19: =SUM(CI19:CJ19) -> #REF! | CL19: =+CH19-CK19 -> #REF! | CN19: =IF((CL19>0),(IF((CL19>300000),(300000*7%),(CL19*7%))),(CH19*1%)) -> #REF! | CO19: =IF((CL19-300000)>0,(IF((CL19>600000),(300000*11%),((CL19-300000)*11%))),("")) -> #REF! | CP19: =IF(((CL19-600000)>0),(IF((CL19>1100000),(500000*15%),((CL19-600000)*15%))),("")) -> #REF! | CQ19: =IF(((CL19-(1100000))>0),(IF((CL19>(1600000)),((500000)*19%),((CL19-(1100000))*19%))),("")) -> #REF! | CR19: =IF(((CL19-(1600000))>0),(IF((CL19>(3200000)),((1600000)*21%),((CL19-(1600000))*21%))),("")) -> #REF! | CS19: =IF(((CL19-(3200000))>0),(IF((CL19>(3200000)),((CL19-(3200000))*24%),(0))),("")) -> #REF! | CT19: =1%*CH19 -> #REF! | CU19: =MAX(CT19:CT19) -> #REF! | CV19: =CC19 -> 143528.21
A20: 343 | B20: OGORI MICHEAL TOMBOIZIBE | C20: BURSARY | D20: CHIEF ACCOUNTANT | E20: UBA | F20: 2196498670 | G20: CONUASS 13/6 | I20: UBA | J20: 2196498670 | K20: ='[5] NON-TEACHING STAFF'!$J$24 -> 22173480742 | L20: 2828060 | M20: =S20-#REF! -> #REF! | N20: 3523334 | O20: 293611.17 | Q20: 73402.792 | R20: 30000 | S20: 410097.33 | V20: 40000 | AA20: =S20*0.35/3 -> 47844.688 | AB20: 25000 | AC20: 2500 | AH20: 51750 | AJ20: 2500 | AL20: 383.33 | AU20: =S20*0.04 -> 16403.893 | AX20: =S20*0.02 -> 8201.9466 | BH20: 3000 | BO20: 205416.67 | BX20: 5000 | BZ20: 2500 | CA20: =CD20*0.02 -> 11593.84 | CC20: 89967.53 | CD20: =AR20+AJ20+AH20+AG20+AE20+AF20+AD20+AC20+AB20+AA20+Z20+Y20+X20+W20+V20+U20+U20+T20+S20 -> 579692.02 | CE20: =SUM(AU20:CC20)+AT20 -> 342083.88 | CF20: =CD20-CE20 -> 237608.14 | CG20: =CD20-CF20 -> 342083.88 | CH20: ='[6]JACKSON AKPOJARO '!C184*12 -> #REF! | CI20: =200000+(0.2*CH20) -> #REF! | CJ20: =CB20*12 -> 0 | CK20: =SUM(CI20:CJ20) -> #REF! | CL20: =+CH20-CK20 -> #REF! | CN20: =IF((CL20>0),(IF((CL20>300000),(300000*7%),(CL20*7%))),(CH20*1%)) -> #REF! | CO20: =IF((CL20-300000)>0,(IF((CL20>600000),(300000*11%),((CL20-300000)*11%))),("")) -> #REF! | CP20: =IF(((CL20-600000)>0),(IF((CL20>1100000),(500000*15%),((CL20-600000)*15%))),("")) -> #REF! | CQ20: =IF(((CL20-(1100000))>0),(IF((CL20>(1600000)),((500000)*19%),((CL20-(1100000))*19%))),("")) -> #REF! | CR20: =IF(((CL20-(1600000))>0),(IF((CL20>(3200000)),((1600000)*21%),((CL20-(1600000))*21%))),("")) -> #REF! | CS20: =IF(((CL20-(3200000))>0),(IF((CL20>(3200000)),((CL20-(3200000))*24%),(0))),("")) -> #REF! | CT20: =1%*CH20 -> #REF! | CU20: =MAX(CT20:CT20) -> #REF! | CV20: =CC20 -> 89967.53
A21: 344 | B21: ANTHONY IGHIEHON | C21: REGISTRY | D21: PRINCIPAL EXECUTIVE OFICER | E21: STERLING | F21: 0086001435 | G21: CONTISS9/5 | I21: STERLING | J21: 0086001435 | K21: ='[5] NON-TEACHING STAFF'!$J$25 -> 22300772577 | L21: 1762132 | M21: =S21-#REF! -> #REF! | N21: 1857913 | O21: 154826.08 | Q21: 38706.521 | R21: 30000 | S21: 229231.25 | AC21: 2500 | AJ21: 2500 | AL21: 383.33 | AU21: =S21*0.04 -> 9169.25 | AW21: 1500 | AX21: =S21*0.02 -> 4584.625 | BO21: 22666.67 | BZ21: 1000 | CA21: =CD21*0.02 -> 4684.625 | CC21: 25517.52 | CD21: =AR21+AJ21+AH21+AG21+AE21+AF21+AD21+AC21+AB21+AA21+Z21+Y21+X21+W21+V21+U21+U21+T21+S21 -> 234231.25 | CE21: =SUM(AU21:CC21)+AT21 -> 69122.69 | CF21: =CD21-CE21 -> 165108.56 | CG21: =CD21-CF21 -> 69122.69 | CH21: ='[6]JACKSON AKPOJARO '!C185*12 -> #REF! | CI21: =200000+(0.2*CH21) -> #REF! | CJ21: =CB21*12 -> 0 | CK21: =SUM(CI21:CJ21) -> #REF! | CL21: =+CH21-CK21 -> #REF! | CN21: =IF((CL21>0),(IF((CL21>300000),(300000*7%),(CL21*7%))),(CH21*1%)) -> #REF! | CO21: =IF((CL21-300000)>0,(IF((CL21>600000),(300000*11%),((CL21-300000)*11%))),("")) -> #REF! | CP21: =IF(((CL21-600000)>0),(IF((CL21>1100000),(500000*15%),((CL21-600000)*15%))),("")) -> #REF! | CQ21: =IF(((CL21-(1100000))>0),(IF((CL21>(1600000)),((500000)*19%),((CL21-(1100000))*19%))),("")) -> #REF! | CR21: =IF(((CL21-(1600000))>0),(IF((CL21>(3200000)),((1600000)*21%),((CL21-(1600000))*21%))),("")) -> #REF! | CS21: =IF(((CL21-(3200000))>0),(IF((CL21>(3200000)),((CL21-(3200000))*24%),(0))),("")) -> #REF! | CT21: =1%*CH21 -> #REF! | CU21: =MAX(CT21:CT21) -> #REF! | CV21: =CC21 -> 25517.52
A22: 345 | B22: ONWUGBUFOR PRINCE UBA | C22: WORKS AND SERVICES | D22: ICT TECH | E22: FIRST | F22: 3080189126 | G22: CONUASS 8/1 | I22: FIRST | J22: 3080189126 | L22: 1343017 | M22: =S22-#REF! -> #REF! | N22: 1343017 | O22: 111918.08 | Q22: 27979.521 | R22: 30000 | S22: 182087.33 | AC22: 2500 | AJ22: 2500 | AL22: 383.33 | AU22: =S22*0.04 -> 7283.4932 | AX22: =S22*0.02 -> 3641.7466 | BL22: 7500 | BO22: 0 | BZ22: 1000 | CA22: =CD22*0.02 -> 3741.7466 | CC22: 18603.94 | CD22: =AR22+AJ22+AH22+AG22+AE22+AF22+AD22+AC22+AB22+AA22+Z22+Y22+X22+W22+V22+U22+U22+T22+S22 -> 187087.33 | CE22: =SUM(AU22:CC22)+AT22 -> 41770.926 | CF22: =CD22-CE22 -> 145316.4 | CG22: =CD22-CF22 -> 41770.926 | CH22: ='[6]JACKSON AKPOJARO '!C186*12 -> #REF! | CI22: =200000+(0.2*CH22) -> #REF! | CJ22: =CB22*12 -> 0 | CK22: =SUM(CI22:CJ22) -> #REF! | CL22: =+CH22-CK22 -> #REF! | CN22: =IF((CL22>0),(IF((CL22>300000),(300000*7%),(CL22*7%))),(CH22*1%)) -> #REF! | CO22: =IF((CL22-300000)>0,(IF((CL22>600000),(300000*11%),((CL22-300000)*11%))),("")) -> #REF! | CP22: =IF(((CL22-600000)>0),(IF((CL22>1100000),(500000*15%),((CL22-600000)*15%))),("")) -> #REF! | CQ22: =IF(((CL22-(1100000))>0),(IF((CL22>(1600000)),((500000)*19%),((CL22-(1100000))*19%))),("")) -> #REF! | CR22: =IF(((CL22-(1600000))>0),(IF((CL22>(3200000)),((1600000)*21%),((CL22-(1600000))*21%))),("")) -> #REF! | CS22: =IF(((CL22-(3200000))>0),(IF((CL22>(3200000)),((CL22-(3200000))*24%),(0))),("")) -> #REF! | CT22: =1%*CH22 -> #REF! | CU22: =MAX(CT22:CT22) -> #REF! | CV22: =CC22 -> 18603.94
A23: 346 | B23: CHARLES VITUS | C23: WORKS AND SERVICES | D23: WORKS AND SERVICE | E23: GTB | F23: 0473592421 | G23: CONTISS 9/10 | I23: GTB | J23: 0473592421 | K23: ='[5] NON-TEACHING STAFF'!$J$27 -> 22278531941 | L23: 2064227 | M23: =S23-#REF! -> #REF! | N23: 2064227 | O23: 173061.92 | Q23: 43265.48 | R23: 30000 | S23: 257724.67 | AB23: 25000 | AC23: 2500 | AJ23: 2500 | AL23: 383.33 | AU23: =S23*0.04 -> 10308.987 | AW23: 1500 | AX23: =S23*0.02 -> 5154.4934 | BO23: 10000 | BZ23: 1000 | CA23: =CD23*0.02 -> 5754.4934 | CC23: 35504.41 | CD23: =AR23+AJ23+AH23+AG23+AE23+AF23+AD23+AC23+AB23+AA23+Z23+Y23+X23+W23+V23+U23+U23+T23+S23 -> 287724.67 | CE23: =SUM(AU23:CC23)+AT23 -> 69222.384 | CF23: =CD23-CE23 -> 218502.29 | CG23: =CD23-CF23 -> 69222.384 | CH23: ='[6]JACKSON AKPOJARO '!C186*12 -> #REF! | CI23: =200000+(0.2*CH23) -> #REF! | CJ23: =CB23*12 -> 0 | CK23: =SUM(CI23:CJ23) -> #REF! | CL23: =+CH23-CK23 -> #REF! | CN23: =IF((CL23>0),(IF((CL23>300000),(300000*7%),(CL23*7%))),(CH23*1%)) -> #REF! | CO23: =IF((CL23-300000)>0,(IF((CL23>600000),(300000*11%),((CL23-300000)*11%))),("")) -> #REF! | CP23: =IF(((CL23-600000)>0),(IF((CL23>1100000),(500000*15%),((CL23-600000)*15%))),("")) -> #REF! | CQ23: =IF(((CL23-(1100000))>0),(IF((CL23>(1600000)),((500000)*19%),((CL23-(1100000))*19%))),("")) -> #REF! | CR23: =IF(((CL23-(1600000))>0),(IF((CL23>(3200000)),((1600000)*21%),((CL23-(1600000))*21%))),("")) -> #REF! | CS23: =IF(((CL23-(3200000))>0),(IF((CL23>(3200000)),((CL23-(3200000))*24%),(0))),("")) -> #REF! | CT23: =1%*CH23 -> #REF! | CU23: =MAX(CT23:CT23) -> #REF! | CV23: =CC23 -> 35504.41
A24: 347 | B24: SUNDAY PERE GABRIEL | C24: REGISTRY | D24: SENIOR ASSISTANT REGISTRAR | E24: STERLING | F24: 0079517653 | G24: CONTISS 11/6 | I24: STERLING | J24: 0079517653 | K24: ='[5] NON-TEACHING STAFF'!$J$29 -> 22212807961 | L24: 2350280 | M24: =S24-#REF! -> #REF! | N24: 2477732 | O24: 206477.67 | Q24: 51619.417 | R24: 30000 | S24: 297220.17 | AB24: 25000 | AC24: 2500 | AH24: 46000 | AJ24: 2500 | AL24: 383.33 | AU24: =S24*0.04 -> 11888.807 | AW24: 2000 | AX24: =S24*0.02 -> 5944.4034 | BO24: 66666.667 | BZ24: 2000 | CA24: =CD24*0.02 -> 7464.4034 | CC24: 50324.94 | CD24: =AR24+AJ24+AH24+AG24+AE24+AF24+AD24+AC24+AB24+AA24+Z24+Y24+X24+W24+V24+U24+U24+T24+S24 -> 373220.17 | CE24: =SUM(AU24:CC24)+AT24 -> 146289.22 | CF24: =CD24-CE24 -> 226930.95 | CG24: =CD24-CF24 -> 146289.22 | CH24: ='[6]JACKSON AKPOJARO '!C187*12 -> #REF! | CI24: =200000+(0.2*CH24) -> #REF! | CJ24: =CB24*12 -> 0 | CK24: =SUM(CI24:CJ24) -> #REF! | CL24: =+CH24-CK24 -> #REF! | CN24: =IF((CL24>0),(IF((CL24>300000),(300000*7%),(CL24*7%))),(CH24*1%)) -> #REF! | CO24: =IF((CL24-300000)>0,(IF((CL24>600000),(300000*11%),((CL24-300000)*11%))),("")) -> #REF! | CP24: =IF(((CL24-600000)>0),(IF((CL24>1100000),(500000*15%),((CL24-600000)*15%))),("")) -> #REF! | CQ24: =IF(((CL24-(1100000))>0),(IF((CL24>(1600000)),((500000)*19%),((CL24-(1100000))*19%))),("")) -> #REF! | CR24: =IF(((CL24-(1600000))>0),(IF((CL24>(3200000)),((1600000)*21%),((CL24-(1600000))*21%))),("")) -> #REF! | CS24: =IF(((CL24-(3200000))>0),(IF((CL24>(3200000)),((CL24-(3200000))*24%),(0))),("")) -> #REF! | CT24: =1%*CH24 -> #REF! | CU24: =MAX(CT24:CT24) -> #REF! | CV24: =CC24 -> 50324.94
A25: 348 | B25: MIRIKI SOKPARA BABATUNDE | C25: REGISTRY | D25: PRINCIPAL ASSISTANT REGISTRAR | E25: STERLING | F25: 0075673724 | G25: CONTISS 13/7 | I25: STERLING | J25: 0075673724 | L25: 3774536 | M25: =S25-#REF! -> #REF! | N25: 3648934 | O25: 304077.83 | Q25: 76019.458 | R25: 30000 | S25: 423180.92 | AA25: =S25*0.35/3 -> 49371.107 | AB25: 25000 | AC25: 2500 | AJ25: 2500 | AL25: 383.33 | AU25: =S25*0.04 -> 16927.237 | AW25: 2500 | AX25: =S25*0.02 -> 8463.6184 | BB25: 100000 | BL25: 15000 | BO25: 160277.33 | BZ25: 2500 | CA25: =CD25*0.02 -> 10051.041 | CC25: 75156.66 | CD25: =AR25+AJ25+AH25+AG25+AE25+AF25+AD25+AC25+AB25+AA25+Z25+Y25+X25+W25+V25+U25+U25+T25+S25 -> 502552.03 | CE25: =SUM(AU25:CC25)+AT25 -> 390875.89 | CF25: =CD25-CE25 -> 111676.14 | CG25: =CD25-CF25 -> 390875.89 | CH25: ='[6]JACKSON AKPOJARO '!C189*12 -> #REF! | CI25: =200000+(0.2*CH25) -> #REF! | CJ25: =CB25*12 -> 0 | CK25: =SUM(CI25:CJ25) -> #REF! | CL25: =+CH25-CK25 -> #REF! | CN25: =IF((CL25>0),(IF((CL25>300000),(300000*7%),(CL25*7%))),(CH25*1%)) -> #REF! | CO25: =IF((CL25-300000)>0,(IF((CL25>600000),(300000*11%),((CL25-300000)*11%))),("")) -> #REF! | CP25: =IF(((CL25-600000)>0),(IF((CL25>1100000),(500000*15%),((CL25-600000)*15%))),("")) -> #REF! | CQ25: =IF(((CL25-(1100000))>0),(IF((CL25>(1600000)),((500000)*19%),((CL25-(1100000))*19%))),("")) -> #REF! | CR25: =IF(((CL25-(1600000))>0),(IF((CL25>(3200000)),((1600000)*21%),((CL25-(1600000))*21%))),("")) -> #REF! | CS25: =IF(((CL25-(3200000))>0),(IF((CL25>(3200000)),((CL25-(3200000))*24%),(0))),("")) -> #REF! | CT25: =1%*CH25 -> #REF! | CU25: =MAX(CT25:CT25) -> #REF! | CV25: =CC25 -> 75156.66
A26: 349 | B26: GARRIE VIVIAN ENIME | C26: REGISTRY | D26: SENIOR ASSISTANT REGISTRAR | E26: FIRST | F26: 3061017477 | G26: CONTISS 11/3 | I26: FIRST | J26: 3061017477 | K26: 22261410235 | L26: 2022036 | M26: =S26-#REF! -> #REF! | N26: 2214985 | O26: 184582.08 | Q26: 46145.521 | R26: 30000 | S26: 269850.67 | AB26: 25000 | AC26: 2500 | AJ26: 2500 | AL26: 383.33 | AU26: =S26*0.04 -> 10794.027 | AW26: 2000 | AX26: =S26*0.02 -> 5397.0134 | BO26: 0 | BY26: 2000 | BZ26: 2000 | CA26: =CD26*0.02 -> 5997.0134 | CC26: 37541.58 | CD26: =AR26+AJ26+AH26+AG26+AE26+AF26+AD26+AC26+AB26+AA26+Z26+Y26+X26+W26+V26+U26+U26+T26+S26 -> 299850.67 | CE26: =SUM(AU26:CC26)+AT26 -> 65729.634 | CF26: =CD26-CE26 -> 234121.04 | CG26: =CD26-CF26 -> 65729.634 | CH26: ='[6]JACKSON AKPOJARO '!C190*12 -> #REF! | CI26: =200000+(0.2*CH26) -> #REF! | CJ26: =CB26*12 -> 0 | CK26: =SUM(CI26:CJ26) -> #REF! | CL26: =+CH26-CK26 -> #REF! | CN26: =IF((CL26>0),(IF((CL26>300000),(300000*7%),(CL26*7%))),(CH26*1%)) -> #REF! | CO26: =IF((CL26-300000)>0,(IF((CL26>600000),(300000*11%),((CL26-300000)*11%))),("")) -> #REF! | CP26: =IF(((CL26-600000)>0),(IF((CL26>1100000),(500000*15%),((CL26-600000)*15%))),("")) -> #REF! | CQ26: =IF(((CL26-(1100000))>0),(IF((CL26>(1600000)),((500000)*19%),((CL26-(1100000))*19%))),("")) -> #REF! | CR26: =IF(((CL26-(1600000))>0),(IF((CL26>(3200000)),((1600000)*21%),((CL26-(1600000))*21%))),("")) -> #REF! | CS26: =IF(((CL26-(3200000))>0),(IF((CL26>(3200000)),((CL26-(3200000))*24%),(0))),("")) -> #REF! | CT26: =1%*CH26 -> #REF! | CU26: =MAX(CT26:CT26) -> #REF! | CV26: =CC26 -> 37541.58
A27: 350 | B27: ALVIN O FORTETA | C27: ICT | D27: ICT TECH | E27: GTB | F27: 0027193142 | G27: CONTISS 13/9 | I27: GTB | J27: 0027193142 | K27: ='[5] NON-TEACHING STAFF'!$J$33 -> 22202025092 | L27: 4025741 | M27: =S27-#REF! -> #REF! | N27: 4025741 | O27: 335478.42 | Q27: 83869.604 | R27: 30000 | S27: =SUM(O27:R27) -> 449348.02 | AA27: =S27*0.35/3 -> 52423.936 | AC27: 2500 | AJ27: 2500 | AL27: 383.33 | AU27: =S27*0.04 -> 17973.921 | AX27: =S27*0.02 -> 8986.9604 | BO27: 116667 | BZ27: 3500 | CA27: =CD27*0.02 -> 10135.439 | CC27: 75966.882 | CD27: =AR27+AJ27+AH27+AG27+AE27+AF27+AD27+AC27+AB27+AA27+Z27+Y27+X27+W27+V27+U27+U27+T27+S27 -> 506771.96 | CE27: =SUM(AU27:CC27)+AT27 -> 233230.2 | CF27: =CD27-CE27 -> 273541.75 | CG27: =CD27-CF27 -> 233230.2 | CH27: ='[6]JACKSON AKPOJARO '!C191*12 -> #REF! | CI27: =200000+(0.2*CH27) -> #REF! | CJ27: =CB27*12 -> 0 | CK27: =SUM(CI27:CJ27) -> #REF! | CL27: =+CH27-CK27 -> #REF! | CN27: =IF((CL27>0),(IF((CL27>300000),(300000*7%),(CL27*7%))),(CH27*1%)) -> #REF! | CO27: =IF((CL27-300000)>0,(IF((CL27>600000),(300000*11%),((CL27-300000)*11%))),("")) -> #REF! | CP27: =IF(((CL27-600000)>0),(IF((CL27>1100000),(500000*15%),((CL27-600000)*15%))),("")) -> #REF! | CQ27: =IF(((CL27-(1100000))>0),(IF((CL27>(1600000)),((500000)*19%),((CL27-(1100000))*19%))),("")) -> #REF! | CR27: =IF(((CL27-(1600000))>0),(IF((CL27>(3200000)),((1600000)*21%),((CL27-(1600000))*21%))),("")) -> #REF! | CS27: =IF(((CL27-(3200000))>0),(IF((CL27>(3200000)),((CL27-(3200000))*24%),(0))),("")) -> #REF! | CT27: =1%*CH27 -> #REF! | CU27: =MAX(CT27:CT27) -> #REF! | CV27: 47322.49
A28: 351 | B28: AKIRO PAUL | C28: WORKS AND SERVICES | D28: HIGHER TRANSPORT SUPERVISOR | E28: UBA | F28: 2052579347 | G28: CONTISS 8/4 | I28: UBA | J28: 2052579347 | L28: 1471351 | M28: =S28-#REF! -> #REF! | N28: 1514130 | O28: 126177.5 | Q28: 31544.375 | R28: 30000 | S28: 197821.33 | AC28: 2500 | AH28: 25000 | AJ28: 2500 | AK28: 2500 | AL28: 2500 | AM28: 2500 | AN28: 2500 | AO28: 2500 | AP28: 2500 | AQ28: 2500 | AU28: =S28*0.04 -> 7912.8532 | AX28: =S28*0.02 -> 3956.4266 | BO28: 97455 | BZ28: 1000 | CA28: =CD28*0.02 -> 4556.4266 | CC28: 25440.65 | CD28: =AR28+AJ28+AH28+AG28+AE28+AF28+AD28+AC28+AB28+AA28+Z28+Y28+X28+W28+V28+U28+U28+T28+S28 -> 227821.33 | CE28: =SUM(AU28:CC28)+AT28 -> 140321.36 | CF28: =CD28-CE28 -> 87499.974 | CG28: =CD28-CF28 -> 140321.36 | CH28: ='[6]JACKSON AKPOJARO '!C193*12 -> #REF! | CI28: =200000+(0.2*CH28) -> #REF! | CJ28: =CB28*12 -> 0 | CK28: =SUM(CI28:CJ28) -> #REF! | CL28: =+CH28-CK28 -> #REF! | CN28: =IF((CL28>0),(IF((CL28>300000),(300000*7%),(CL28*7%))),(CH28*1%)) -> #REF! | CO28: =IF((CL28-300000)>0,(IF((CL28>600000),(300000*11%),((CL28-300000)*11%))),("")) -> #REF! | CP28: =IF(((CL28-600000)>0),(IF((CL28>1100000),(500000*15%),((CL28-600000)*15%))),("")) -> #REF! | CQ28: =IF(((CL28-(1100000))>0),(IF((CL28>(1600000)),((500000)*19%),((CL28-(1100000))*19%))),("")) -> #REF! | CR28: =IF(((CL28-(1600000))>0),(IF((CL28>(3200000)),((1600000)*21%),((CL28-(1600000))*21%))),("")) -> #REF! | CS28: =IF(((CL28-(3200000))>0),(IF((CL28>(3200000)),((CL28-(3200000))*24%),(0))),("")) -> #REF! | CT28: =1%*CH28 -> #REF! | CU28: =MAX(CT28:CT28) -> #REF! | CV28: =CC28 -> 25440.65
A29: 352 | B29: AGBALAKO PATIENCE | C29: WORKS AND SERVICES | D29: OFFICE ATTENDANT LIASSON OFFICE | E29: UBA | F29: 2103764171 | G29: CONTISS 5/11 | I29: UBA | J29: 2103764171 | K29: 22453419020 | L29: 638685 | M29: =S29-#REF! -> #REF! | N29: 656150 | O29: 54679.167 | Q29: 13669.792 | R29: 40000 | S29: 110168.25 | AC29: 2500 | AJ29: 2500 | AK29: 2500 | AL29: 2500 | AM29: 2500 | AN29: 2500 | AO29: 2500 | AP29: 2500 | AQ29: 2500 | AU29: =S29*0.03 -> 3305.0475 | BE29: =S29*0.03 -> 3305.0475 | BO29: 0 | BY29: 1000 | BZ29: =500*2 -> 1000 | CA29: =CD29*0.02 -> 2303.365 | CC29: 8320.19 | CD29: =AR29+AJ29+AH29+AG29+AE29+AF29+AD29+AC29+AB29+AA29+Z29+Y29+X29+W29+V29+U29+U29+T29+S29 -> 115168.25 | CE29: =SUM(AU29:CC29)+AT29 -> 19233.65 | CF29: =CD29-CE29 -> 95934.6 | CG29: =CD29-CF29 -> 19233.65 | CH29: ='[6]JACKSON AKPOJARO '!C194*12 -> #REF! | CI29: =200000+(0.2*CH29) -> #REF! | CJ29: =CB29*12 -> 0 | CK29: =SUM(CI29:CJ29) -> #REF! | CL29: =+CH29-CK29 -> #REF! | CN29: =IF((CL29>0),(IF((CL29>300000),(300000*7%),(CL29*7%))),(CH29*1%)) -> #REF! | CO29: =IF((CL29-300000)>0,(IF((CL29>600000),(300000*11%),((CL29-300000)*11%))),("")) -> #REF! | CP29: =IF(((CL29-600000)>0),(IF((CL29>1100000),(500000*15%),((CL29-600000)*15%))),("")) -> #REF! | CQ29: =IF(((CL29-(1100000))>0),(IF((CL29>(1600000)),((500000)*19%),((CL29-(1100000))*19%))),("")) -> #REF! | CR29: =IF(((CL29-(1600000))>0),(IF((CL29>(3200000)),((1600000)*21%),((CL29-(1600000))*21%))),("")) -> #REF! | CS29: =IF(((CL29-(3200000))>0),(IF((CL29>(3200000)),((CL29-(3200000))*24%),(0))),("")) -> #REF! | CT29: =1%*CH29 -> #REF! | CU29: =MAX(CT29:CT29) -> #REF! | CV29: =CC29 -> 8320.19
A30: 353 | B30: INERITEI TARI WARIPAMO | C30: LAB TECHNOLOGIST | D30: TECHNOLOGIST II | E30: STERING | F30: 0090021740 | G30: CONTISS 9/7 | I30: STERLING | J30: 0090021740 | K30: ='[5] NON-TEACHING STAFF'!$J$37 -> 22261685510 | L30: 1913180 | M30: =S30-#REF! -> #REF! | N30: 1862830 | O30: 163943.92 | Q30: 40985.98 | R30: 30000 | S30: 240628.67 | AC30: 2500 | AE30: 30000 | AJ30: 2500 | AL30: 383.33 | AU30: =S30*0.04 -> 9625.1468 | AX30: =S30*0.02 -> 4812.5734 | AZ30: 1000 | BL30: 15000 | BO30: 85000 | BZ30: 1000 | CA30: =CD30*0.02 -> 5512.5734 | CC30: 33472.28 | CD30: =AR30+AJ30+AH30+AG30+AE30+AF30+AD30+AC30+AB30+AA30+Z30+Y30+X30+W30+V30+U30+U30+T30+S30 -> 275628.67 | CE30: =SUM(AU30:CC30)+AT30 -> 155422.57 | CF30: =CD30-CE30 -> 120206.1 | CG30: =CD30-CF30 -> 155422.57 | CH30: ='[6]JACKSON AKPOJARO '!C195*12 -> #REF! | CI30: =200000+(0.2*CH30) -> #REF! | CJ30: =CB30*12 -> 0 | CK30: =SUM(CI30:CJ30) -> #REF! | CL30: =+CH30-CK30 -> #REF! | CN30: =IF((CL30>0),(IF((CL30>300000),(300000*7%),(CL30*7%))),(CH30*1%)) -> #REF! | CO30: =IF((CL30-300000)>0,(IF((CL30>600000),(300000*11%),((CL30-300000)*11%))),("")) -> #REF! | CP30: =IF(((CL30-600000)>0),(IF((CL30>1100000),(500000*15%),((CL30-600000)*15%))),("")) -> #REF! | CQ30: =IF(((CL30-(1100000))>0),(IF((CL30>(1600000)),((500000)*19%),((CL30-(1100000))*19%))),("")) -> #REF! | CR30: =IF(((CL30-(1600000))>0),(IF((CL30>(3200000)),((1600000)*21%),((CL30-(1600000))*21%))),("")) -> #REF! | CS30: =IF(((CL30-(3200000))>0),(IF((CL30>(3200000)),((CL30-(3200000))*24%),(0))),("")) -> #REF! | CT30: =1%*CH30 -> #REF! | CU30: =MAX(CT30:CT30) -> #REF! | CV30: =CC30 -> 33472.28
A31: 354 | B31: ISAAC BIOGBO | C31: WORKS AND SERVICES | D31: MOTOR DRIVER | E31: STERING | F31: 0075274554 | G31: CONTISS 5/6 | I31: STERING | J31: 0075274554 | L31: 535105 | M31: =S31-#REF! -> #REF! | N31: 535105 | O31: 45786.42 | Q31: 11446.605 | R31: 42499.81 | S31: 101071.92 | AC31: 2500 | AJ31: 2500 | AL31: 383.33 | AU31: =S31*0.03 -> 3032.1576 | BB31: 13890.88 | BE31: =S31*0.03 -> 3032.1576 | BO31: 46666.666 | BZ31: 500 | CA31: =CD31*0.02 -> 2121.4384 | CC31: 7228.83 | CD31: =AR31+AJ31+AH31+AG31+AE31+AF31+AD31+AC31+AB31+AA31+Z31+Y31+X31+W31+V31+U31+U31+T31+S31 -> 106071.92 | CE31: =SUM(AU31:CC31)+AT31 -> 76472.13 | CF31: =CD31-CE31 -> 29599.79 | CG31: =CD31-CF31 -> 76472.13 | CH31: ='[6]JACKSON AKPOJARO '!C196*12 -> #REF! | CI31: =200000+(0.2*CH31) -> #REF! | CJ31: =CB31*12 -> 0 | CK31: =SUM(CI31:CJ31) -> #REF! | CL31: =+CH31-CK31 -> #REF! | CN31: =IF((CL31>0),(IF((CL31>300000),(300000*7%),(CL31*7%))),(CH31*1%)) -> #REF! | CO31: =IF((CL31-300000)>0,(IF((CL31>600000),(300000*11%),((CL31-300000)*11%))),("")) -> #REF! | CP31: =IF(((CL31-600000)>0),(IF((CL31>1100000),(500000*15%),((CL31-600000)*15%))),("")) -> #REF! | CQ31: =IF(((CL31-(1100000))>0),(IF((CL31>(1600000)),((500000)*19%),((CL31-(1100000))*19%))),("")) -> #REF! | CR31: =IF(((CL31-(1600000))>0),(IF((CL31>(3200000)),((1600000)*21%),((CL31-(1600000))*21%))),("")) -> #REF! | CS31: =IF(((CL31-(3200000))>0),(IF((CL31>(3200000)),((CL31-(3200000))*24%),(0))),("")) -> #REF! | CT31: =1%*CH31 -> #REF! | CU31: =MAX(CT31:CT31) -> #REF! | CV31: =CC31 -> 7228.83
